Workbook
Name _1Excel_BuiltIn_Print_Area_2: NA()
Name _4Z_FE2C2EAB_4123_4290_86BA_08E4AC7C24C1_.wvu.Rows_1: ([1]DCF!#REF!,[1]DCF!#REF!,[1]DCF!$18:$19)
Name _4Z_FE2C2EAB_4123_4290_86BA_08E4AC7C24C1_.wvu.Rows_1: ([1]DCF!#REF!,[1]DCF!#REF!,[1]DCF!$18:$19)
Name _4Z_FE2C2EAB_4123_4290_86BA_08E4AC7C24C1_.wvu.Rows_1: ([1]DCF!#REF!,[1]DCF!#REF!,[1]DCF!$18:$19)
Name _4Z_FE2C2EAB_4123_4290_86BA_08E4AC7C24C1_.wvu.Rows_1: ([1]DCF!#REF!,[1]DCF!#REF!,[1]DCF!$18:$19)
Name BC: #REF!
Name BC: #REF!
Name BC: #REF!
Name CF: [2]MHPP!#REF!
Name CF: [2]MHPP!#REF!
Name CF: [2]MHPP!#REF!
Name EMITEN: 'DAFTAR EMITEN 2023'!$B$1:$D$964
Name Jadwal: #REF!
Name Jadwal: #REF!
Name Jadwal: #REF!
Name MULTIPLE: 'PASAR KESEBANDINGAN'!$C$40:$C$44
Name MULTIPLES: 'PASAR KESEBANDINGAN'!$C$40:$N$44
Name PRINT_AREA_MI: NA()
Name RPP: #REF!
Name RPP: #REF!
Name RPP: #REF!
Name RPP: #REF!
Name Slicer_Cash_Flow_Indicator: #N/A
Name Slicer_Leverage_Ratio: #N/A
Name Slicer_Liquidity_Measurement_Ratio: #N/A
Name Slicer_Ratio: #N/A
Name Z_AC236A6A_632A_43B1_B283_C6312913D85E_.wvu.PrintArea: #REF!
Name Z_AC236A6A_632A_43B1_B283_C6312913D85E_.wvu.PrintArea: #REF!
Name Z_AC236A6A_632A_43B1_B283_C6312913D85E_.wvu.PrintArea: #REF!
Name Z_AC236A6A_632A_43B1_B283_C6312913D85E_.wvu.Rows: [1]DCF!#REF!
Name Z_AC236A6A_632A_43B1_B283_C6312913D85E_.wvu.Rows: [1]DCF!#REF!
Name Z_AC236A6A_632A_43B1_B283_C6312913D85E_.wvu.Rows: [1]DCF!#REF!
Name Z_FE2C2EAB_4123_4290_86BA_08E4AC7C24C1_.wvu.PrintArea: #REF!
Name Z_FE2C2EAB_4123_4290_86BA_08E4AC7C24C1_.wvu.PrintArea: #REF!
Name Z_FE2C2EAB_4123_4290_86BA_08E4AC7C24C1_.wvu.PrintArea: #REF!
Name Z_FE2C2EAB_4123_4290_86BA_08E4AC7C24C1_.wvu.Rows: (#REF!,#REF!)
Name Z_FE2C2EAB_4123_4290_86BA_08E4AC7C24C1_.wvu.Rows: (#REF!,#REF!)
Name Z_FE2C2EAB_4123_4290_86BA_08E4AC7C24C1_.wvu.Rows: (#REF!,#REF!)

Sheet CATATAN FINAL
A1: CATATAN FINAL - OVERWRITE WORKBOOK
A2: Sheet ini mendokumentasikan cell yang diubah/update/sesuaikan pada workbook final. Seluruh cell target pada sheet asal diberi font merah.
A3: No. | B3: Timestamp | C3: Sheet | D3: Cell | E3: Before | F3: After | G3: Tujuan Cell | H3: Alasan Perubahan / Judgment | I3: Formula? | J3: Font Merah?
A4: 1 | B4: 2026-04-30 09:30:15 | C4: HOME | D4: B7 | E4: 1610000000 | F4: '=B6 | G4: Jumlah saham dinilai | H4: Valuation objective is 100% equity on controlling, marketable basis. | I4: Ya | J4: Ya
A5: 2 | B5: 2026-04-30 09:30:15 | C5: HOME | D5: B15 | E5: '=DLOM!F34 | F5: '=STAT_ASSUMPTIONS!B15 | G5: DLOM input | H5: DLOM is not applied under final instruction. | I5: Ya | J5: Ya
A6: 3 | B6: 2026-04-30 09:30:15 | C6: HOME | D6: B16 | E6: '='DLOC(PFC)'!E25 | F6: '=STAT_ASSUMPTIONS!B15 | G6: DLOC/PFC input | H6: DLOC/minority/control discount is not applied under final instruction. | I6: Ya | J6: Ya
A7: 4 | B7: 2026-04-30 09:30:15 | C7: BALANCE SHEET | D7: B46 | E7: Current Profit (Laba Usaha Tahun Berjalan 2021) | F7: Current Profit - Commercial NPAT (Laba Bersih Komersial) | G7: Current profit label | H7: Clarifies that earning/current profit basis is commercial, not fiscal. | I7: Tidak | J7: Ya
A8: 5 | B8: 2026-04-30 09:30:15 | C8: BALANCE SHEET | D8: C46 | E8: 619603684 | F8: '='INCOME STATEMENT'!C35 | G8: Retained earnings current profit | H8: Commercial NPAT is used as the current profit reference; fiscal current profit is not earning power. | I8: Ya | J8: Ya
A9: 6 | B9: 2026-04-30 09:30:15 | C9: BALANCE SHEET | D9: D46 | E9: 1205375265 | F9: '='INCOME STATEMENT'!D35 | G9: Retained earnings current profit | H9: Commercial NPAT is used as the current profit reference; fiscal current profit is not earning power. | I9: Ya | J9: Ya
A10: 7 | B10: 2026-04-30 09:30:15 | C10: BALANCE SHEET | D10: E46 | E10: 2590960070 | F10: '='INCOME STATEMENT'!E35 | G10: Retained earnings current profit | H10: Commercial NPAT is used as the current profit reference; fiscal current profit is not earning power. | I10: Ya | J10: Ya
A11: 8 | B11: 2026-04-30 09:30:15 | C11: BALANCE SHEET | D11: C47 | E11: '=+C46+C45 | F11: '=+C46+C45 | G11: Dependent balance/equity output | H11: Formula result changes because current profit basis was corrected to commercial NPAT. | I11: Ya | J11: Ya
A12: 9 | B12: 2026-04-30 09:30:15 | C12: BALANCE SHEET | D12: D47 | E12: '=+D46+D45 | F12: '=+D46+D45 | G12: Dependent balance/equity output | H12: Formula result changes because current profit basis was corrected to commercial NPAT. | I12: Ya | J12: Ya
A13: 10 | B13: 2026-04-30 09:30:15 | C13: BALANCE SHEET | D13: E47 | E13: '=+E46+E45 | F13: '=+E46+E45 | G13: Dependent balance/equity output | H13: Formula result changes because current profit basis was corrected to commercial NPAT. | I13: Ya | J13: Ya
A14: 11 | B14: 2026-04-30 09:30:15 | C14: BALANCE SHEET | D14: C48 | E14: '=+C42+C47+C43 | F14: '=+C42+C47+C43 | G14: Dependent balance/equity output | H14: Formula result changes because current profit basis was corrected to commercial NPAT. | I14: Ya | J14: Ya
A15: 12 | B15: 2026-04-30 09:30:15 | C15: BALANCE SHEET | D15: D48 | E15: '=+D42+D47+D43 | F15: '=+D42+D47+D43 | G15: Dependent balance/equity output | H15: Formula result changes because current profit basis was corrected to commercial NPAT. | I15: Ya | J15: Ya
... A147: 144 | B147: 2026-04-30 09:30:15 | C147: ROIC | D147: F9 | E147: Asumsi ini sesuai dengan Laporan Penilaian Wajib Pajak bahwa Kas dan Deposito adalah Non Operating Asset | F147: Non-operating fixed assets remain zero unless idle assets are specifically identified. | G147: ROIC note | H147: No evidence of idle/non-operating fixed assets was available. | I147: Tidak | J147: Ya
A148: 145 | B148: 2026-04-30 09:30:15 | C148: ROIC | D148: F10 | F148: Cash and bank/deposit treated as excess cash; minimum operating cash remains a judgment sensitivity. | G148: ROIC note | H148: Documents the cash classification judgment directly beside the formula. | I148: Tidak | J148: Ya
A149: 146 | B149: 2026-04-30 09:30:15 | C149: ROIC | D149: B12 | E149: '=SUM(B8:B11) | F149: '=SUM(B8:B11) | G149: ROIC dependent output | H149: Dependent output from corrected excess cash formula. | I149: Ya | J149: Ya
A150: 147 | B150: 2026-04-30 09:30:15 | C150: ROIC | D150: C12 | E150: '=SUM(C8:C11) | F150: '=SUM(C8:C11) | G150: ROIC dependent output | H150: Dependent output from corrected excess cash formula. | I150: Ya | J150: Ya
A151: 148 | B151: 2026-04-30 09:30:15 | C151: ROIC | D151: D12 | E151: '=SUM(D8:D11) | F151: '=SUM(D8:D11) | G151: ROIC dependent output | H151: Dependent output from corrected excess cash formula. | I151: Ya | J151: Ya
A152: 149 | B152: 2026-04-30 09:30:15 | C152: ROIC | D152: C13 | E152: '=B12 | F152: '=B12 | G152: ROIC dependent output | H152: Dependent output from corrected excess cash formula. | I152: Ya | J152: Ya
A153: 150 | B153: 2026-04-30 09:30:15 | C153: ROIC | D153: D13 | E153: '=C12 | F153: '=C12 | G153: ROIC dependent output | H153: Dependent output from corrected excess cash formula. | I153: Ya | J153: Ya
A154: 151 | B154: 2026-04-30 09:30:15 | C154: ROIC | D154: C15 | E154: '=C7/C13 | F154: '=C7/C13 | G154: ROIC dependent output | H154: Dependent output from corrected excess cash formula. | I154: Ya | J154: Ya
A155: 152 | B155: 2026-04-30 09:30:15 | C155: ROIC | D155: D15 | E155: '=D7/D13 | F155: '=D7/D13 | G155: ROIC dependent output | H155: Dependent output from corrected excess cash formula. | I155: Ya | J155: Ya
A156: 153 | B156: 2026-04-30 09:30:15 | C156: EEM | D156: D7 | E156: '=AAM!E16+AAM!E22-(AAM!E29+AAM!E30+AAM!E31+AAM!E36)-AAM!E9 | F156: '='STAT_EEM'!B7 | G156: Net operating tangible asset base | H156: Uses final operating NTA: fixed assets net plus operating NWC. | I156: Ya | J156: Ya
A157: 154 | B157: 2026-04-30 09:30:15 | C157: EEM | D157: C8 | E157: '='BORROWING CAP'!F14 | F157: '='STAT_EEM'!B15 | G157: Return on tangible asset | H157: Uses workbook-derived return on NTA from final EEM assumptions. | I157: Ya | J157: Ya
A158: 155 | B158: 2026-04-30 09:30:15 | C158: EEM | D158: D9 | E158: '=+D7*C8 | F158: '=D7*C8 | G158: Required return on NTA | H158: Required return must be charged against operating tangible assets. | I158: Ya | J158: Ya
A159: 156 | B159: 2026-04-30 09:30:15 | C159: EEM | D159: D12 | E159: '=NOPLAT!E19 | F159: '='STAT_EEM'!B14 | G159: Normalized NOPLAT | H159: Uses commercial EBIT taxed at statutory 22%; no fiscal correction. | I159: Ya | J159: Ya
A160: 157 | B160: 2026-04-30 09:30:15 | C160: EEM | D160: D13 | E160: '='FIXED ASSET'!E51 | F160: '=0 | G160: Depreciation add-back | H160: EEM excess earnings is based on normalized NOPLAT, not historical FCF with 2021 WC release. | I160: Ya | J160: Ya
... A189: 186 | B189: 2026-04-30 09:30:15 | C189: DCF | D189: F5 | E189: '=E5+1 | F189: '=E5+1 | G189: Projection year | H189: Expands DCF explicit period to 2022E-2026E. | I189: Ya | J189: Ya
A190: 187 | B190: 2026-04-30 09:30:15 | C190: DCF | D190: G5 | F190: '=F5+1 | G190: Projection year | H190: Expands DCF explicit period to 2022E-2026E. | I190: Ya | J190: Ya
A191: 188 | B191: 2026-04-30 09:30:15 | C191: DCF | D191: H5 | F191: '=G5+1 | G191: Projection year | H191: Expands DCF explicit period to 2022E-2026E. | I191: Ya | J191: Ya
A192: 189 | B192: 2026-04-30 09:30:15 | C192: DCF | D192: A12 | E192: (Increase) Decrease in Current Asset | F192: Less: Change in Operating NWC | G192: DCF working capital label | H192: DCF uses operating NWC change from final STAT_DCF model. | I192: Tidak | J192: Ya
A193: 190 | B193: 2026-04-30 09:30:15 | C193: DCF | D193: A13 | E193: Increase (Decrease) in Current Liabilities | F193: Operating WC detail included in row 12 | G193: DCF working capital label | H193: Prevents old current-asset/current-liability wording from implying total current assets/liabilities. | I193: Tidak | J193: Ya
A194: 191 | B194: 2026-04-30 09:30:15 | C194: DCF | D194: C7 | E194: '=NOPLAT!E19 | F194: '=STAT_DCF!B15 | G194: DCF NOPLAT | H194: Uses final commercial statutory 22% NOPLAT. | I194: Ya | J194: Ya
A195: 192 | B195: 2026-04-30 09:30:15 | C195: DCF | D195: C8 | E195: '='FIXED ASSET'!E51 | F195: '=STAT_DCF!B26 | G195: DCF D&A add-back | H195: Uses D&A add-back from final STAT_DCF. | I195: Ya | J195: Ya
A196: 193 | B196: 2026-04-30 09:30:15 | C196: DCF | D196: C9 | E196: '=+C7+C8 | F196: '=C7+C8 | G196: DCF gross cash flow | H196: Formula subtotal from final NOPLAT and D&A. | I196: Ya | J196: Ya
A197: 194 | B197: 2026-04-30 09:30:15 | C197: DCF | D197: C12 | E197: '='CASH FLOW STATEMENT'!E8 | F197: '=0 | G197: Base-period NWC change | H197: No base-period NWC change in valuation cash-flow projection. | I197: Ya | J197: Ya
A198: 195 | B198: 2026-04-30 09:30:15 | C198: DCF | D198: C13 | E198: '='CASH FLOW STATEMENT'!E9 | F198: '=0 | G198: DCF operating WC detail placeholder | H198: Operating WC movement is consolidated in row 12. | I198: Ya | J198: Ya
A199: 196 | B199: 2026-04-30 09:30:15 | C199: DCF | D199: C14 | E199: '='CASH FLOW STATEMENT'!E10 | F199: '=SUM(C12:C13) | G199: DCF total NWC cash-flow effect | H199: Keeps the original subtotal structure. | I199: Ya | J199: Ya
A200: 197 | B200: 2026-04-30 09:30:15 | C200: DCF | D200: C16 | E200: '='FIXED ASSET'!E23*-1 | F200: '=-STAT_DCF!B27 | G200: DCF maintenance capex | H200: Maintenance capex equals depreciation in final model. | I200: Ya | J200: Ya
A201: 198 | B201: 2026-04-30 09:30:15 | C201: DCF | D201: C18 | E201: '=+C14+C16 | F201: '=C14+C16 | G201: DCF gross investment | H201: Operating NWC effect plus maintenance capex. | I201: Ya | J201: Ya
A202: 199 | B202: 2026-04-30 09:30:15 | C202: DCF | D202: C20 | E202: '=+C9+C18 | F202: '=C9+C18 | G202: DCF free cash flow | H202: Final FCFF by year. | I202: Ya | J202: Ya
A203: 200 | B203: 2026-04-30 09:30:15 | C203: DCF | D203: D7 | E203: '='PROY NOPLAT'!D19 | F203: '=STAT_DCF!C15 | G203: DCF NOPLAT | H203: Uses final commercial statutory 22% NOPLAT. | I203: Ya | J203: Ya
... A229: 226 | B229: 2026-04-30 09:30:15 | C229: DCF | D229: F20 | E229: '=+F9+F18 | F229: '=F9+F18 | G229: DCF free cash flow | H229: Final FCFF by year. | I229: Ya | J229: Ya
A230: 227 | B230: 2026-04-30 09:30:15 | C230: DCF | D230: G7 | F230: '=STAT_DCF!F15 | G230: DCF NOPLAT | H230: Uses final commercial statutory 22% NOPLAT. | I230: Ya | J230: Ya
A231: 228 | B231: 2026-04-30 09:30:15 | C231: DCF | D231: G8 | F231: '=STAT_DCF!F26 | G231: DCF D&A add-back | H231: Uses D&A add-back from final STAT_DCF. | I231: Ya | J231: Ya
A232: 229 | B232: 2026-04-30 09:30:15 | C232: DCF | D232: G9 | F232: '=G7+G8 | G232: DCF gross cash flow | H232: Formula subtotal from final NOPLAT and D&A. | I232: Ya | J232: Ya
A233: 230 | B233: 2026-04-30 09:30:15 | C233: DCF | D233: G12 | F233: '=-STAT_DCF!F25 | G233: DCF change in operating NWC | H233: FCFF subtracts change in operating NWC. | I233: Ya | J233: Ya
A234: 231 | B234: 2026-04-30 09:30:15 | C234: DCF | D234: G13 | F234: '=0 | G234: DCF operating WC detail placeholder | H234: Operating WC movement is consolidated in row 12. | I234: Ya | J234: Ya
A235: 232 | B235: 2026-04-30 09:30:15 | C235: DCF | D235: G14 | F235: '=SUM(G12:G13) | G235: DCF total NWC cash-flow effect | H235: Keeps the original subtotal structure. | I235: Ya | J235: Ya
A236: 233 | B236: 2026-04-30 09:30:15 | C236: DCF | D236: G16 | F236: '=-STAT_DCF!F27 | G236: DCF maintenance capex | H236: Maintenance capex equals depreciation in final model. | I236: Ya | J236: Ya
A237: 234 | B237: 2026-04-30 09:30:15 | C237: DCF | D237: G18 | F237: '=G14+G16 | G237: DCF gross investment | H237: Operating NWC effect plus maintenance capex. | I237: Ya | J237: Ya
A238: 235 | B238: 2026-04-30 09:30:15 | C238: DCF | D238: G20 | F238: '=G9+G18 | G238: DCF free cash flow | H238: Final FCFF by year. | I238: Ya | J238: Ya
A239: 236 | B239: 2026-04-30 09:30:15 | C239: DCF | D239: H7 | F239: '=STAT_DCF!G15 | G239: DCF NOPLAT | H239: Uses final commercial statutory 22% NOPLAT. | I239: Ya | J239: Ya
A240: 237 | B240: 2026-04-30 09:30:15 | C240: DCF | D240: H8 | F240: '=STAT_DCF!G26 | G240: DCF D&A add-back | H240: Uses D&A add-back from final STAT_DCF. | I240: Ya | J240: Ya
A241: 238 | B241: 2026-04-30 09:30:15 | C241: DCF | D241: H9 | F241: '=H7+H8 | G241: DCF gross cash flow | H241: Formula subtotal from final NOPLAT and D&A. | I241: Ya | J241: Ya
... A247: 244 | B247: 2026-04-30 09:30:15 | C247: DCF | D247: H20 | F247: '=H9+H18 | G247: DCF free cash flow | H247: Final FCFF by year. | I247: Ya | J247: Ya
A248: 245 | B248: 2026-04-30 09:30:15 | C248: DCF | D248: D22 | E248: '=YEARFRAC($C$6,$D$6) | F248: 1 | G248: DCF period index | H248: Five-year explicit forecast period. | I248: Tidak | J248: Ya
A249: 246 | B249: 2026-04-30 09:30:15 | C249: DCF | D249: D23 | E249: '=1/((1+$B$23)^D22) | F249: '=1/((1+$B$23)^D22) | G249: DCF discount factor | H249: Discount factor using source WACC. | I249: Ya | J249: Ya
A250: 247 | B250: 2026-04-30 09:30:15 | C250: DCF | D250: D24 | E250: '=D20*D23 | F250: '=D20*D23 | G250: PV of free cash flow | H250: Present value of final FCFF. | I250: Ya | J250: Ya
A251: 248 | B251: 2026-04-30 09:30:15 | C251: DCF | D251: E22 | E251: '=D22+1 | F251: 2 | G251: DCF period index | H251: Five-year explicit forecast period. | I251: Tidak | J251: Ya
A252: 249 | B252: 2026-04-30 09:30:15 | C252: DCF | D252: E23 | E252: '=1/((1+$B$23)^E22) | F252: '=1/((1+$B$23)^E22) | G252: DCF discount factor | H252: Discount factor using source WACC. | I252: Ya | J252: Ya
A253: 250 | B253: 2026-04-30 09:30:15 | C253: DCF | D253: E24 | E253: '=E20*E23 | F253: '=E20*E23 | G253: PV of free cash flow | H253: Present value of final FCFF. | I253: Ya | J253: Ya
A254: 251 | B254: 2026-04-30 09:30:15 | C254: DCF | D254: F22 | E254: '=E22+1 | F254: 3 | G254: DCF period index | H254: Five-year explicit forecast period. | I254: Tidak | J254: Ya
A255: 252 | B255: 2026-04-30 09:30:15 | C255: DCF | D255: F23 | E255: '=1/((1+$B$23)^F22) | F255: '=1/((1+$B$23)^F22) | G255: DCF discount factor | H255: Discount factor using source WACC. | I255: Ya | J255: Ya
A256: 253 | B256: 2026-04-30 09:30:15 | C256: DCF | D256: F24 | E256: '=F20*F23 | F256: '=F20*F23 | G256: PV of free cash flow | H256: Present value of final FCFF. | I256: Ya | J256: Ya
A257: 254 | B257: 2026-04-30 09:30:15 | C257: DCF | D257: G22 | F257: 4 | G257: DCF period index | H257: Five-year explicit forecast period. | I257: Tidak | J257: Ya
A258: 255 | B258: 2026-04-30 09:30:15 | C258: DCF | D258: G23 | F258: '=1/((1+$B$23)^G22) | G258: DCF discount factor | H258: Discount factor using source WACC. | I258: Ya | J258: Ya
A259: 256 | B259: 2026-04-30 09:30:15 | C259: DCF | D259: G24 | F259: '=G20*G23 | G259: PV of free cash flow | H259: Present value of final FCFF. | I259: Ya | J259: Ya
A260: 257 | B260: 2026-04-30 09:30:15 | C260: DCF | D260: H22 | F260: 5 | G260: DCF period index | H260: Five-year explicit forecast period. | I260: Tidak | J260: Ya
A261: 258 | B261: 2026-04-30 09:30:15 | C261: DCF | D261: H23 | F261: '=1/((1+$B$23)^H22) | G261: DCF discount factor | H261: Discount factor using source WACC. | I261: Ya | J261: Ya
A262: 259 | B262: 2026-04-30 09:30:15 | C262: DCF | D262: H24 | F262: '=H20*H23 | G262: PV of free cash flow | H262: Present value of final FCFF. | I262: Ya | J262: Ya
A263: 260 | B263: 2026-04-30 09:30:15 | C263: DCF | D263: B23 | E263: '='DISCOUNT RATE'!H10 | F263: '=STAT_ASSUMPTIONS!B6 | G263: DCF WACC | H263: Uses source WACC as base discount rate. | I263: Ya | J263: Ya
A264: 261 | B264: 2026-04-30 09:30:15 | C264: DCF | D264: C25 | E264: '=SUM(D24:F24) | F264: '=SUM(D24:H24) | G264: PV explicit FCF | H264: Sums 2022E-2026E present values. | I264: Ya | J264: Ya
A265: 262 | B265: 2026-04-30 09:30:15 | C265: DCF | D265: B26 | E265: '='GROWTH RATE'!C14 | F265: '=STAT_ASSUMPTIONS!B8 | G265: Terminal growth | H265: Base case terminal growth is 0%. | I265: Ya | J265: Ya
A266: 263 | B266: 2026-04-30 09:30:15 | C266: DCF | D266: C27 | E266: '=F20*((1+B26)/(B23-B26)) | F266: '=H20*((1+B26)/(B23-B26)) | G266: Terminal value | H266: Terminal value based on 2026E FCFF. | I266: Ya | J266: Ya
A267: 264 | B267: 2026-04-30 09:30:15 | C267: DCF | D267: C28 | E267: '=C27*F23 | F267: '=C27*H23 | G267: PV terminal value | H267: Discounts terminal value to valuation date. | I267: Ya | J267: Ya
A268: 265 | B268: 2026-04-30 09:30:15 | C268: DCF | D268: C29 | E268: '=C25+C28 | F268: '=C25+C28 | G268: Enterprise value | H268: Explicit PV plus terminal PV. | I268: Ya | J268: Ya
A269: 266 | B269: 2026-04-30 09:30:15 | C269: DCF | D269: C30 | E269: '=('BALANCE SHEET'!E30+'BALANCE SHEET'!E37)*-1 | F269: '=-STAT_DCF!B38 | G269: Interest-bearing debt | H269: Subtracts interest-bearing debt; current debt is zero. | I269: Ya | J269: Ya
A270: 267 | B270: 2026-04-30 09:30:15 | C270: DCF | D270: C31 | E270: '=ROIC!D10*-1 | F270: '=STAT_DCF!B37 | G270: Surplus asset cash | H270: Adds cash, bank/deposit, and employee receivable as non-operating assets. | I270: Ya | J270: Ya
A271: 268 | B271: 2026-04-30 09:30:15 | C271: DCF | D271: C32 | E271: '=ROIC!D9*-1 | F271: '=0 | G271: Non-operating fixed assets | H271: No idle/non-operating fixed assets identified. | I271: Ya | J271: Ya
A272: 269 | B272: 2026-04-30 09:30:15 | C272: DCF | D272: C33 | E272: '=SUM(C29:C32) | F272: '=SUM(C29:C32) | G272: Equity Value 100% - DCF | H272: Final DCF equity value before discounts, with corrected surplus asset bridge. | I272: Ya | J272: Ya
A273: 270 | B273: 2026-04-30 09:30:15 | C273: DCF | D273: B34 | E273: '=HOME!B15*-1 | F273: '=0 | G273: DLOM | H273: No DLOM applied. | I273: Ya | J273: Ya
A274: 271 | B274: 2026-04-30 09:30:15 | C274: DCF | D274: C34 | E274: '=C33*B34 | F274: '=C33*B34 | G274: DLOM amount | H274: No DLOM applied. | I274: Ya | J274: Ya
... A293: 290 | B293: 2026-04-30 09:30:15 | C293: AAM | D293: E59 | E293: '=+E57*D58 | F293: '=E57*D58 | G293: Market value 100% equity | H293: D58 is locked to 100%. | I293: Ya | J293: Ya
A294: 291 | B294: 2026-04-30 09:30:15 | C294: AAM | D294: A60 | F294: Value per share | G294: AAM per-share label | H294: Adds useful per-share reference from 100% equity value. | I294: Tidak | J294: Ya
A295: 292 | B295: 2026-04-30 09:30:15 | C295: AAM | D295: E60 | E295: '=E59-HOME!B7 | F295: '=E59/HOME!B6 | G295: Value per share | H295: Corrects prior nonsensical subtraction formula and divides 100% equity by total shares. | I295: Ya | J295: Ya
A296: 293 | B296: 2026-04-30 09:30:15 | C296: FINAL_SOURCE_BRIDGE | D296: A1 | E296: Source Workbook Treatment vs Final Review | F296: Pre-Overwrite Source Treatment vs Final Review | G296: Source bridge title | H296: Clarifies that this diagnostic table describes the source workbook before this overwrite pass. | I296: Tidak | J296: Ya
A297: 294 | B297: 2026-04-30 09:30:15 | C297: FINAL_SOURCE_BRIDGE | D297: B2 | E297: Source Workbook Formula / Logic | F297: Pre-Overwrite Source Formula / Logic | G297: Source bridge header | H297: Avoids ambiguity after formulas in source sheets are overwritten. | I297: Tidak | J297: Ya
A298: 295 | B298: 2026-04-30 09:30:15 | C298: FINAL_SOURCE_BRIDGE | D298: C2 | E298: Source Amount | F298: Pre-Overwrite Source Amount | G298: Source bridge header | H298: Avoids ambiguity after formulas in source sheets are overwritten. | I298: Tidak | J298: Ya
A299: 296 | B299: 2026-04-30 09:30:15 | C299: STAT_SUMMARY | D299: B6 | E299: Existing Workbook Pre-Discount | F299: Overwritten Source Model | G299: Summary header | H299: The source method sheets have now been overwritten to final treatment. | I299: Tidak | J299: Ya
A300: 297 | B300: 2026-04-30 09:30:15 | C300: STAT_SUMMARY | D300: B7 | E300: '=AAM!E53 | F300: '=AAM!E53 | G300: AAM source model indication | H300: AAM source sheet now uses no DLOM/DLOC and 100% basis. | I300: Ya | J300: Ya
A301: 298 | B301: 2026-04-30 09:30:15 | C301: STAT_SUMMARY | D301: B8 | E301: '=EEM!D34 | F301: '=EEM!D34 | G301: EEM source model indication | H301: EEM source sheet now uses final commercial statutory 22% treatment. | I301: Ya | J301: Ya
A302: 299 | B302: 2026-04-30 09:30:15 | C302: STAT_SUMMARY | D302: B9 | E302: '=DCF!C33 | F302: '=DCF!C33 | G302: DCF source model indication | H302: DCF source sheet now uses final five-year FCFF treatment. | I302: Ya | J302: Ya
A303: 300 | B303: 2026-04-30 09:33:11 | C303: FIXED ASSET | D303: H73 | E303: '=#REF! | F303: '=H72 | G303: Nilai tanggungan tanah | H303: Inherited #REF! repaired conservatively by equating nilai tanggungan to carrying land value, so adjustment tanah is zero absent independent collateral/appraisal data. | I303: Ya | J303: Ya
A304: 301 | B304: 2026-04-30 09:33:11 | C304: BALANCE SHEET | D304: M8 | E304: '=IFERROR((C8-#REF!)/#REF!,0) | F304: '=0 | G304: First historical horizontal growth | H304: Inherited #REF! in first-period growth formula repaired to zero because there is no prior comparative year in the workbook. | I304: Ya | J304: Ya
A305: 302 | B305: 2026-04-30 09:33:11 | C305: BALANCE SHEET | D305: M9 | E305: '=IFERROR((C9-#REF!)/#REF!,0) | F305: '=0 | G305: First historical horizontal growth | H305: Inherited #REF! in first-period growth formula repaired to zero because there is no prior comparative year in the workbook. | I305: Ya | J305: Ya
A306: 303 | B306: 2026-04-30 09:33:11 | C306: BALANCE SHEET | D306: M10 | E306: '=IFERROR((C10-#REF!)/#REF!,0) | F306: '=0 | G306: First historical horizontal growth | H306: Inherited #REF! in first-period growth formula repaired to zero because there is no prior comparative year in the workbook. | I306: Ya | J306: Ya
... A331: 328 | B331: 2026-04-30 09:33:11 | C331: PASAR PEMBANDING_ | D331: E3 | E331: '='PASAR KESEBANDINGAN'!#REF! | F331: '='PASAR KESEBANDINGAN'!N39 | G331: Selected comparable header | H331: Inherited #REF! repaired by linking to selected comparable ticker in PASAR KESEBANDINGAN. | I331: Ya | J331: Ya

Sheet HOME
A1: KERTAS KERJA PENILAIAN BISNIS
A4: Nama Objek Pajak | B4: Makmur Jaya Sejati Raya
A5: NPWP Objek Pajak | B5: 211437892119000
A6: Sektor Perusahaan | B6: Consumer Cyclicals | D6: Basic Materials | E6: Orang Pribadi
A7: Jenis Perusahaan | B7: Tertutup | D7: Consumer Cyclicals | E7: Badan
A9: Nama Subjek Pajak | B9: Helga | D9: Consumer Non-Cyclicals
A10: NPWP Subjek Pajak | B10: 211437892119000 | D10: Energy | E10: Lembar Saham
A11: Jenis Subjek Pajak | B11: Orang Pribadi | E11: Modal Disetor
A12: Jenis Kepemilikan Saham | B12: Minoritas
A14: Jenis Peralihan yang Diketahui | B14: Modal Disetor
A15: =IF(B14="Modal Disetor","Jumlah Modal Disetor 100%","Jumlah Saham Beredar 100%") -> Jumlah Modal Disetor 100% | B15: 5280000000 | D15: Financials | E15: Saham
A16: =IF(B14="Modal Disetor","Jumlah Modal Disetor yang Dinilai","Jumlah Saham yang Dinilai") -> Jumlah Modal Disetor yang Dinilai | B16: 1600000000 | D16: Healthcare | E16: Bisnis
A17: =IF(B14="Modal Disetor","Proporsi Modal Disetor yang Dinilai","Proporsi Saham yang Dinilai") -> Proporsi Modal Disetor yang Dinilai | B17: =IF(B16/B15>100%,"Data Tidak Valid",IF(B16/B15<=0,"Data Tidak Valid",B16/B15)) -> 0.3030303 | D17: Industrials
A19: Tahun Transaksi Pengalihan | B19: 2022 | D19: Infrastructures
A20: Cut off Date | B20: =DATE(B19-1, 12, 31) -> 44561 | D20: Properties & Real Estate
A21: Akhir Periode Proyeksi Pertama | B21: =DATE(B19, 12, 31) -> 44926 | D21: Transportation & Logistic
A22: Objek Penilaian | B22: Saham | D22: Technology
A24: Tahun Pengalihan | B24: =YEAR(B20) -> 2021 | D24: Tertutup
A25: DISCOUNT LACK OF MARKETABILITY | B25: =STAT_ASSUMPTIONS!B15 -> 0 | D25: Terbuka (Tbk)
A26: DISCOUNT LACK OF CONTROL/PREMIUM FOR CONTROL | B26: =STAT_ASSUMPTIONS!B15 -> 0
A28: LAPORAN KEUANGAN HISTORIS | B28: PERTIMBANGAN | C28: PROYEKSI | D28: PENDEKATAN PENILAIAN | E28: KESIMPULAN

Sheet DAFTAR EMITEN 2023
A1: 1 | B1: AADI | C1: PT Adaro Andalan Indonesia Tbk | D1: 05 Des 2024
A2: 2 | B2: AALI | C2: Astra Agro Lestari Tbk | D2: 09 Des 1997
A3: 3 | B3: ABBA | C3: Mahaka Media Tbk | D3: 37349
A4: 4 | B4: ABDA | C4: Asuransi Bina Dana Arta Tbk | D4: 32695
A5: 5 | B5: ABMM | C5: ABM Investama Tbk | D5: 06 Des 2011
A6: 6 | B6: ACES | C6: PT Aspirasi Hidup Indonesia Tbk | D6: 39392
A7: 7 | B7: ACRO | C7: PT Samcro Hyosung Adilestari Tbk. | D7: 45302
A8: 8 | B8: ACST | C8: PT Acset Indonusa Tbk. | D8: 41449
A9: 9 | B9: ADCP | C9: PT Adhi Commuter Properti Tbk | D9: 21 Mei 2021
A10: 10 | B10: ADES | C10: Akasha Wira International Tbk Tbk | D10: 34498
A11: 11 | B11: ADHI | C11: PT Adhi Karya (Persero) Tbk. | D11: 38064
A12: 12 | B12: ADMF | C12: Adira Dinamika Multi Finance Tbk | D12: 38077
A13: 13 | B13: ADMG | C13: Polychem Indonesia Tbk | D13: 20 Okt 1993
A14: 14 | B14: ADMR | C14: PT Alamtri Minerals Indonesia Tbk | D14: 44564
A15: 15 | B15: ADRO | C15: Alamtri Resources Indonesia Tbk | D15: 39645
A16: 16 | B16: AEGS | C16: PT Anugerah Spareparts Sejahtera Tbk. | D16: 45180
A17: 17 | B17: AGAR | C17: PT Asia Sejahtera Mina Tbk | D17: 02 Des 2019
A18: 18 | B18: AGII | C18: PT Samator Indo Gas Tbk | D18: 42641
A19: 19 | B19: AGRO | C19: PT Bank Raya Indonesia Tbk | D19: 08 Agt 2003
A20: 20 | B20: AGRS | C20: PT Bank IBK Indonesia Tbk. | D20: 22 Des 2014
A21: 21 | B21: AHAP | C21: Asuransi Harta Aman Pratama Tbk | D21: 33130
A22: 22 | B22: AIMS | C22: PT Artha Mahiya Investama Tbk | D22: 37092
A23: 23 | B23: AISA | C23: PT FKS Food Sejahtera Tbk | D23: 35592
A24: 24 | B24: AKKU | C24: PT Anugerah Kagum Karya Utama Tbk | D24: 38292
A25: 25 | B25: AKPI | C25: Argha Karya Prima Ind. Tbk | D25: 18 Des 1992
A26: 26 | B26: AKRA | C26: PT AKR Corporindo Tbk. | D26: 03 Okt 1994
A27: 27 | B27: AKSI | C27: PT Mineral Sumberdaya Mandiri Tbk | D27: 37085
A28: 28 | B28: ALDO | C28: Alkindo Naratama Tbk | D28: 40736
A29: 29 | B29: ALII | C29: PT Ancara Logistics Indonesia Tbk | D29: 45329
A30: 30 | B30: ALKA | C30: Alakasa Industrindo Tbk | D30: 33066
A31: 31 | B31: ALMI | C31: Alumindo Light Metal Industry Tbk | D31: 35432
A32: 32 | B32: ALTO | C32: Tri Banyan Tirta Tbk | D32: 41100
A33: 33 | B33: AMAG | C33: Asuransi Multi Artha Guna Tbk | D33: 23 Des 2005
A34: 34 | B34: AMAN | C34: PT Makmur Berkah Amanda Tbk. | D34: 43903
A35: 35 | B35: AMAR | C35: PT Bank Amar Indonesia Tbk. | D35: 43839
A36: 36 | B36: AMFG | C36: Asahimas Flat Glass Tbk | D36: 35011
A37: 37 | B37: AMIN | C37: PT Ateliers Mecaniques D Indonesie Tbk. | D37: 10 Des 2015
A38: 38 | B38: AMMN | C38: PT Amman Mineral Internasional Tbk. | D38: 45114
A39: 39 | B39: AMMS | C39: PT Agung Menjangan Mas Tbk | D39: 04 Agt 2022
A40: 40 | B40: AMOR | C40: PT Ashmore Asset Management Indonesia Tbk. | D40: 43844
A41: 41 | B41: AMRT | C41: PT Sumber Alfaria Trijaya Tbk. | D41: 39828
A42: 42 | B42: ANDI | C42: PT Andira Agro Tbk | D42: 16 Agt 2018
A43: 43 | B43: ANJT | C43: PT Austindo Nusantara Jaya Tbk. | D43: 08 Mei 2013
A44: 44 | B44: ANTM | C44: Aneka Tambang Tbk. | D44: 35761
A45: 45 | B45: APEX | C45: Apexindo Pratama Duta Tbk | D45: 41430
A46: 46 | B46: APIC | C46: PACIFIC STRATEGIC FINANCIAL Tbk | D46: 18 Des 2002
A47: 47 | B47: APII | C47: PT Arita Prima Indonesia Tbk. | D47: 29 Okt 2013
A48: 48 | B48: APLI | C48: Asiaplast Industries Tbk | D48: 01 Mei 2000
A49: 49 | B49: APLN | C49: PT Agung Podomoro Land Tbk. | D49: 40493
A50: 50 | B50: ARCI | C50: PT Archi Indonesia Tbk | D50: 44375
A51: 51 | B51: AREA | C51: PT Dunia Virtual Online Tbk | D51: 45383
A52: 52 | B52: ARGO | C52: Argo Pantes Tbk | D52: 33245
A53: 53 | B53: ARII | C53: Atlas Resources Tbk | D53: 40855
A54: 54 | B54: ARKA | C54: PT Arkha Jayanti Persada Tbk. | D54: 43656
A55: 55 | B55: ARKO | C55: PT Arkora Hydro Tbk. | D55: 44750
A56: 56 | B56: ARMY | C56: PT Armidian Karyatama Tbk | D56: 42907
A57: 57 | B57: ARNA | C57: Arwana Citramulia Tbk | D57: 37089
A58: 58 | B58: ARTA | C58: Arthavest Tbk | D58: 37565
A59: 59 | B59: ARTI | C59: Ratu Prabu Energi Tbk | D59: 37741
A60: 60 | B60: ARTO | C60: PT Bank Jago Tbk. | D60: 42381
A61: 61 | B61: ASBI | C61: Asuransi Bintang Tbk | D61: 32841
A62: 62 | B62: ASDM | C62: Asuransi Dayin Mitra Tbk | D62: 15 Des 1989
A63: 63 | B63: ASGR | C63: Astra Graphia Tbk | D63: 32827
A64: 64 | B64: ASHA | C64: PT Cilacap Samudera Fishing Industry Tbk | D64: 27 Mei 2022
A65: 65 | B65: ASII | C65: Astra International Tbk | D65: 32967
A66: 66 | B66: ASJT | C66: Asuransi Jasa Tania Tbk | D66: 23 Des 2003
A67: 67 | B67: ASLC | C67: PT Autopedia Sukses Lestari Tbk | D67: 44586
A68: 68 | B68: ASLI | C68: PT Asri Karya Lestari Tbk. | D68: 45296
A69: 69 | B69: ASMI | C69: PT Asuransi Maximus Graha Persada Tbk. | D69: 41655
A70: 70 | B70: ASPI | C70: PT Andalan Sakti Primaindo Tbk. | D70: 43878
A71: 71 | B71: ASPR | C71: PT Asia Pramulia Tbk | D71: 45846
A72: 72 | B72: ASRI | C72: ALAM SUTERA REALTY Tbk | D72: 18 Des 2007
A73: 73 | B73: ASRM | C73: Asuransi Ramayana Tbk | D73: 32951
A74: 74 | B74: ASSA | C74: Adi Sarana Armada Tbk | D74: 41225
A75: 75 | B75: ATAP | C75: PT Trimitra Prawara Goldland Tbk | D75: 11 Des 2020
A76: 76 | B76: ATIC | C76: PT Anabatic Technologies Tbk | D76: 42193
A77: 77 | B77: ATLA | C77: PT Atlantis Subsea Indonesia Tbk | D77: 45398
A78: 78 | B78: AUTO | C78: Astra Otoparts Tbk | D78: 35961
A79: 79 | B79: AVIA | C79: PT Avia Avian Tbk | D79: 08 Des 2021
A80: 80 | B80: AWAN | C80: PT Era Digital Media Tbk | D80: 45034
A81: 81 | B81: AXIO | C81: PT Tera Data Indonusa Tbk | D81: 44762
A82: 82 | B82: AYAM | C82: PT Janu Putra Sejahtera Tbk. | D82: 45260
A83: 83 | B83: AYLS | C83: PT Agro Yasa Lestari Tbk | D83: 43873
A84: 84 | B84: BABP | C84: PT Bank MNC Internasional Tbk. | D84: 37452
A85: 85 | B85: BABY | C85: PT Multitrend Indo Tbk. | D85: 45176
A86: 86 | B86: BACA | C86: PT Bank Capital Indonesia Tbk | D86: 04 Okt 2007
A87: 87 | B87: BAIK | C87: PT Bersama Mencapai Puncak Tbk. | D87: 45337
A88: 88 | B88: BAJA | C88: Saranacentral Bajatama Tbk | D88: 21 Des 2011
A89: 89 | B89: BALI | C89: PT Bali Towerindo Sentra Tbk. | D89: 41711
A90: 90 | B90: BANK | C90: PT Bank Aladin Syariah Tbk | D90: 44228
A91: 91 | B91: BAPA | C91: Bekasi Asri Pemula Tbk | D91: 39461
A92: 92 | B92: BAPI | C92: PT Bhakti Agung Propertindo Tbk. | D92: 43724
A93: 93 | B93: BATA | C93: Sepatu Bata Tbk | D93: 30034
A94: 94 | B94: BATR | C94: PT Benteng Api Technic Tbk | D94: 45453
A95: 95 | B95: BAUT | C95: PT Mitra Angkasa Sejahtera Tbk | D95: 44589
A96: 96 | B96: BAYU | C96: Bayu Buana Tbk | D96: 30 Okt 1989
A97: 97 | B97: BBCA | C97: PT Bank Central Asia Tbk. | D97: 31 Mei 2000
A98: 98 | B98: BBHI | C98: PT Allo Bank Indonesia Tbk | D98: 12 Agt 2015
A99: 99 | B99: BBKP | C99: PT Bank KB Bukopin Tbk | D99: 38908
A100: 100 | B100: BBLD | C100: Buana Finance Tbk | D100: 07 Mei 1990
...

Sheet FIXED ASSET
A1: ='INCOME STATEMENT'!A1 -> Makmur Jaya Sejati Raya
A2: Fixed Asset Schedules
A3: ='[3]BALANCE SHEET'!A3 -> (IDR)
C5: ='BALANCE SHEET'!C4 -> 2019 | D5: =C5+1 -> 2020 | E5: =D5+1 -> 2021
A6: A. Acquisition Costs
A7: Beginning
B8: Land (Tanah Lahan Sawit + Tanah Lahan Sawit (TA)) | C8: =1267580000+3184183925 -> 4451763925 | D8: =C26 -> 7817274315 | E8: =D26 -> 7817274315 | F8: =4633090390+3184183925 -> 7817274315 | H8: Isinya Rumus
B9: Building (Bangunan Mess/Barak + Bangunan Mess/Barak (TA) + Lapangan + Kantor) | C9: =200592860+105000000+131056000+104864091 -> 541512951 | D9: =C27 -> 651512951 | E9: =D27 -> 653687951 | F9: =310592860+105000000+131056000+107039091 -> 653687951
B10: Equipment, Laboratory, & Machinery (Sarana & Prasarana) | C10: 176449500 | D10: =C28 -> 176449500 | E10: =D28 -> 176449500
B11: Vehicle & Heavy Equipment (Alat Berat + Kendaraan) | C11: =350000000+1435472728 -> 1785472728 | D11: =C29 -> 2060472728 | E11: =D29 -> 2207972728 | F11: =625000000+1582972728 -> 2207972728
B12: Office Inventory (Inventaris Tanaman Sawit + Inventaris Tanaman Sawit (TA)) | C12: =1720800000+2000000000 -> 3720800000 | D12: =C30 -> 10145509610 | E12: =D30 -> 10145509610 | F12: =8145509610+2000000000 -> 10145509610
B13: Electrical | C13: 0 | D13: =C31 -> 0 | E13: =D31 -> 0
A14: Total | C14: =SUM(C8:C13) -> 10675999104 | D14: =SUM(D8:D13) -> 20851219104 | E14: =SUM(E8:E13) -> 21000894104
A16: Additions | G16: =$D$5 -> 2020 | H16: =$E$5 -> 2021 | I16: AVERAGE
B17: Land (Tanah Lahan Sawit + Tanah Lahan Sawit (TA)) | C17: 3365510390 | D17: 0 | E17: 0 | G17: =IFERROR((D17-C17)/C17,0) -> -1 | H17: =IFERROR((E17-D17)/D17,0) -> 0 | I17: =AVERAGE(G17:H17) -> -0.5
B18: Building (Bangunan Mess/Barak + Bangunan Mess/Barak (TA) + Lapangan + Kantor) | C18: 110000000 | D18: 2175000 | E18: 0 | G18: =IFERROR((D18-C18)/C18,0) -> -0.98022727 | H18: =IFERROR((E18-D18)/D18,0) -> -1 | I18: =AVERAGE(G18:H18) -> -0.99011364
B19: Equipment, Laboratory, & Machinery (Sarana & Prasarana) | C19: 0 | D19: 0 | E19: 0 | G19: =IFERROR((D19-C19)/C19,0) -> 0 | H19: =IFERROR((E19-D19)/D19,0) -> 0 | I19: =AVERAGE(G19:H19) -> 0
B20: Vehicle & Heavy Equipment (Alat Berat + Kendaraan) | C20: 275000000 | D20: 147500000 | E20: 0 | G20: =IFERROR((D20-C20)/C20,0) -> -0.46363636 | H20: =IFERROR((E20-D20)/D20,0) -> -1 | I20: =AVERAGE(G20:H20) -> -0.73181818
B21: Office Inventory (Inventaris Tanaman Sawit + Inventaris Tanaman Sawit (TA)) | C21: 6424709610 | D21: 0 | E21: 0 | G21: =IFERROR((D21-C21)/C21,0) -> -1 | H21: =IFERROR((E21-D21)/D21,0) -> 0 | I21: =AVERAGE(G21:H21) -> -0.5
B22: Electrical | C22: 0 | D22: 0 | E22: 0 | G22: =IFERROR((D22-C22)/C22,0) -> 0 | H22: =IFERROR((E22-D22)/D22,0) -> 0 | I22: =AVERAGE(G22:H22) -> 0
A23: Total | C23: =SUM(C17:C22) -> 10175220000 | D23: =SUM(D17:D22) -> 149675000 | E23: =SUM(E17:E22) -> 0
A25: Ending
B26: Land (Tanah Lahan Sawit + Tanah Lahan Sawit (TA)) | C26: =+C8+C17 -> 7817274315 | D26: =+D8+D17 -> 7817274315 | E26: =+E8+E17 -> 7817274315
B27: Building (Bangunan Mess/Barak + Bangunan Mess/Barak (TA) + Lapangan + Kantor) | C27: =+C9+C18 -> 651512951 | D27: =+D9+D18 -> 653687951 | E27: =+E9+E18 -> 653687951
B28: Equipment, Laboratory, & Machinery (Sarana & Prasarana) | C28: =+C10+C19 -> 176449500 | D28: =+D10+D19 -> 176449500 | E28: =+E10+E19 -> 176449500
B29: Vehicle & Heavy Equipment (Alat Berat + Kendaraan) | C29: =+C11+C20 -> 2060472728 | D29: =+D11+D20 -> 2207972728 | E29: =+E11+E20 -> 2207972728
B30: Office Inventory (Inventaris Tanaman Sawit + Inventaris Tanaman Sawit (TA)) | C30: =+C12+C21 -> 10145509610 | D30: =+D12+D21 -> 10145509610 | E30: =+E12+E21 -> 10145509610
B31: Electrical | C31: =+C13+C22 -> 0 | D31: =+D13+D22 -> 0 | E31: =+E13+E22 -> 0
A32: Total | C32: =+C14+C23 -> 20851219104 | D32: =+D14+D23 -> 21000894104 | E32: =+E14+E23 -> 21000894104
A34: B. Depreciation
A35: Beginning
B36: Land (Tanah Lahan Sawit + Tanah Lahan Sawit (TA)) | C36: 0 | D36: =C54 -> 0 | E36: =D54 -> 0
B37: Building (Bangunan Mess/Barak + Bangunan Mess/Barak (TA) + Lapangan + Kantor) | C37: 203967215 | D37: =C55 -> 242886427 | E37: =D55 -> 276895183
B38: Equipment, Laboratory, & Machinery (Sarana & Prasarana) | C38: 141871766 | D38: =C56 -> 155035543 | E38: =D56 -> 165897295
B39: Vehicle & Heavy Equipment (Alat Berat + Kendaraan) | C39: 1433114708 | D39: =C57 -> 1637977421 | E39: =D57 -> 1826348345
B40: Office Inventory (Inventaris Tanaman Sawit + Inventaris Tanaman Sawit (TA)) | C40: 754572077 | D40: =C58 -> 851107950 | E40: =D58 -> 1738665546
B41: Electrical | C41: 0 | D41: =C59 -> 0 | E41: =D59 -> 0
A42: Total | B42: =2391654000+141871766 -> 2533525766 | C42: =SUM(C36:C41) -> 2533525766 | D42: =SUM(D36:D41) -> 2887007341 | E42: =SUM(E36:E41) -> 4007806369
A44: Additions | G44: =$D$5 -> 2020 | H44: =$E$5 -> 2021 | I44: AVERAGE
B45: Land (Tanah Lahan Sawit + Tanah Lahan Sawit (TA)) | C45: 0 | D45: 0 | E45: 0 | G45: =IFERROR((D45-C45)/C45,0) -> 0 | H45: =IFERROR((E45-D45)/D45,0) -> 0 | I45: =AVERAGE(G45:H45) -> 0
B46: Building (Bangunan Mess/Barak + Bangunan Mess/Barak (TA) + Lapangan + Kantor) | C46: =10790628+12359737+15768847 -> 38919212 | D46: =8279196+15529644+10199916 -> 34008756 | E46: 36224681 | F46: =11972842+15529643+8722196 -> 36224681 | G46: =IFERROR((D46-C46)/C46,0) -> -0.12617049 | H46: =IFERROR((E46-D46)/D46,0) -> 0.065157485 | I46: =AVERAGE(G46:H46) -> -0.030506502
B47: Equipment, Laboratory, & Machinery (Sarana & Prasarana) | C47: 13163777 | D47: 10861752 | E47: 10552203 | G47: =IFERROR((D47-C47)/C47,0) -> -0.17487572 | H47: =IFERROR((E47-D47)/D47,0) -> -0.028498994 | I47: =AVERAGE(G47:H47) -> -0.10168736
B48: Vehicle & Heavy Equipment (Alat Berat + Kendaraan) | C48: =136112713+68750000 -> 204862713 | D48: =136808424+51562500 -> 188370924 | E48: 158340567 | F48: =119668692+38671875 -> 158340567 | G48: =IFERROR((D48-C48)/C48,0) -> -0.080501663 | H48: =IFERROR((E48-D48)/D48,0) -> -0.1594214 | I48: =AVERAGE(G48:H48) -> -0.11996153
B49: Office Inventory (Inventaris Tanaman Sawit + Inventaris Tanaman Sawit (TA)) | C49: 96535873 | D49: 887557596 | E49: 776612890 | G49: =IFERROR((D49-C49)/C49,0) -> 8.1940702 | H49: =IFERROR((E49-D49)/D49,0) -> -0.12500001 | I49: =AVERAGE(G49:H49) -> 4.0345351
B50: Electrical | C50: 0 | D50: 0 | E50: 0 | G50: =IFERROR((D50-C50)/C50,0) -> 0 | H50: =IFERROR((E50-D50)/D50,0) -> 0 | I50: =AVERAGE(G50:H50) -> 0
A51: Total | C51: =SUM(C45:C50) -> 353481575 | D51: =SUM(D45:D50) -> 1120799028 | E51: =SUM(E45:E50) -> 981730341
D52: =(D51-C51)/C51 -> 2.1707424 | E52: =(E51-D51)/D51 -> -0.12407995
A53: Ending
B54: Land (Tanah Lahan Sawit + Tanah Lahan Sawit (TA)) | C54: =+C36+C45 -> 0 | D54: =+D36+D45 -> 0 | E54: =+E36+E45 -> 0
B55: Building (Bangunan Mess/Barak + Bangunan Mess/Barak (TA) + Lapangan + Kantor) | C55: =+C37+C46 -> 242886427 | D55: =+D37+D46 -> 276895183 | E55: =+E37+E46 -> 313119864
B56: Equipment, Laboratory, & Machinery (Sarana & Prasarana) | C56: =+C38+C47 -> 155035543 | D56: =+D38+D47 -> 165897295 | E56: =+E38+E47 -> 176449498
B57: Vehicle & Heavy Equipment (Alat Berat + Kendaraan) | C57: =+C39+C48 -> 1637977421 | D57: =+D39+D48 -> 1826348345 | E57: =+E39+E48 -> 1984688912
B58: Office Inventory (Inventaris Tanaman Sawit + Inventaris Tanaman Sawit (TA)) | C58: =+C40+C49 -> 851107950 | D58: =+D40+D49 -> 1738665546 | E58: =+E40+E49 -> 2515278436
B59: Electrical | C59: =+C41+C50 -> 0 | D59: =+D41+D50 -> 0 | E59: =+E41+E50 -> 0
A60: Total | C60: =+C42+C51 -> 2887007341 | D60: =+D42+D51 -> 4007806369 | E60: =+E42+E51 -> 4989536710 | F60: =3944467162+176449500 -> 4120916662
A62: Net Value Fixed Assets
B63: Land (Tanah Lahan Sawit + Tanah Lahan Sawit (TA)) | C63: =+C26-C54 -> 7817274315 | D63: =+D26-D54 -> 7817274315 | E63: =+E26-E54 -> 7817274315 | G63: =E63 -> 7817274315 | H63: =G63 -> 7817274315
B64: Building (Bangunan Mess/Barak + Bangunan Mess/Barak (TA) + Lapangan + Kantor) | C64: =+C27-C55 -> 408626524 | D64: =+D27-D55 -> 376792768 | E64: =+E27-E55 -> 340568087 | G64: =SUM(E64:E68) -> 8194083079 | H64: =[4]BANGUNAN!$U$5 -> 1.6634234e+11
B65: Equipment, Laboratory, & Machinery (Sarana & Prasarana) | C65: =+C28-C56 -> 21413957 | D65: =+D28-D56 -> 10552205 | E65: =+E28-E56 -> 2 | H65: ='[4]FIXTURE FURNITURE EQUIPMENT'!$X$5 -> 1.438601e+11
B66: Vehicle & Heavy Equipment (Alat Berat + Kendaraan) | C66: =+C29-C57 -> 422495307 | D66: =+D29-D57 -> 381624383 | E66: =+E29-E57 -> 223283816 | H66: =SUM(H64:H65) -> 3.1020244e+11
B67: Office Inventory (Inventaris Tanaman Sawit + Inventaris Tanaman Sawit (TA)) | C67: =+C30-C58 -> 9294401660 | D67: =+D30-D58 -> 8406844064 | E67: =+E30-E58 -> 7630231174 | H67: =SUM(H63:H65) -> 3.1801971e+11 | I67: =H66-G64 -> 3.0200836e+11
B68: Electrical | C68: =+C31-C59 -> 0 | D68: =+D31-D59 -> 0 | E68: =+E31-E59 -> 0 | I68: =H67-E69 -> 3.0200836e+11
A69: Total | C69: =SUM(C63:C68) -> 17964211763 | D69: =SUM(D63:D68) -> 16993087735 | E69: =SUM(E63:E68) -> 16011357394
G72: tanah | H72: =E63 -> 7817274315
G73: nilai tanggungan | H73: =H72 -> 7817274315
G74: adjustment tanah | H74: =H73-H72 -> 0

Sheet BALANCE SHEET
A1: =HOME!B4 -> Makmur Jaya Sejati Raya | N1: LEGENDA
A2: Balance Sheet | G2: COMMON SIZE | O2: Komponen Cash Flow Statement, Changes on Working Capital, Current Assets
A3: (IDR) | O3: Komponen Cash Flow Statement, Changes on Working Capital, Current Liabilities
C4: =D4-1 -> 2019 | D4: =E4-1 -> 2020 | E4: =YEAR(HOME!B20) -> 2021 | G4: 2021 | H4: 2022 | I4: 2023 | J4: AVG | L4: Growth | M4: 2021 | N4: 2022 | O4: 2023 | P4: AVG
A5: ASSETS
A7: Current Assets
B8: Cash on Hands (Kas + Kas) | C8: 44887819 | D8: =53472823+97995296 -> 151468119 | E8: =82771246+635077549 -> 717848795 | G8: =C8/C$26 -> 0.0024042069 | H8: =D8/D$26 -> 0.0082273239 | I8: =E8/E$26 -> 0.04154628 | J8: =AVERAGE(G8:I8) -> 0.017392604 | M8: =0 -> 0 | N8: =IFERROR((D8-C8)/C8,0) -> 2.3743702 | O8: =IFERROR((E8-D8)/D8,0) -> 3.7392732 | P8: =AVERAGE(M8:O8) -> 2.0378811
B9: Cash on Bank (Bank Danomon A/C 006600669813 + Deposito Bank Danamon) | C9: 374140018 | D9: 572440850 | E9: 337031731 | G9: =C9/C$26 -> 0.020039067 | H9: =D9/D$26 -> 0.031093383 | I9: =E9/E$26 -> 0.019506078 | J9: =AVERAGE(G9:I9) -> 0.023546176 | M9: =0 -> 0 | N9: =IFERROR((D9-C9)/C9,0) -> 0.5300177 | O9: =IFERROR((E9-D9)/D9,0) -> -0.41123746 | P9: =AVERAGE(M9:O9) -> 0.039593415
B10: Account Receivable (Piutang Dagang) | C10: 248591028 | D10: 675378320 | E10: 191055111 | G10: =C10/C$26 -> 0.01331462 | H10: =D10/D$26 -> 0.036684658 | I10: =E10/E$26 -> 0.011057522 | J10: =AVERAGE(G10:I10) -> 0.020352267 | M10: =0 -> 0 | N10: =IFERROR((D10-C10)/C10,0) -> 1.716825 | O10: =IFERROR((E10-D10)/D10,0) -> -0.71711394 | P10: =AVERAGE(M10:O10) -> 0.33323702
B11: Other Receivable (Piutang Karyawan) | C11: 38700000 | D11: 18000000 | E11: 21000000 | G11: =C11/C$26 -> 0.0020727852 | H11: =D11/D$26 -> 0.00097770958 | I11: =E11/E$26 -> 0.0012153978 | J11: =AVERAGE(G11:I11) -> 0.0014219642 | M11: =0 -> 0 | N11: =IFERROR((D11-C11)/C11,0) -> -0.53488372 | O11: =IFERROR((E11-D11)/D11,0) -> 0.16666667 | P11: =AVERAGE(M11:O11) -> -0.12273902
B12: Inventory | C12: 0 | D12: 0 | E12: 0 | G12: =C12/C$26 -> 0 | H12: =D12/D$26 -> 0 | I12: =E12/E$26 -> 0 | J12: =AVERAGE(G12:I12) -> 0 | M12: =0 -> 0 | N12: =IFERROR((D12-C12)/C12,0) -> 0 | O12: =IFERROR((E12-D12)/D12,0) -> 0 | P12: =AVERAGE(M12:O12) -> 0
B13: Others | C13: 0 | D13: 0 | E13: 0 | G13: =C13/C$26 -> 0 | H13: =D13/D$26 -> 0 | I13: =E13/E$26 -> 0 | J13: =AVERAGE(G13:I13) -> 0 | M13: =0 -> 0 | N13: =IFERROR((D13-C13)/C13,0) -> 0 | O13: =IFERROR((E13-D13)/D13,0) -> 0 | P13: =AVERAGE(M13:O13) -> 0
A15: Current Assets | C15: =SUM(C8:C13) -> 706318865 | D15: =SUM(D8:D13) -> 1417287289 | E15: =SUM(E8:E13) -> 1266935637
A17: Non Current Assets
A18: Fixed Asset
B19: Beginning | C19: ='FIXED ASSET'!C32 -> 20851219104 | D19: ='FIXED ASSET'!D32 -> 21000894104 | E19: ='FIXED ASSET'!E32 -> 21000894104 | G19: =C19/C$26 -> 1.1167984 | H19: =D19/D$26 -> 1.1407097 | I19: =E19/E$26 -> 1.2154496 | J19: =AVERAGE(G19:I19) -> 1.1576526 | M19: =0 -> 0 | N19: =IFERROR((D19-C19)/C19,0) -> 0.0071782374 | O19: =IFERROR((E19-D19)/D19,0) -> 0 | P19: =AVERAGE(M19:O19) -> 0.0023927458
B20: Accumulated Depreciations | C20: ='FIXED ASSET'!C60*-1 -> -2887007341 | D20: ='FIXED ASSET'!D60*-1 -> -4007806369 | E20: ='FIXED ASSET'!E60*-1 -> -4989536710 | G20: =C20/C$26 -> -0.1546291 | H20: =D20/D$26 -> -0.21769282 | I20: =E20/E$26 -> -0.28877486 | J20: =AVERAGE(G20:I20) -> -0.22036559 | M20: =0 -> 0 | N20: =IFERROR((D20-C20)/C20,0) -> 0.38822175 | O20: =IFERROR((E20-D20)/D20,0) -> 0.24495453 | P20: =AVERAGE(M20:O20) -> 0.21105876
B21: Fixed Assets, Net | C21: =C19+C20 -> 17964211763 | D21: =D19+D20 -> 16993087735 | E21: =E19+E20 -> 16011357394 | M21: =0 -> 0 | N21: =IFERROR((D21-C21)/C21,0) -> -0.054058817 | O21: =IFERROR((E21-D21)/D21,0) -> -0.057772334 | P21: =AVERAGE(M21:O21) -> -0.03727705
A22: Non Current Assets | C22: 0 | D22: 0 | E22: 0 | M22: =0 -> 0 | N22: =IFERROR((D22-C22)/C22,0) -> 0 | O22: =IFERROR((E22-D22)/D22,0) -> 0 | P22: =AVERAGE(M22:O22) -> 0
A23: Intangible Assets | C23: 0 | D23: 0 | E23: 0 | M23: =0 -> 0 | N23: =IFERROR((D23-C23)/C23,0) -> 0 | O23: =IFERROR((E23-D23)/D23,0) -> 0 | P23: =AVERAGE(M23:O23) -> 0
A24: Total Non Current Asset | C24: =C21+C22+C23 -> 17964211763 | D24: =D21+D22+D23 -> 16993087735 | E24: =E21+E22+E23 -> 16011357394 | M24: =0 -> 0 | N24: =IFERROR((D24-C24)/C24,0) -> -0.054058817 | O24: =IFERROR((E24-D24)/D24,0) -> -0.057772334 | P24: =AVERAGE(M24:O24) -> -0.03727705
A26: ASSETS | C26: =+C15+C24 -> 18670530628 | D26: =+D15+D24 -> 18410375024 | E26: =+E15+E24 -> 17278293031
A28: LIABILITIES & EQUITY
A29: Current Liabilities
B30: Bank Loan-Short Term | C30: 0 | D30: 0 | E30: 0 | G30: =C30/C$50 -> 0 | H30: =D30/D$50 -> 0 | I30: =E30/E$50 -> 0 | J30: =AVERAGE(G30:I30) -> 0 | M30: =0 -> 0 | N30: =IFERROR((D30-C30)/C30,0) -> 0 | O30: =IFERROR((E30-D30)/D30,0) -> 0 | P30: =AVERAGE(M30:O30) -> 0
B31: Account Payables (Hutang Dagang) | C31: 1349091893 | D31: 722586680 | E31: 1823364600 | G31: =C31/C$50 -> 0.072956728 | H31: =D31/D$50 -> 0.039169761 | I31: =E31/E$50 -> 0.10482686 | J31: =AVERAGE(G31:I31) -> 0.072317782 | M31: =0 -> 0 | N31: =IFERROR((D31-C31)/C31,0) -> -0.46439032 | O31: =IFERROR((E31-D31)/D31,0) -> 1.5233853 | P31: =AVERAGE(M31:O31) -> 0.35299832
B32: Tax Payable (Hutang PPh Pasal 29 + Hutang PPh Pasal 25 + Hutang PPh Pasal 21 + Hutang PPN + PPN dan PPh 29) | C32: =20499268+7791190+71113530 -> 99403988 | D32: =28927903+9457631+2401280+70425650+139134936 -> 250347400 | E32: =263030563+11451679+81022+102761900+301193090 -> 678518254 | G32: =C32/C$50 -> 0.0053756084 | H32: =D32/D$50 -> 0.013570756 | I32: =E32/E$50 -> 0.03900862 | J32: =AVERAGE(G32:I32) -> 0.019318328 | M32: =0 -> 0 | N32: =IFERROR((D32-C32)/C32,0) -> 1.5184845 | O32: =IFERROR((E32-D32)/D32,0) -> 1.7103068 | P32: =AVERAGE(M32:O32) -> 1.0762637
B33: Others (Hutang Gaji Karyawan) | C33: 397739810 | D33: 295472920 | E33: 1075354928 | G33: =C33/C$50 -> 0.021509132 | H33: =D33/D$50 -> 0.016016907 | I33: =E33/E$50 -> 0.061823114 | J33: =AVERAGE(G33:I33) -> 0.033116384 | M33: =0 -> 0 | N33: =IFERROR((D33-C33)/C33,0) -> -0.25712008 | O33: =IFERROR((E33-D33)/D33,0) -> 2.6394365 | P33: =AVERAGE(M33:O33) -> 0.79410547
A34: Current Liabilities | C34: =SUM(C30:C33) -> 1846235691 | D34: =SUM(D30:D33) -> 1268407000 | E34: =SUM(E30:E33) -> 3577237782
A36: Non Current Liabilities
B37: Bank Loan-Long Term | C37: 0 | D37: 0 | E37: 0 | G37: =C37/C$50 -> 0 | H37: =D37/D$50 -> 0 | I37: =E37/E$50 -> 0 | J37: =AVERAGE(G37:I37) -> 0 | M37: =0 -> 0 | N37: =IFERROR((D37-C37)/C37,0) -> 0 | O37: =IFERROR((E37-D37)/D37,0) -> 0 | P37: =AVERAGE(M37:O37) -> 0
B38: Related Party acc. Payable & Employee Benefits | C38: 0 | D38: 0 | E38: 0 | G38: =C38/C$50 -> 0 | H38: =D38/D$50 -> 0 | I38: =E38/E$50 -> 0 | J38: =AVERAGE(G38:I38) -> 0 | M38: =0 -> 0 | N38: =IFERROR((D38-C38)/C38,0) -> 0 | O38: =IFERROR((E38-D38)/D38,0) -> 0 | P38: =AVERAGE(M38:O38) -> 0
A39: Non Current Liabilities | C39: =+C37+C38 -> 0 | D39: =+D37+D38 -> 0 | E39: =+E37+E38 -> 0 | G39: =C39/C$50 -> 0 | H39: =D39/D$50 -> 0 | I39: =E39/E$50 -> 0 | J39: =AVERAGE(G39:I39) -> 0
A40: LIABILITIES | C40: =+C34+C39 -> 1846235691 | D40: =+D34+D39 -> 1268407000 | E40: =+E34+E39 -> 3577237782
A41: Shareholders' Equity
A42: Paid Up Capital (Modal Disetor) | C42: 5280000000 | D42: 5280000000 | E42: 5280000000 | G42: =C42/C$50 -> 0.28553394 | H42: =D42/D$50 -> 0.28621665 | I42: =E42/E$50 -> 0.30355191 | J42: =AVERAGE(G42:I42) -> 0.2917675 | M42: =0 -> 0 | N42: =IFERROR((D42-C42)/C42,0) -> 0 | O42: =IFERROR((E42-D42)/D42,0) -> 0 | P42: =AVERAGE(M42:O42) -> 0
A43: Addition (Uang Muka Setoran Modal) | C43: 3550000000 | D43: 3150000000 | E43: 0
A44: Retained Earnings
B45: Surplus (Laba di Tahan (TA) + Laba Ditahan Tahun Lalu - Deviden) | C45: =5289183925+2085507326 -> 7374691251 | D45: =5289183925+2705111011 -> 7994294936 | E45: =5289183925+3909531302-2500000000 -> 6698715227 | G45: =C45/C$50 -> 0.39881149 | H45: =D45/D$50 -> 0.43335233 | I45: =E45/E$50 -> 0.38511511 | J45: =AVERAGE(G45:I45) -> 0.40575965 | M45: =0 -> 0 | N45: =IFERROR((D45-C45)/C45,0) -> 0.084017576 | O45: =IFERROR((E45-D45)/D45,0) -> -0.16206304 | P45: =AVERAGE(M45:O45) -> -0.026015153
B46: Current Profit - Commercial NPAT (Laba Bersih Komersial) | C46: ='INCOME STATEMENT'!C35 -> 440745074 | D46: ='INCOME STATEMENT'!D35 -> 754862153 | E46: ='INCOME STATEMENT'!E35 -> 1838106527 | G46: =C46/C$50 -> 0.023834788 | H46: =D46/D$50 -> 0.04091934 | I46: =E46/E$50 -> 0.10567438 | J46: =AVERAGE(G46:I46) -> 0.056809504 | M46: =0 -> 0 | N46: =IFERROR((D46-C46)/C46,0) -> 0.71269561 | O46: =IFERROR((E46-D46)/D46,0) -> 1.4350228 | P46: =AVERAGE(M46:O46) -> 0.71590612
A47: Retained Earnings, Ending Balance | C47: =+C46+C45 -> 7815436325 | D47: =+D46+D45 -> 8749157089 | E47: =+E46+E45 -> 8536821754 | G47: =C47/C$50 -> 0.42264628 | H47: =D47/D$50 -> 0.47427167 | I47: =E47/E$50 -> 0.4907895 | J47: =AVERAGE(G47:I47) -> 0.46256915 | M47: =0 -> 0 | N47: =IFERROR((D47-C47)/C47,0) -> 0.11947135 | O47: =IFERROR((E47-D47)/D47,0) -> -0.024269233 | P47: =AVERAGE(M47:O47) -> 0.03173404
A48: Shareholders' Equity | C48: =+C42+C47+C43 -> 16645436325 | D48: =+D42+D47+D43 -> 17179157089 | E48: =+E42+E47+E43 -> 13816821754
A50: LIABILITES & EQUITY | C50: =C34+C39+C48 -> 18491672016 | D50: =D34+D39+D48 -> 18447564089 | E50: =E34+E39+E48 -> 17394059536
E51: =E26-E50 -> -115766505

Sheet INCOME STATEMENT
A1: ='BALANCE SHEET'!A1 -> Makmur Jaya Sejati Raya
A2: Income Statement
A3: ='[3]BALANCE SHEET'!A3 -> (IDR) | G3: COMMON SIZE | L3: HORIZONTAL
C5: =D5-1 -> 2019 | D5: =E5-1 -> 2020 | E5: =YEAR(HOME!B20) -> 2021 | G5: =C5 -> 2019 | H5: =D5 -> 2020 | I5: =E5 -> 2021 | J5: AVG | L5: 2021 | M5: 2022 | N5: 2023 | O5: AVG
A6: Revenue (Penjualan) | C6: 9335637236 | D6: 11406787320 | E6: =16663916100 -> 16663916100 | G6: =IFERROR((C6-0)/0,0) -> 0 | H6: =(D6-C6)/C6 -> 0.22185417 | I6: =(E6-D6)/D6 -> 0.46087725 | J6: =AVERAGE(G6:I6) -> 0.22757714 | L6: =IFERROR((C6-0)/0,0) -> 0 | M6: =(D6-C6)/C6 -> 0.22185417 | N6: =(E6-D6)/D6 -> 0.46087725 | O6: =AVERAGE(L6:N6) -> 0.22757714
A7: Cost of Good Sold (Pupuk + Obat-Obatan + Ongkos Angkut Pembelian TBS + Langsir & Muat TBS + Gaji Pegawai Bag. Lapangan + Keperluan Lapangan + Bibit Sawit) | C7: =(1341236655+237790000+532433990+60489260+4531901900+176756281)*-1 -> -6880608086 | D7: =(1118290360+389785500+47250000+678881440+154953960+4984022900+192568750)*-1 -> -7565752910 | E7: =(1868593447+567317727+806095500+470963990+6699039850+367647700)*-1 -> -10779658214 | G7: =C7/C$6 -> -0.73702608 | H7: =D7/D$6 -> -0.66326764 | I7: =E7/E$6 -> -0.64688625 | J7: =AVERAGE(G7:I7) -> -0.68239332 | L7: =IFERROR((C7-0)/0,0) -> 0 | M7: =(D7-C7)/C7 -> 0.099576202 | N7: =(E7-D7)/D7 -> 0.42479649 | O7: =AVERAGE(L7:N7) -> 0.1747909
A8: Gross Profit | C8: =SUM(C6:C7) -> 2455029150 | D8: =SUM(D6:D7) -> 3841034410 | E8: =SUM(E6:E7) -> 5884257886 | G8: =C8/C$6 -> 0.26297392 | H8: =D8/D$6 -> 0.33673236 | I8: =E8/E$6 -> 0.35311375 | J8: =AVERAGE(G8:I8) -> 0.31760668
B9: Gross Profit Margin | C9: =+C8/C6 -> 0.26297392 | D9: =+D8/D6 -> 0.33673236 | E9: =+E8/E6 -> 0.35311375 | I9: =I8-H8 -> 0.016381389
A11: Operating Expenses:
B12: Others | C12: 0 | D12: 0 | E12: 0 | G12: =C12/C$6 -> 0 | H12: =D12/D$6 -> 0 | I12: =E12/E$6 -> 0 | J12: =AVERAGE(G12:I12) -> 0 | L12: =IFERROR((C12-0)/0,0) -> 0 | M12: =IFERROR((D12-C12)/C12,0) -> 0 | N12: =IFERROR((E12-D12)/D12,0) -> 0 | O12: =AVERAGE(L12:N12) -> 0
B13: General & Administrative Overheads (Iuran & Retribusi + BBM + STNK & Pajak Kendaraan + Spare Parts Kendaraan + Perjalanan Dinas + Pem. & Perawatan Sarana & Prasarana + Gaji Pegawai Bag. Administrasi + Adm. Bank + Rek. Listrik + Keperluan Kantor + STP + PBB + Pemeliharaan Mess + Notaris) | C13: =(28989940+226329500+10176400+336574200+171636900+55010000+507006500+1505306+4000000+17133467+25364440+36857132)*-1 -> -1420583785 | D13: =(39888220+388515583+12543000+475888200+19685000+331373500+445539100+1477600+22156200+14335851+58476654)*-1 -> -1809878908 | E13: =(10290500+543625269+10767100+809649273+146537000+507940000+449519500+1418500+24268976+37800600+34972298+64306088)*-1 -> -2641095104 | G13: =C13/C$6 -> -0.15216784 | H13: =D13/D$6 -> -0.15866684 | I13: =E13/E$6 -> -0.15849186 | J13: =AVERAGE(G13:I13) -> -0.15644218 | L13: =IFERROR((C13-0)/0,0) -> 0 | M13: =(D13-C13)/C13 -> 0.27403883 | N13: =(E13-D13)/D13 -> 0.45926619 | O13: =AVERAGE(L13:N13) -> 0.24443501
A15: Operating Expenses | C15: =C12+C13 -> -1420583785 | D15: =D12+D13 -> -1809878908 | E15: =E12+E13 -> -2641095104 | G15: =C15/C$6 -> -0.15216784 | H15: =D15/D$6 -> -0.15866684 | I15: =E15/E$6 -> -0.15849186 | J15: =AVERAGE(G15:I15) -> -0.15644218 | L15: =IFERROR((C15-0)/0,0) -> 0 | M15: =(D15-C15)/C15 -> 0.27403883 | N15: =(E15-D15)/D15 -> 0.45926619 | O15: =AVERAGE(L15:N15) -> 0.24443501
A16: (Exclude Depreciation)
A18: EBITDA | C18: =C8+C15 -> 1034445365 | D18: =D8+D15 -> 2031155502 | E18: =E8+E15 -> 3243162782 | G18: =C18/C$6 -> 0.11080608 | H18: =D18/D$6 -> 0.17806552 | I18: =E18/E$6 -> 0.19462189 | J18: =AVERAGE(G18:I18) -> 0.16116449 | L18: =IFERROR((C18-0)/0,0) -> 0 | M18: =(D18-C18)/C18 -> 0.96352129 | N18: =(E18-D18)/D18 -> 0.59670827 | O18: =AVERAGE(L18:N18) -> 0.52007652
B19: EBITDA margin | C19: =C18/C6 -> 0.11080608 | D19: =D18/D6 -> 0.17806552 | E19: =E18/E6 -> 0.19462189
A21: Depreciation | C21: ='FIXED ASSET'!C51*-1 -> -353481575 | D21: ='FIXED ASSET'!D51*-1 -> -1120799028 | E21: ='FIXED ASSET'!E51*-1 -> -981730341
A22: EBIT | C22: =+C18+C21 -> 680963790 | D22: =+D18+D21 -> 910356474 | E22: =+E18+E21 -> 2261432441 | G22: =C22/C$6 -> 0.0729424 | H22: =D22/D$6 -> 0.079808315 | I22: =E22/E$6 -> 0.13570834 | J22: =AVERAGE(G22:I22) -> 0.096153019 | L22: =IFERROR((C22-0)/0,0) -> 0 | M22: =(D22-C22)/C22 -> 0.33686473 | N22: =(E22-D22)/D22 -> 1.4841175 | O22: =AVERAGE(L22:N22) -> 0.60699407
B23: EBIT margin | C23: =+C22/C6 -> 0.0729424 | D23: =+D22/D6 -> 0.079808315 | E23: =+E22/E6 -> 0.13570834 | G23: =C23/C$6 -> 7.8133285e-12 | H23: =D23/D$6 -> 6.9965638e-12 | I23: =E23/E$6 -> 8.1438446e-12 | J23: =AVERAGE(G23:I23) -> 7.6512456e-12
A25: Other Incomes/(Charges):
B26: Interest Income (Pendapatan Jasa Giro + Pendapatan Bagi Hasil (Bank) + Pendapatan Bunga Deposito) | C26: =7222836+74171233 -> 81394069 | D26: =6803933+5000000 -> 11803933 | E26: =(2443706+2266459+9247176) -> 13957341 | G26: =C26/C$6 -> 0.0087186409 | H26: =D26/D$6 -> 0.0010348166 | I26: =E26/E$6 -> 0.00083757869 | J26: =AVERAGE(G26:I26) -> 0.0035303454
B27: Interest Expense (Beban Jasa Giro + Beban Lain-Lain) | C27: =(1444567+14834247)*-1 -> -16278814 | D27: =(1360787+341)*-1 -> -1361128 | E27: =(488741+453292)*-1 -> -942033 | G27: =C27/C$6 -> -0.0017437282 | H27: =D27/D$6 -> -0.00011932615 | I27: =E27/E$6 -> -5.653131e-05 | J27: =AVERAGE(G27:I27) -> -0.00063986189 | L27: =IFERROR((C27-0)/0,0) -> 0 | M27: =(D27-C27)/C27 -> -0.91638654 | N27: =(E27-D27)/D27 -> -0.30790271 | O27: =AVERAGE(L27:N27) -> -0.40809642
A28: Other Incomes/(Charges) | C28: =+C26+C27 -> 65115255 | D28: =+D26+D27 -> 10442805 | E28: =+E26+E27 -> 13015308 | G28: =C28/C$6 -> 0.0069749127 | H28: =D28/D$6 -> 0.00091549046 | I28: =E28/E$6 -> 0.00078104738 | J28: =AVERAGE(G28:I28) -> 0.0028904835 | L28: =IFERROR((C28-0)/0,0) -> 0 | M28: =(D28-C28)/C28 -> -0.83962583 | N28: =(E28-D28)/D28 -> 0.24634215 | O28: =AVERAGE(L28:N28) -> -0.19776123
A30: Non Operating Income (Pendapatan Lain-Lain - Beban Lain-Lain) | C30: 0 | D30: 0 | E30: =(12125-225000) -> -212875 | G30: =C30/C$6 -> 0 | H30: =D30/D$6 -> 0 | I30: =E30/E$6 -> -1.2774608e-05 | J30: =AVERAGE(G30:I30) -> -4.2582027e-06 | L30: =IFERROR((C30-0)/0,0) -> 0 | M30: =IFERROR((D30-C30)/C30,0) -> 0 | N30: =IFERROR((E30-D30)/D30,0) -> 0 | O30: =AVERAGE(L30:N30) -> 0
A32: Profit Before Tax | C32: =+C22+C28+C30 -> 746079045 | D32: =+D22+D28+D30 -> 920799279 | E32: =+E22+E28+E30 -> 2274234874 | G32: =C32/C$6 -> 0.079917313 | H32: =D32/D$6 -> 0.080723805 | I32: =E32/E$6 -> 0.13647662 | J32: =AVERAGE(G32:I32) -> 0.099039245 | L32: =IFERROR((C32-0)/0,0) -> 0 | M32: =(D32-C32)/C32 -> 0.23418462 | N32: =(E32-D32)/D32 -> 1.4698487 | O32: =AVERAGE(L32:N32) -> 0.56801109
A33: Corporate Tax | C33: -305333971 | D33: -165937126 | E33: -436128347 | I33: =(E33-D33)/D33 -> 1.6282747
A35: Net Profit After Tax | C35: =+C32+C33 -> 440745074 | D35: =+D32+D33 -> 754862153 | E35: =+E32+E33 -> 1838106527 | G35: =C35/C$6 -> 0.047211033 | H35: =D35/D$6 -> 0.066176578 | I35: =E35/E$6 -> 0.1103046 | J35: =AVERAGE(G35:I35) -> 0.074564069 | L35: =IFERROR((C35-0)/0,0) -> 0 | M35: =(D35-C35)/C35 -> 0.71269561 | N35: =(E35-D35)/D35 -> 1.4350228 | O35: =AVERAGE(L35:N35) -> 0.71590612
B36: Net Profit Margin | C36: =+C35/C6 -> 0.047211033 | D36: =+D35/D6 -> 0.066176578 | E36: =+E35/E6 -> 0.1103046 | H36: =I35-H35 -> 0.044128017

Sheet ACC PAYABLES
A1: =HOME!B4 -> Makmur Jaya Sejati Raya
A2: Bank Loan Schedules
A3: ='BALANCE SHEET'!A3 -> (IDR)
C5: ='FIXED ASSET'!C5 -> 2019 | D5: ='FIXED ASSET'!D5 -> 2020 | E5: ='FIXED ASSET'!E5 -> 2021
A7: Bank Loan-SHORT TERM
A8: Principal | C8: 0.13 | D8: 0.13 | E8: 0.13
A9: Beginning | C9: =0 -> 0 | D9: =C12 -> 0 | E9: =D12 -> 0
B10: Addition | C10: =('BALANCE SHEET'!C30-0) -> 0 | D10: =('BALANCE SHEET'!D30-'BALANCE SHEET'!C30) -> 0 | E10: =('BALANCE SHEET'!E30-'BALANCE SHEET'!D30) -> 0
B11: Repayment | C11: 0 | D11: 0 | E11: 0
A12: Ending | C12: =SUM(C9:C11) -> 0 | D12: =SUM(D9:D11) -> 0 | E12: =SUM(E9:E11) -> 0
A14: Interest Payable | C14: 0 | D14: 0 | E14: 0
A16: Bank Loan-LONG TERM
A17: Principal | C17: 0.13 | D17: 0.13 | E17: 0.13
A18: Beginning | C18: 0 | D18: =C21 -> 0 | E18: =D21 -> 0
B19: Addition | C19: 0 | D19: 0 | E19: 0
B20: Repayment | C20: 0 | D20: 0 | E20: 0
A21: Ending | C21: =SUM(C18:C20) -> 0 | D21: =SUM(D18:D20) -> 0 | E21: =SUM(E18:E20) -> 0
A23: Interest Payable | C23: 0 | D23: 0 | E23: 0

Sheet CASH FLOW STATEMENT
A1: =HOME!B4 -> Makmur Jaya Sejati Raya
A2: Cash Flow Statement
A3: ='BALANCE SHEET'!A3 -> (IDR)
C4: ='INCOME STATEMENT'!C5 -> 2019 | D4: ='INCOME STATEMENT'!D5 -> 2020 | E4: ='INCOME STATEMENT'!E5 -> 2021 | I4: LEGENDA
A5: EBITDA | C5: ='INCOME STATEMENT'!C18 -> 1034445365 | D5: ='INCOME STATEMENT'!D18 -> 2031155502 | E5: ='INCOME STATEMENT'!E18 -> 3243162782 | J5: ="Angkanya didapat dari saldo "&C4&" - "&C4-1&", karena "&C4-1&" ada LK-nya sehingga diisi sekalian di Balance Sheet biar otomatis nyambung." -> Angkanya didapat dari saldo 2019 - 2018, karena 2018 ada LK-nya sehingga diisi sekalian di Balance Sheet biar otomatis nyambung.
A6: Corporate Tax | C6: ='INCOME STATEMENT'!C33 -> -305333971 | D6: ='INCOME STATEMENT'!D33 -> -165937126 | E6: ='INCOME STATEMENT'!E33 -> -436128347
A7: Changes in Working Capital
B8: Operating Current Assets (AR + Inventory) | C8: =('BALANCE SHEET'!C10+'BALANCE SHEET'!C12)*-1 -> -248591028 | D8: =(('BALANCE SHEET'!D10+'BALANCE SHEET'!D12)-('BALANCE SHEET'!C10+'BALANCE SHEET'!C12))*-1 -> -426787292 | E8: =(('BALANCE SHEET'!E10+'BALANCE SHEET'!E12)-('BALANCE SHEET'!D10+'BALANCE SHEET'!D12))*-1 -> 484323209
B9: Operating Current Liabilities (AP + Other Payable) | C9: =('BALANCE SHEET'!C31+'BALANCE SHEET'!C33)-(0+0) -> 1746831703 | D9: =('BALANCE SHEET'!D31+'BALANCE SHEET'!D33)-('BALANCE SHEET'!C31+'BALANCE SHEET'!C33) -> -728772103 | E9: =('BALANCE SHEET'!E31+'BALANCE SHEET'!E33)-('BALANCE SHEET'!D31+'BALANCE SHEET'!D33) -> 1880659928
A10: Working Capital | C10: =+C8+C9 -> 1498240675 | D10: =+D8+D9 -> -1155559395 | E10: =+E8+E9 -> 2364983137
A11: Cash Flow from Operations | C11: =SUM(C5:C9) -> 2227352069 | D11: =SUM(D5:D9) -> 709658981 | E11: =SUM(E5:E9) -> 5172017572
A13: Cash Flow from Non Operations | C13: ='INCOME STATEMENT'!C30 -> 0 | D13: ='INCOME STATEMENT'!D30 -> 0 | E13: ='INCOME STATEMENT'!E30 -> -212875
A17: Cash Flow from Investment (Capital Expenditure) | C17: ='FIXED ASSET'!C23*-1 -> -10175220000 | D17: ='FIXED ASSET'!D23*-1 -> -149675000 | E17: ='FIXED ASSET'!E23*-1 -> 0
A19: Cash Flow before Financing | C19: =C11+C13+C17 -> -7947867931 | D19: =D11+D13+D17 -> 559983981 | E19: =E11+E13+E17 -> 5171804697
A21: Financing
B22: Equity Injection | C22: =('BALANCE SHEET'!C42+'BALANCE SHEET'!C43)-0 -> 8830000000 | D22: =('BALANCE SHEET'!D42+'BALANCE SHEET'!D43)-('BALANCE SHEET'!C42+'BALANCE SHEET'!C43) -> -400000000 | E22: =('BALANCE SHEET'!E42+'BALANCE SHEET'!E43)-('BALANCE SHEET'!D42+'BALANCE SHEET'!D43) -> -3150000000
B23: New Loan | C23: ='ACC PAYABLES'!C10+'ACC PAYABLES'!C19 -> 0 | D23: ='ACC PAYABLES'!D10+'ACC PAYABLES'!D19 -> 0 | E23: ='ACC PAYABLES'!E10+'ACC PAYABLES'!E19 -> 0
B24: Interenst Payment | C24: ='INCOME STATEMENT'!C27 -> -16278814 | D24: ='INCOME STATEMENT'!D27 -> -1361128 | E24: ='INCOME STATEMENT'!E27 -> -942033
B25: Interest Income | C25: ='INCOME STATEMENT'!C26 -> 81394069 | D25: ='INCOME STATEMENT'!D26 -> 11803933 | E25: ='INCOME STATEMENT'!E26 -> 13957341
B26: Principal Repayment | C26: ='ACC PAYABLES'!C20 -> 0 | D26: ='ACC PAYABLES'!D20 -> 0 | E26: ='ACC PAYABLES'!E20 -> 0
A28: Cash Flow from Financing | C28: =SUM(C22:C26) -> 8895115255 | D28: =SUM(D22:D26) -> -389557195 | E28: =SUM(E22:E26) -> -3136984692
A30: Net Cash Flow | C30: =+C11+C13+C17+C28 -> 947247324 | D30: =+D11+D13+D17+D28 -> 170426786 | E30: =+E11+E13+E17+E28 -> 2034820005
A32: Cash-Beginning Balance | C32: =259004307+250716909+3500000000 -> 4009721216 | D32: =C33 -> 419027837 | E32: =D33 -> 723908969
A33: Cash-Ending Balance | C33: ='BALANCE SHEET'!C8+'BALANCE SHEET'!C9 -> 419027837 | D33: ='BALANCE SHEET'!D8+'BALANCE SHEET'!D9 -> 723908969 | E33: ='BALANCE SHEET'!E8+'BALANCE SHEET'!E9 -> 1054880526
A35: Cash Ending in Bank | C35: ='BALANCE SHEET'!C9 -> 374140018 | D35: ='BALANCE SHEET'!D9 -> 572440850 | E35: ='BALANCE SHEET'!E9 -> 337031731
A36: Cash Ending in Cash on Hand | C36: ='BALANCE SHEET'!C8 -> 44887819 | D36: ='BALANCE SHEET'!D8 -> 151468119 | E36: ='BALANCE SHEET'!E8 -> 717848795

Sheet FINANCIAL RATIO
A1: =HOME!B4 -> Makmur Jaya Sejati Raya
A2: Financial Ratios
B4: Ratio | C4: Formula | D4: =ROIC!B5 -> 2019 | E4: =ROIC!C5 -> 2020 | F4: =ROIC!D5 -> 2021 | G4: Average
A5: Profitability Indicator Ratio | B5: Profitability Indicator Ratio | C5: Formula | D5: Column3 | E5: Column4 | F5: Column5 | G5: Column6
B6: Gross Profit Margin | C6: GP/Sales | D6: ='INCOME STATEMENT'!C9 -> 0.26297392 | E6: ='INCOME STATEMENT'!D9 -> 0.33673236 | F6: ='INCOME STATEMENT'!E9 -> 0.35311375 | G6: =AVERAGE(D6:F6) -> 0.31760668
B7: EBITDA Margin | C7: EBITDA/Sales | D7: ='INCOME STATEMENT'!C19 -> 0.11080608 | E7: ='INCOME STATEMENT'!D19 -> 0.17806552 | F7: ='INCOME STATEMENT'!E19 -> 0.19462189 | G7: =AVERAGE(D7:F7) -> 0.16116449
B8: EBIT Margin | C8: EBIT/Sales | D8: ='INCOME STATEMENT'!C23 -> 0.0729424 | E8: ='INCOME STATEMENT'!D23 -> 0.079808315 | F8: ='INCOME STATEMENT'!E23 -> 0.13570834 | G8: =AVERAGE(D8:F8) -> 0.096153019
B9: Net Profit Margin | C9: Net Profit/Sales | D9: ='INCOME STATEMENT'!C36 -> 0.047211033 | E9: ='INCOME STATEMENT'!D36 -> 0.066176578 | F9: ='INCOME STATEMENT'!E36 -> 0.1103046 | G9: =AVERAGE(D9:F9) -> 0.074564069
B10: Return On Asset | C10: Net Profit/Asset | D10: ='INCOME STATEMENT'!C35/'BALANCE SHEET'!C26 -> 0.023606457 | E10: ='INCOME STATEMENT'!D35/'BALANCE SHEET'!D26 -> 0.041001998 | F10: ='INCOME STATEMENT'!E35/'BALANCE SHEET'!E26 -> 0.10638241 | G10: =AVERAGE(D10:F10) -> 0.056996956
B11: Return On Equity | C11: Net Profit/Equity | D11: ='INCOME STATEMENT'!C35/'BALANCE SHEET'!C48 -> 0.026478433 | E11: ='INCOME STATEMENT'!D35/'BALANCE SHEET'!D48 -> 0.043940582 | F11: ='INCOME STATEMENT'!E35/'BALANCE SHEET'!E48 -> 0.13303396 | G11: =AVERAGE(D11:F11) -> 0.067817659
A13: Liquidity Measurement Ratio | B13: Liquidity Measurement Ratio | C13: Formula | D13: Column3 | E13: Column4 | F13: Column5 | G13: Column6
B14: Current Ratio | C14: CA/CL | D14: ='BALANCE SHEET'!C15/'BALANCE SHEET'!C34 -> 0.38257242 | E14: ='BALANCE SHEET'!D15/'BALANCE SHEET'!D34 -> 1.1173758 | F14: ='BALANCE SHEET'!E15/'BALANCE SHEET'!E34 -> 0.3541659 | G14: =AVERAGE(D14:F14) -> 0.61803804
B15: Quick Ratio | C15: (Cash+A/R)/CL | D15: =('BALANCE SHEET'!C8+'BALANCE SHEET'!C9+'BALANCE SHEET'!C10)/'BALANCE SHEET'!C34 -> 0.36161085 | E15: =('BALANCE SHEET'!D8+'BALANCE SHEET'!D9+'BALANCE SHEET'!D10)/'BALANCE SHEET'!D34 -> 1.1031848 | F15: =('BALANCE SHEET'!E8+'BALANCE SHEET'!E9+'BALANCE SHEET'!E10)/'BALANCE SHEET'!E34 -> 0.34829545 | G15: =AVERAGE(D15:F15) -> 0.60436369
B16: Cash Ratio | C16: Cash/CL | D16: =('BALANCE SHEET'!C8+'BALANCE SHEET'!C9)/'BALANCE SHEET'!C34 -> 0.22696335 | E16: =('BALANCE SHEET'!D8+'BALANCE SHEET'!D9)/'BALANCE SHEET'!D34 -> 0.57072294 | F16: =('BALANCE SHEET'!E8+'BALANCE SHEET'!E9)/'BALANCE SHEET'!E34 -> 0.29488689 | G16: =AVERAGE(D16:F16) -> 0.36419106
A18: Leverage Ratio | B18: Leverage Ratio | C18: Formula | D18: Column3 | E18: Column4 | F18: Column5 | G18: Column6
B19: Debt to Assets Ratio | C19: Liabilities/Asset | D19: =('BALANCE SHEET'!C34+'BALANCE SHEET'!C39)/'BALANCE SHEET'!C26 -> 0.098885014 | E19: =('BALANCE SHEET'!D34+'BALANCE SHEET'!D39)/'BALANCE SHEET'!D26 -> 0.068896315 | F19: =('BALANCE SHEET'!E34+'BALANCE SHEET'!E39)/'BALANCE SHEET'!E26 -> 0.20703653 | G19: =AVERAGE(D19:F19) -> 0.12493929
B20: Debt to Equity Ratio | C20: Liabilities/Equity | D20: =('BALANCE SHEET'!C34+'BALANCE SHEET'!C39)/'BALANCE SHEET'!C48 -> 0.11091543 | E20: =('BALANCE SHEET'!D34+'BALANCE SHEET'!D39)/'BALANCE SHEET'!D48 -> 0.073834065 | F20: =('BALANCE SHEET'!E34+'BALANCE SHEET'!E39)/'BALANCE SHEET'!E48 -> 0.25890453 | G20: =AVERAGE(D20:F20) -> 0.14788468
B21: Capitalization Ratio | C21: LTD/(LTD+Equity) | D21: ='BALANCE SHEET'!C37/('BALANCE SHEET'!C37+'BALANCE SHEET'!C48) -> 0 | E21: ='BALANCE SHEET'!D37/('BALANCE SHEET'!D37+'BALANCE SHEET'!D48) -> 0 | F21: ='BALANCE SHEET'!E37/('BALANCE SHEET'!E37+'BALANCE SHEET'!E48) -> 0 | G21: =AVERAGE(D21:F21) -> 0
B22: Interest Coverage | C22: EBIT/Interest Expense | D22: =IFERROR(ABS('INCOME STATEMENT'!C22/'INCOME STATEMENT'!C27),0) -> 41.83129 | E22: =IFERROR(ABS('INCOME STATEMENT'!D22/'INCOME STATEMENT'!D27),0) -> 668.82503 | F22: =IFERROR(ABS('INCOME STATEMENT'!E22/'INCOME STATEMENT'!E27),0) -> 2400.5873 | G22: =AVERAGE(D22:F22) -> 1037.0812
B23: Equity to Total Asset | D23: ='BALANCE SHEET'!C48/'BALANCE SHEET'!C26 -> 0.89153526 | E23: ='BALANCE SHEET'!D48/'BALANCE SHEET'!D26 -> 0.93312369 | F23: ='BALANCE SHEET'!E48/'BALANCE SHEET'!E26 -> 0.79966359 | G23: =AVERAGE(D23:F23) -> 0.87477418
A25: Cash Flow Indicator | B25: Cash Flow Indicator | C25: Column2 | D25: Column3 | E25: Column4 | F25: Column5 | G25: Column6
B26: Operating Cash Flow/Sales | C26: Operating Cash Flow/Sales | D26: ='CASH FLOW STATEMENT'!C11/'INCOME STATEMENT'!C6 -> 0.23858597 | E26: ='CASH FLOW STATEMENT'!D11/'INCOME STATEMENT'!D6 -> 0.062213747 | F26: ='CASH FLOW STATEMENT'!E11/'INCOME STATEMENT'!E6 -> 0.31037228 | G26: =AVERAGE(D26:F26) -> 0.203724
B27: FCF/Operating Cash Ratio | C27: FCF/Operating Cash Flow | D27: =FCF!C20/'CASH FLOW STATEMENT'!C11 -> -3.4984797 | E27: =FCF!D20/'CASH FLOW STATEMENT'!D11 -> 0.74069757 | F27: =FCF!E20/'CASH FLOW STATEMENT'!E11 -> 0.98813098 | G27: =AVERAGE(D27:F27) -> -0.58988372
B28: Short Term Debt Coverage | C28: Operating Cash Flow/Bank Loan Short Term | D28: =IFERROR('CASH FLOW STATEMENT'!C11/'BALANCE SHEET'!C30,0) -> 0 | E28: =IFERROR('CASH FLOW STATEMENT'!D11/'BALANCE SHEET'!D30,0) -> 0 | F28: =IFERROR('CASH FLOW STATEMENT'!E11/'BALANCE SHEET'!E30,0) -> 0 | G28: =AVERAGE(D28:F28) -> 0
B30: Capex Coverage | C30: Operating CF/Capex | D30: =IFERROR(ABS('CASH FLOW STATEMENT'!C11/'CASH FLOW STATEMENT'!C17),0) -> 0.21889965 | E30: =IFERROR(ABS('CASH FLOW STATEMENT'!D11/'CASH FLOW STATEMENT'!D17),0) -> 4.7413328 | F30: =IFERROR(ABS('CASH FLOW STATEMENT'!E11/'CASH FLOW STATEMENT'!E17),0) -> 0 | G30: =AVERAGE(D30:F30) -> 1.6534108

Sheet KEY DRIVERS
A1: =HOME!B4 -> Makmur Jaya Sejati Raya
A2: Key Drivers
A3: Asumsi-asumsi dari Key Drivers Proyeksi Kinerja Keuangan
A4: ='BALANCE SHEET'!A3 -> (IDR)
D6: ='INCOME STATEMENT'!E5+1 -> 2022 | E6: =D6+1 -> 2023 | F6: =E6+1 -> 2024 | G6: =F6+1 -> 2025 | H6: =G6+1 -> 2026 | I6: =H6+1 -> 2027 | J6: =I6+1 -> 2028
A7: Financial Drivers
A8: Interest Rate (Short Term Loan) | C8: 0.14
A9: Interest Rate (Long Term Loan) | C9: 0.12 | M9: tidak usah terlalu dipikirin
A10: Bank Deposit Rate | C10: 0.09
A11: Corporate Tax Rate | C11: 0.22
A13: Operational Drivers
A14: Sales Vol. | C14: unit | D14: 1091700 | E14: =ROUND(D14*(1+E15),-2) -> 1146300 | F14: =ROUND(E14*(1+F15),-2) -> 1260900 | G14: =ROUND(F14*(1+G15),-2) -> 1387000 | H14: =ROUND(G14*(1+H15),-2) -> 1525700 | I14: =ROUND(H14*(1+I15),-2) -> 1678300 | J14: =ROUND(I14*(1+J15),-2) -> 1846100 | M14: tanya manajemen
B15: Increment | E15: 0.05 | F15: 0.1 | G15: 0.1 | H15: 0.1 | I15: 0.1 | J15: 0.1
A17: Sales Price | C17: IDR/unit | D17: 111000 | E17: =ROUNDUP(D17*(1+E18),-3) -> 117000 | F17: =ROUNDUP(E17*(1+F18),-3) -> 123000 | G17: =ROUNDUP(F17*(1+G18),-3) -> 130000 | H17: =ROUNDUP(G17*(1+H18),-3) -> 137000 | I17: =ROUNDUP(H17*(1+I18),-3) -> 144000 | J17: =ROUNDUP(I17*(1+J18),-3) -> 152000
B18: Increment | E18: 0.05 | F18: 0.05 | G18: 0.05 | H18: 0.05 | I18: 0.05 | J18: 0.05 | M18: tanya manajemen
A20: Cost of Goods Sold | C20: %/revenue | D20: ='INCOME STATEMENT'!J7 -> -0.68239332 | E20: =D20 -> -0.68239332 | F20: =E20 -> -0.68239332 | G20: =F20 -> -0.68239332 | H20: =G20 -> -0.68239332 | I20: =H20 -> -0.68239332 | J20: =I20 -> -0.68239332
A22: Operating expense
B23: Selling | C23: %/revenue | D23: ='INCOME STATEMENT'!J12 -> 0 | E23: =D23 -> 0 | F23: =E23 -> 0 | G23: =F23 -> 0 | H23: =G23 -> 0 | I23: =H23 -> 0 | J23: =I23 -> 0 | M23: tanya manajemen, lihat common size, forecasting statistik
B24: G & A | C24: inflation | D24: ='INCOME STATEMENT'!J13 -> -0.15644218 | E24: =D24 -> -0.15644218 | F24: =E24 -> -0.15644218 | G24: =F24 -> -0.15644218 | H24: =G24 -> -0.15644218 | I24: =H24 -> -0.15644218 | J24: =I24 -> -0.15644218
A26: Balance Sheet Drivers
A27: Working Capital:
B28: Acc. Receivable | C28: days | D28: 35 | E28: 35 | F28: 35 | G28: 35 | H28: 35 | I28: 35 | J28: 35
B29: Inventory | C29: days | D29: 50 | E29: 50 | F29: 50 | G29: 50 | H29: 50 | I29: 50 | J29: 50
B30: Account Payable | C30: days | D30: 90 | E30: 90 | F30: 90 | G30: 90 | H30: 90 | I30: 90 | J30: 90
A32: Additional Capex
B33: Land
B34: Building
B35: Equipment | D35: 1000 | E35: 1000 | F35: 1000 | G35: 1000 | H35: 1000 | I35: 1000 | J35: 1000
B36: Others | D36: 500 | E36: 500 | F36: 500 | G36: 500 | H36: 500 | I36: 500 | J36: 500
A37: Total Additional Capex | D37: =SUM(D35:D36) -> 1500 | E37: =SUM(E35:E36) -> 1500 | F37: =SUM(F35:F36) -> 1500 | G37: =SUM(G35:G36) -> 1500 | H37: =SUM(H35:H36) -> 1500 | I37: =SUM(I35:I36) -> 1500 | J37: =SUM(J35:J36) -> 1500

Sheet NOPLAT
A1: =HOME!B4 -> Makmur Jaya Sejati Raya
A2: NOPLAT
A3: ='BALANCE SHEET'!A3 -> (IDR)
C5: ='ACC PAYABLES'!C5 -> 2019 | D5: ='ACC PAYABLES'!D5 -> 2020 | E5: ='ACC PAYABLES'!E5 -> 2021
A7: Profit Before Tax | C7: ='INCOME STATEMENT'!C32 -> 746079045 | D7: ='INCOME STATEMENT'!D32 -> 920799279 | E7: ='INCOME STATEMENT'!E32 -> 2274234874
A8: Add: Interest Expenses | C8: ='INCOME STATEMENT'!C27*-1 -> 16278814 | D8: ='INCOME STATEMENT'!D27*-1 -> 1361128 | E8: ='INCOME STATEMENT'!E27*-1 -> 942033
A9: Less: Interest Income | C9: ='INCOME STATEMENT'!C26*-1 -> -81394069 | D9: ='INCOME STATEMENT'!D26*-1 -> -11803933 | E9: ='INCOME STATEMENT'!E26*-1 -> -13957341
A10: Non Operating Income | C10: ='INCOME STATEMENT'!C30*-1 -> 0 | D10: ='INCOME STATEMENT'!D30*-1 -> 0 | E10: ='INCOME STATEMENT'!E30*-1 -> 212875
A11: EBIT | C11: =SUM(C7:C10) -> 680963790 | D11: =SUM(D7:D10) -> 910356474 | E11: =SUM(E7:E10) -> 2261432441
A13: Statutory Tax on EBIT | C13: =C11*STAT_ASSUMPTIONS!$B$5 -> 1.4981203e+08 | D13: =D11*STAT_ASSUMPTIONS!$B$5 -> 2.0027842e+08 | E13: =E11*STAT_ASSUMPTIONS!$B$5 -> 4.9751514e+08
A14: Tax Shield on Interest Expenses (excluded) | C14: =0 -> 0 | D14: =0 -> 0 | E14: =0 -> 0
A15: Tax on Interest Income (excluded) | C15: =0 -> 0 | D15: =0 -> 0 | E15: =0 -> 0
A16: Tax on Non Operating Income (excluded) | C16: =0 -> 0 | D16: =0 -> 0 | E16: =0 -> 0
A17: Total Taxes on EBIT | C17: =SUM(C13:C16) -> 1.4981203e+08 | D17: =SUM(D13:D16) -> 2.0027842e+08 | E17: =SUM(E13:E16) -> 4.9751514e+08
A19: NOPLAT | C19: =C11-C17 -> 5.3115176e+08 | D19: =D11-D17 -> 7.1007805e+08 | E19: =E11-E17 -> 1.7639173e+09

Sheet FCF
A1: =HOME!B4 -> Makmur Jaya Sejati Raya
A2: Free Cash Flow
A3: ='BALANCE SHEET'!A3 -> (IDR)
C5: =NOPLAT!C5 -> 2019 | D5: =NOPLAT!D5 -> 2020 | E5: =NOPLAT!E5 -> 2021
A7: NOPLAT | C7: =NOPLAT!C19 -> 5.3115176e+08 | D7: =NOPLAT!D19 -> 7.1007805e+08 | E7: =NOPLAT!E19 -> 1.7639173e+09
A8: Add: Depreciation | C8: ='FIXED ASSET'!C51 -> 353481575 | D8: ='FIXED ASSET'!D51 -> 1120799028 | E8: ='FIXED ASSET'!E51 -> 981730341
A9: Gross Cash Flow | C9: =+C7+C8 -> 8.8463333e+08 | D9: =+D7+D8 -> 1.8308771e+09 | E9: =+E7+E8 -> 2.7456476e+09
A11: Changes in Working Capital
A12: (Increase) Decrease in Current Asset | C12: ='CASH FLOW STATEMENT'!C8 -> -248591028 | D12: ='CASH FLOW STATEMENT'!D8 -> -426787292 | E12: ='CASH FLOW STATEMENT'!E8 -> 484323209
A13: Increase (Decrease) in Current Liabilities | C13: ='CASH FLOW STATEMENT'!C9 -> 1746831703 | D13: ='CASH FLOW STATEMENT'!D9 -> -728772103 | E13: ='CASH FLOW STATEMENT'!E9 -> 1880659928
A14: Total Net Changes in Working Capital | C14: ='CASH FLOW STATEMENT'!C10 -> 1498240675 | D14: ='CASH FLOW STATEMENT'!D10 -> -1155559395 | E14: ='CASH FLOW STATEMENT'!E10 -> 2364983137
A16: Less: Capital Expenditures | C16: ='FIXED ASSET'!C23*-1 -> -10175220000 | D16: ='FIXED ASSET'!D23*-1 -> -149675000 | E16: ='FIXED ASSET'!E23*-1 -> 0
A18: Gross Investment | C18: =+C14+C16 -> -8676979325 | D18: =+D14+D16 -> -1305234395 | E18: =+E14+E16 -> 2364983137
A20: Free Cash Flow | C20: =+C9+C18 -> -7.792346e+09 | D20: =+D9+D18 -> 5.2564268e+08 | E20: =+E9+E18 -> 5.1106308e+09

Sheet ROIC
A1: =HOME!B4 -> Makmur Jaya Sejati Raya
A2: ROIC
A3: ='BALANCE SHEET'!A3 -> (IDR)
B5: ='BALANCE SHEET'!C4 -> 2019 | C5: =B5+1 -> 2020 | D5: =C5+1 -> 2021
A7: NOPLAT | B7: =FCF!C20 -> -7.792346e+09 | C7: =FCF!D20 -> 5.2564268e+08 | D7: =FCF!E20 -> 5.1106308e+09
A8: Total Asset in Balance Sheet | B8: ='BALANCE SHEET'!C26 -> 18670530628 | C8: ='BALANCE SHEET'!D26 -> 18410375024 | D8: ='BALANCE SHEET'!E26 -> 17278293031
A9: Less Non Operating Fixed Assets *) | B9: 0 | C9: 0 | D9: 0 | F9: Non-operating fixed assets remain zero unless idle assets are specifically identified.
A10: Less Excess Cash / Cash and Deposit **) | B10: =('BALANCE SHEET'!C8+'BALANCE SHEET'!C9)*-1 -> -419027837 | C10: =('BALANCE SHEET'!D8+'BALANCE SHEET'!D9)*-1 -> -723908969 | D10: =('BALANCE SHEET'!E8+'BALANCE SHEET'!E9)*-1 -> -1054880526 | F10: Cash and bank/deposit treated as excess cash; minimum operating cash remains a judgment sensitivity.
A11: Less Marketable Securities | B11: 0 | C11: 0 | D11: 0
A12: Total Invested Capital at End of Year | B12: =SUM(B8:B11) -> 18251502791 | C12: =SUM(C8:C11) -> 17686466055 | D12: =SUM(D8:D11) -> 16223412505
A13: Total Invested Capital at Beginning of Year | C13: =B12 -> 18251502791 | D13: =C12 -> 17686466055
A15: ROIC = NOPLAT/Inves Capital Beginning of Year | C15: =C7/C13 -> 0.028799967 | D15: =D7/D13 -> 0.28895715
A18: Catatan
A19: *)Book Value Asset yang menganggur (idle) tidak digunakan untuk operasional
A20: **)Asumsi Idle Cash tiap tahun

Sheet KUISIONER
A1: DAFTAR PERTANYAAN UNTUK WAJIB PAJAK
A2: ="Asumsi kondisi "&HOME!B4&" pada saat tanggal Penilaian ("&TEXT(HOME!B20,"dd/mm/yyyy")&")" -> Asumsi kondisi Makmur Jaya Sejati Raya pada saat tanggal Penilaian (31/12/2021)
A5: No. | B5: Pertanyaan
A6: 1 | B6: Apakah terdapat perjanjian dari pemegang saham yang mengatur posisi dalam susunan manajemen perusahaan yang akan menjalankan perusahaan tanpa melihat jumlah kepemilikan saham ?
B7: Jawaban:
B8: a. Ada
B9: b. Tidak ada
A11: 2 | B11: Besarnya kerugian pemegang saham minoritas dari perusahaan tertutup apabila dibandingkan dengan pemegang saham minoritas perusahaan terbuka ?
B12: Jawaban:
B13: a. Rendah
B14: b. Sedang
B15: c. Tinggi
A17: 3 | B17: Hal-hal yang dilakukan oleh pemegang saham pengendali terhadap perusahaan yang dikendalikan untuk membuat saham yang dimilikinya lebih menguntungkan ?
B18: Jawaban:
B19: a. Rendah
B20: b. Moderat
B21: c. Dominan
A23: 4 | B23: Apakah manajemen perusahaan ditunjuk oleh pemegang saham mayoritas ?
B24: Jawaban:
B25: a. Tidak ada
B26: b. Sebagian
B27: c. Seluruhnya
A29: 5 | B29: Apakah pemegang saham mayoritas sebagai pengendali operasional perusahaan ?
B30: Jawaban:
B31: a. Tidak
B32: b. Sebagian
B33: c. Ya
A35: 6 | B35: Apakah telah ada pembatasan atas perijinan usaha, namun banyak investor yang berminat disebabkan prospek usaha dibidang industri tersebut memiliki prospek yang cerah ?
B36: Jawaban:
B37: a. Ada
B38: b. Terbatas
B39: c. Tidak ada
A41: 7 | B41: Apakah untuk industri tersebut membutuhkan skala ekonomis usaha yang besar, sehingga hanya investor tertentu dengan modal besar yang dapat masuk dibidang industri tersebut ?
B42: Jawaban:
B43: a. Tidak terbatas
B44: b. Segmen tertentu
B45: c. Skala besar
A47: 8 | B47: Apakah kebijakan dividen perusahaan telah diputuskan setiap tahun melalui RUPS, serta ada pembagian dividen setiap tahun ?
B48: Jawaban:
B49: a. Ya
B50: b. Kadang-kadang
B51: c. Tidak ada
A53: 9 | B53: Apakah tingkat profitabilitas (EBITDA) perusahaan sesuai dengan tingkat profitabilitas industri sejenis ?
B54: Jawaban:
B55: a. Di atas
B56: b. Rata-rata
B57: c. Di bawah
A59: 10 | B59: Apakah laba bersih perusahaan berfluktuasi ?
B60: Jawaban:
B61: a. Cenderung meningkat
B62: b. Sedang, stabil
B63: c. Fluktuatif/Menurun
A65: 11 | B65: Apakah struktur permodalan (debt to equity ratio) perusahaan sesuai dengan rata-rata industri sejenis ?
B66: Jawaban:
B67: a. Di atas
B68: b. Rata-rata
B69: c. Di bawah
A71: 12 | B71: Apakah liquiditas (current ratio) perusahaan sesuai dengan rata-rata industri sejenis ?
B72: Jawaban:
B73: a. Di atas
B74: b. Rata-rata
B75: c. Di bawah
A77: 13 | B77: Pertumbuhan penjualan perusahaan dibandingkan dengan rata-rata industri sejenis ?
B78: Jawaban:
B79: a. Lebih besar
B80: b. Rata-rata
B81: c. Lebih kecil
A83: 14 | B83: Bagaimana Prospek perusahaan maupun industrinya dimasa mendatang ?
B84: Jawaban:
B85: a. Meningkat
B86: b. Seperti saat ini
B87: c. Menurun
A89: 15 | B89: Apakah kualitas manajemen perusahaan dapat mencapai tingkat keberhasilan operasi dan keuangan perusahaan serta mempunyai probabilitas yang tinggi untuk memperoleh hasil yang diharapkan ?
B90: Jawaban:
B91: a. Ya
B92: b. Seperti saat ini
B93: c. Tidak
A95: 16 | B95: Apakah Perusahaan memiliki pelanggan lebih dari 1 ?
B96: Jawaban:
B97: a. Tidak, hanya 1
B98: b. Ya
A100: 17 | B100: Apakah pada saat pendirian perusahaan ada rencana pembubaran pada jangka waktu tertentu
B101: Jawaban:
B102: a. Tidak ada
B103: b. Ada, pada…..............................................
A105: 18 | B105: Apakah kontrak kerja yang pernah didapatkan selama ini, secara historis dapat dilakukan perpanjangan kontrak?
B106: Jawaban:
B107: a. Tidak dapat diperpanjang
B108: b. Dapat diperpanjang
A110: 19 | B110: Apakah kontrak kerja yang sedang berlangsung sekarang (pada tanggal penilaian) berakhir, tidak dapat diperpanjang ?
B111: Jawaban:
B112: a. Tidak dapat diperpanjang
B113: b. Dapat diperpanjang
A115: 20 | B115: Apabila Jawaban nomor 19 adalah tidak dapat diperpanjang, apakah Perusahaan akan mencari kontrak kerja lain ?
B116: Jawaban:
B117: a. Ya
B118: b. Tidak
A120: 21 | B120: Apabila Jawaban nomor 20 adalah tidak, apakah Perusahaan akan ditutup ?
B121: Jawaban:
B122: a. Ya
...

Sheet DLOC(PFC)
A2: PERTIMBANGAN PREMI FOR CONTROL (PFC)
A4: NO | B4: FAKTOR PERTIMBANGAN | C4: KONDISI PERUSAHAAN DENGAN PEMEGANG SAHAM | D4: KONFIRMASI | E4: NILAI KENDALI
A7: 1 | B7: Perjanjian antara Pemegang Saham | C7: Apakah terdapat perjanjian dari pemegang saham yang mengatur posisi dalam susunan manajemen perusahaan yang akan menjalankan perusahaan tanpa melihat jumlah kepemilikan saham? (Ada/Tidak Ada) | E7: Ada | F7: =IF(E7="Ada",0,1) -> 0 | H7: Ada | I7: Rendah | J7: Rendah | K7: Tidak Ada | L7: Tidak
H8: Tidak Ada | I8: Sedang | J8: Moderat | K8: Sebagian | L8: Sebagian
A9: 2 | B9: Kerugian Saham Minoritas | C9: Besarnya kerugian pemegang saham minoritas dari perusahaan tertutup apabila dibandingkan dengan pemegang saham minoritas perusahaan terbuka? (Rendah, Sedang atau Tinggi) | E9: Rendah | F9: =IF(E9="Rendah",0,IF(E9="Sedang",0.5,1)) -> 0 | I9: Tinggi | J9: Dominan | K9: Seluruhnya | L9: Ya
A11: 3 | B11: Pemegang Saham Pengendali | C11: Hal-hal yang dilakukan oleh pemegang saham pengendali terhadap perusahaan yang dikendalikan untuk membuat saham yang dimilikinya lebih menguntungkan? (Rendah, Moderat atau Dominan) | E11: Rendah | F11: =IF(E11="Rendah",0,IF(E11="Moderat",0.5,1)) -> 0
A13: 4 | B13: Penunjukkan Manajemen | C13: Apakah manajemen perusahaan ditunjuk oleh pemegang saham mayoritas? (Tidak Ada, Sebagian atau Seluruhnya) | E13: Sebagian | F13: =IF(E13="Tidak Ada",0,IF(E13="Sebagian",0.5,1)) -> 0.5
A15: 5 | B15: Pengendalian Operasional Perusahaan | C15: Apakah pemegang saham mayoritas sebagai pengendali operasional perusahaan? (Tidak, Sebagian atau Ya) | E15: Tidak | F15: =IF(E15="Tidak",0,IF(E15="Sebagian",0.5,1)) -> 0
A17: JUMLAH | F17: =SUM(F7:F16) -> 0.5
C19: ="Perhitungan"&" "&E20 -> Perhitungan DLOC
A20: =IF(B20="DLOC Perusahaan tertutup ",1,2) -> 1 | B20: =IF(HOME!B7="tertutup","DLOC Perusahaan tertutup ","DLOC Perusahaan terbuka ") -> DLOC Perusahaan tertutup | C20: Jenis Kepemilikan Saham yang Dinilai | E20: =IF(HOME!B12="Minoritas","DLOC","PFC") -> DLOC
A21: =IF(B31="Minoritas",5,7) -> 7 | B21: Mayoritas
B22: =IF(A20=1," 30% - 70%"," 20% - 35%") -> 30% - 70% | C22: Maksimum Skor | E22: 5
C23: =E20&" "&"Perusahaan Tertutup 30% - 70%" -> DLOC Perusahaan Tertutup 30% - 70% | E23: =RIGHT(B22,3)-LEFT(B22,4) -> 0.4
C24: Jumlah Skor | E24: =F17 -> 0.5
C25: Persentase Perhitungan | E25: =LEFT(B22,4)+(E24/E22*E23) -> 0.34
C26: =E20&" "&"Objek Penilaian" -> DLOC Objek Penilaian | E26: =IF(E20="DLOC",E25,(E25*-1)) -> 0.34
C27: ="Status"&" "&C26 -> Status DLOC Objek Penilaian | E27: =IF(AND(E26<=-30%, E26>=-43%), "Rendah", IF(AND(E26<=-44%, E26>=-57%), "Moderat", IF(AND(E26<=-58%, E26>=-70%), "Tinggi", IF(AND(E26>=30%, E26<=43%), "Rendah", IF(AND(E26>=44%, E26<=57%), "Moderat", IF(AND(E26>=58%, E26<=70%), "Tinggi", "-")))))) -> Rendah
C28: Potensi Resistensi Wajib Pajak | E28: =IF(AND(E27="Rendah", E26>0), "Tinggi", IF(AND(E27="Rendah", E26<0), "Rendah", IF(E27="Moderat", "Moderat", IF(AND(E27="Tinggi", E26>0), "Rendah", IF(AND(E27="Tinggi", E26<0), "Tinggi", "-"))))) -> Tinggi
D31: DLOC
C32: Rendah | D32: 30%-43%
C33: Moderat | D33: 44%-57%
C34: Tinggi | D34: 58%-70%
D36: PFC
C37: Rendah | D37: -30%-43%
C38: Moderat | D38: -44%-57%
C39: Tinggi | D39: -58%-70%

Sheet DLOM
B2: PERTIMBANGAN DISCOUNT LACK OF MARKETABILITY (DLOM)
B4: NO | C4: FAKTOR PERTIMBANGAN | D4: KONDISI PERUSAHAAN DALAM INDUSTRI | E4: KONFIRMASI | F4: NILAI MAKETABILITAS
B7: 1 | C7: Entry Barier Perijinan Usaha | D7: Apakah telah ada pembatasan atas perijinan usaha, namun banyak investor yang berminat disebabkan prospek usaha dibidang industri tersebut memiliki prospek yang cerah? (Ada, Terbatas atau Tidak Ada) | F7: Ada | G7: =IF(F7="Ada",0,IF(F7="Terbatas",0.5,1)) -> 0 | I7: Ada | J7: Tidak Terbatas | K7: Ya | L7: Diatas | M7: Tidak, Meningkat
I8: Terbatas | J8: Segmen Tertentu | K8: Kadang-kadang | L8: Rata-rata | M8: Sedang, Stabil
B9: 2 | C9: Entry Barier Skala Ekonomis Usaha | D9: Apakah untuk industri tersebut membutuhkan skala ekonomis usaha yang besar, sehingga hanya investor tertentu dengan modal besar yang dapat masuk dibidang industri tersebut? (Tidak Terbatas, Segmen Tertentu atau Skala Besar) | F9: Segmen Tertentu | G9: =IF(F9="Tidak Terbatas",0,IF(F9="Segmen Tertentu",0.5,1)) -> 0.5 | I9: Tidak Ada | J9: Skala Besar | K9: Tidak Ada | L9: Dibawah | M9: Ya, Menurun
B11: 3 | C11: Dividen | D11: Apakah kebijakan dividen perusahaan telah diputuskan setiap tahun melalui RUPS, serta ada pembagian dividen setiap tahun? (Ya, Kadang-kadang atau Tidak Ada) | F11: Kadang-kadang | G11: =IF(F11="Ya",0,IF(F11="Kadang-kadang",0.5,1)) -> 0.5 | I11: Dibawah | J11: Diatas | K11: Lebih Besar | L11: Meningkat | M11: Ya
I12: Rata-rata | J12: Rata-rata | K12: Rata-rata | L12: Seperti Saat Ini | M12: Seperti Saat Ini
B13: 4 | C13: Profitabilitas (EBITDA) | D13: Apakah tingkat profitabilitas (EBITDA) perusahaan sesuai dengan tingkat profitabilitas industri sejenis? (Diatas, Rata-Rata atau Dibawah) | F13: Diatas | G13: =IF(F13="Diatas",0,IF(F13="Rata-rata",0.5,1)) -> 0 | I13: Diatas | J13: Dibawah | K13: Lebih Kecil | L13: Menurun | M13: Tidak
B15: 5 | C15: Fluktuasi Laba Bersih | D15: Apakah laba bersih perusahaan berfluktuasi? (Tidak, Meningkat; Sedang, Stabil; atau, Ya, Menurun) | F15: Tidak, Meningkat | G15: =IF(F15="Tidak, Meningkat",0,IF(F15="Sedang, Stabil",0.5,1)) -> 0
B17: 6 | C17: Struktur Permodalan | D17: Apakah struktur permodalan (Debt to Equity Ratio) perusahaan sesuai dengan rata-rata industri sejenis? (Dibawah, Rata-Rata atau Diatas) | F17: Rata-rata | G17: =IF(F17="Dibawah",0,IF(F17="Rata-rata",0.5,1)) -> 0.5
B19: 7 | C19: Liquiditas | D19: Apakah liquiditas (Current Ratio) perusahaan sesuai dengan rata-rata industri sejenis? (Diatas, Rata-Rata atau Dibawah) | F19: Rata-rata | G19: =IF(F19="Diatas",0,IF(F19="Rata-rata",0.5,1)) -> 0.5
B21: 8 | C21: Pertumbuhan Penjualan | D21: Pertumbuhan penjualan perusahaan dibandingkan dengan rata-rata industri sejenis? (Lebih Besar, Rata-Rata atau Lebih Kecil) | F21: Lebih Besar | G21: =IF(F21="Lebih Besar",0,IF(F21="Rata-rata",0.5,1)) -> 0
B23: 9 | C23: Prospek Perusahaan dan Industri | D23: Bagaimana Prospek perusahaan maupun industrinya dimasa mendatang? (Meningkat, Seperti saat ini atau Menurun) | F23: Seperti Saat Ini | G23: =IF(F23="Meningkat",0,IF(F23="Seperti Saat Ini",0.5,1)) -> 0.5
B25: 10 | C25: Kualitas Manajemen | D25: Apakah kualitas manajemen perusahaan dapat mencapai tingkat keberhasilan operasi dan keuangan perusahaan serta mempunyai probabilitas yang tinggi untuk memperoleh hasil yang diharapkan? (Ya, Seperti Saat Ini atau Tidak) | F25: Ya | G25: =IF(F25="Ya",0,IF(F25="Seperti Saat Ini",0.5,1)) -> 0
B27: JUMLAH | G27: =SUM(G7:G26) -> 2.5
B30: =IF(C30="DLOM Perusahaan tertutup ",1,2) -> 1 | C30: DLOM Perusahaan tertutup | D30: Perhitungan DLOM
B31: =IF(C31="Minoritas",5,7) -> 7 | C31: Mayoritas | D31: Maksimum Skor | F31: 10
C32: =IF(B30+B31=6,"30% - 50%",IF(B30+B31=8,"20% - 40%",IF(B30+B31=7,"10% - 30%",IF(B30+B31=9,"0% - 20%","-")))) -> 20% - 40% | D32: =C30&C32 -> DLOM Perusahaan tertutup 20% - 40% | F32: =RIGHT(C32,3)-LEFT(C32,3) -> 0.2
D33: Jumlah Skor | F33: =G27 -> 2.5
D34: DLOM Objek Penilaian | F34: =LEFT(C32,3)+(F33/F31*F32) -> 0.25
D35: Status DLOM Objek Penilaian | F35: =IF(AND(F34>=20%, F34<=26%), C38, IF(AND(F34>=27%, F34<=33%), C39, IF(AND(F34>=34%, F34<=40%), C40, ""))) -> Rendah
D36: Potensi Resistensi Wajib Pajak | F36: =IF(F35="Rendah","Tinggi",IF(F35="Moderat","Moderat","Rendah")) -> Tinggi
C38: Rendah | D38: 20%-26%
C39: Moderat | D39: 27%-33%
C40: Tinggi | D40: 34%-40%

Sheet TL
N2: Cuti Off Date
P9: SUBSEQUENT EVENT
C10: ='BALANCE SHEET'!D4 -> 2020 | H10: ? | L10: ='BALANCE SHEET'!E4 -> 2021 | Q10: =L10+1 -> 2022
C11: Net Profit | D11: ='INCOME STATEMENT'!D35 -> 754862153 | H11: Net Profit | L11: Net Profit | M11: ='INCOME STATEMENT'!E35 -> 1838106527 | Q11: Net Profit | R11: =1341033576-379554295 -> 961479281
C12: Ekuitas | D12: ='BALANCE SHEET'!D48 -> 17179157089 | H12: Ekuitas | L12: Ekuitas | M12: ='BALANCE SHEET'!E48 -> 13816821754 | Q12: Ekuitas | R12: 14328714899
C13: DER | D13: ='FINANCIAL RATIO'!E20 -> 0.073834065 | H13: DER | L13: DER | M13: ='FINANCIAL RATIO'!F20 -> 0.25890453 | Q13: DER | R13: =1741793728/R12 -> 0.12155966
C14: NPM | D14: ='FINANCIAL RATIO'!E9 -> 0.066176578 | H14: NPM | L14: NPM | M14: ='FINANCIAL RATIO'!F9 -> 0.1103046 | Q14: NPM | R14: =R11/15069211620 -> 0.063804219

Sheet DASHBOARD
M2: HISTORIS | U2: PROYEKSI
R50: Cuti Off Date
T57: SUBSEQUENT EVENT
G58: =TL!C10 -> 2020 | L58: =TL!H10 -> ? | P58: =TL!L10 -> 2021 | U58: =P58+1 -> 2022
G59: Net Profit | H59: =TL!D11 -> 754862153 | L59: =TL!H11 -> Net Profit | M59: =TL!I11 -> 0 | P59: Net Profit | Q59: =TL!M11 -> 1838106527 | U59: Net Profit | V59: =TL!R11 -> 961479281
G60: Ekuitas | H60: =TL!D12 -> 17179157089 | L60: =TL!H12 -> Ekuitas | M60: =TL!I12 -> 0 | P60: Ekuitas | Q60: =TL!M12 -> 13816821754 | U60: Ekuitas | V60: =TL!R12 -> 14328714899
G61: DER | H61: =TL!D13 -> 0.073834065 | L61: =TL!H13 -> DER | M61: =TL!I13 -> 0 | P61: DER | Q61: =TL!M13 -> 0.25890453 | U61: DER | V61: =TL!R13 -> 0.12155966
G62: NPM | H62: =TL!D14 -> 0.066176578 | L62: =TL!H14 -> NPM | M62: =TL!I14 -> 0 | P62: NPM | Q62: =TL!M14 -> 0.1103046 | U62: NPM | V62: =TL!R14 -> 0.063804219

Sheet RESUME
A1: Accounts | B1: =C1-1 -> 2018 | C1: ='BALANCE SHEET'!C4 -> 2019 | D1: ='BALANCE SHEET'!D4 -> 2020 | E1: ='BALANCE SHEET'!E4 -> 2021 | F1: ='PROY BALANCE SHEET'!D5&"P" -> 2022P | G1: ='PROY BALANCE SHEET'!E5&"P" -> 2023P | H1: ='PROY BALANCE SHEET'!F5&"P" -> 2024P
A2: Current Assets | B2: 0 | C2: ='BALANCE SHEET'!C15 -> 706318865 | D2: ='BALANCE SHEET'!D15 -> 1417287289 | E2: ='BALANCE SHEET'!E15 -> 1266935637 | F2: ='PROY BALANCE SHEET'!D21 -> 2.8042595e+09 | G2: ='PROY BALANCE SHEET'!E21 -> 7.3448411e+09 | H2: ='PROY BALANCE SHEET'!F21 -> 2.0971058e+10
A3: Total Non Current Asset | B3: 0 | C3: ='BALANCE SHEET'!C24 -> 17964211763 | D3: ='BALANCE SHEET'!D24 -> 16993087735 | E3: ='BALANCE SHEET'!E24 -> 16011357394 | F3: ='PROY BALANCE SHEET'!D31 -> 1.5147877e+10 | G3: ='PROY BALANCE SHEET'!E31 -> 1.4388089e+10 | H3: ='PROY BALANCE SHEET'!F31 -> 1.3719242e+10
A4: ASSETS | B4: 0 | C4: ='BALANCE SHEET'!C26 -> 18670530628 | D4: ='BALANCE SHEET'!D26 -> 18410375024 | E4: ='BALANCE SHEET'!E26 -> 17278293031 | F4: ='PROY BALANCE SHEET'!D33 -> 1.7952136e+10 | G4: ='PROY BALANCE SHEET'!E33 -> 2.173293e+10 | H4: ='PROY BALANCE SHEET'!F33 -> 3.4690299e+10
A5: Current Liabilities | B5: 0 | C5: ='BALANCE SHEET'!C34 -> 1846235691 | D5: ='BALANCE SHEET'!D34 -> 1268407000 | E5: ='BALANCE SHEET'!E34 -> 3577237782 | F5: ='PROY BALANCE SHEET'!D45 -> 5.8050923e+09 | G5: ='PROY BALANCE SHEET'!E45 -> 9.7242321e+09 | H5: ='PROY BALANCE SHEET'!F45 -> 1.6799259e+10
A6: Non Current Liabilities | B6: 0 | C6: ='BALANCE SHEET'!C39 -> 0 | D6: ='BALANCE SHEET'!D39 -> 0 | E6: ='BALANCE SHEET'!E39 -> 0 | F6: ='PROY BALANCE SHEET'!D52 -> 0 | G6: ='PROY BALANCE SHEET'!E52 -> 0 | H6: ='PROY BALANCE SHEET'!F52 -> 0
A7: LIABILITIES | B7: 0 | C7: ='BALANCE SHEET'!C40 -> 1846235691 | D7: ='BALANCE SHEET'!D40 -> 1268407000 | E7: ='BALANCE SHEET'!E40 -> 3577237782 | F7: ='PROY BALANCE SHEET'!D45+'PROY BALANCE SHEET'!D52 -> 5.8050923e+09 | G7: ='PROY BALANCE SHEET'!E45+'PROY BALANCE SHEET'!E52 -> 9.7242321e+09 | H7: ='PROY BALANCE SHEET'!F45+'PROY BALANCE SHEET'!F52 -> 1.6799259e+10
A8: Shareholders' Equity | B8: 0 | C8: ='BALANCE SHEET'!C48 -> 16645436325 | D8: ='BALANCE SHEET'!D48 -> 17179157089 | E8: ='BALANCE SHEET'!E48 -> 13816821754 | F8: ='PROY BALANCE SHEET'!D60 -> 1.5724851e+10 | G8: ='PROY BALANCE SHEET'!E60 -> 1.8299019e+10 | H8: ='PROY BALANCE SHEET'!F60 -> 2.1662562e+10
A9: LIABILITES & EQUITY | B9: 0 | C9: ='BALANCE SHEET'!C50 -> 18491672016 | D9: ='BALANCE SHEET'!D50 -> 18447564089 | E9: ='BALANCE SHEET'!E50 -> 17394059536 | F9: ='PROY BALANCE SHEET'!D62 -> 2.1529943e+10 | G9: ='PROY BALANCE SHEET'!E62 -> 2.8023252e+10 | H9: ='PROY BALANCE SHEET'!F62 -> 3.846182e+10
A10: Revenue | B10: 0 | C10: ='INCOME STATEMENT'!C6 -> 9335637236 | D10: ='INCOME STATEMENT'!D6 -> 11406787320 | E10: ='INCOME STATEMENT'!E6 -> 16663916100 | F10: ='PROY LR'!D8 -> 2.0456242e+10 | G10: ='PROY LR'!E8 -> 2.5111616e+10 | H10: ='PROY LR'!F8 -> 3.0826445e+10
A11: COGS | B11: 0 | C11: ='INCOME STATEMENT'!C7 -> -6880608086 | D11: ='INCOME STATEMENT'!D7 -> -7565752910 | E11: ='INCOME STATEMENT'!E7 -> -10779658214 | F11: ='PROY LR'!D10 -> -1.3959203e+10 | G11: ='PROY LR'!E10 -> -1.7135999e+10 | H11: ='PROY LR'!F10 -> -2.1035761e+10
A12: Gross Profit | B12: 0 | C12: ='INCOME STATEMENT'!C8 -> 2455029150 | D12: ='INCOME STATEMENT'!D8 -> 3841034410 | E12: ='INCOME STATEMENT'!E8 -> 5884257886 | F12: ='PROY LR'!D11 -> 6.4970392e+09 | G12: ='PROY LR'!E11 -> 7.9756168e+09 | H12: ='PROY LR'!F11 -> 9.7906849e+09
A13: Operating Expenses | B13: 0 | C13: ='INCOME STATEMENT'!C15 -> -1420583785 | D13: ='INCOME STATEMENT'!D15 -> -1809878908 | E13: ='INCOME STATEMENT'!E15 -> -2641095104 | F13: ='PROY LR'!D17 -> -3.2002192e+09 | G13: ='PROY LR'!E17 -> -3.928516e+09 | H13: ='PROY LR'!F17 -> -4.8225564e+09
A14: EBITDA | B14: 0 | C14: ='INCOME STATEMENT'!C18 -> 1034445365 | D14: ='INCOME STATEMENT'!D18 -> 2031155502 | E14: ='INCOME STATEMENT'!E18 -> 3243162782 | F14: ='PROY LR'!D19 -> 3.29682e+09 | G14: ='PROY LR'!E19 -> 4.0471009e+09 | H14: ='PROY LR'!F19 -> 4.9681285e+09
A15: Depreciation/Amortization | B15: 0 | C15: ='INCOME STATEMENT'!C21 -> -353481575 | D15: ='INCOME STATEMENT'!D21 -> -1120799028 | E15: ='INCOME STATEMENT'!E21 -> -981730341 | F15: ='PROY LR'!D22 -> -8.6348083e+08 | G15: ='PROY LR'!E22 -> -7.5978737e+08 | H15: ='PROY LR'!F22 -> -6.6884766e+08
A16: EBIT | B16: 0 | C16: ='INCOME STATEMENT'!C22 -> 680963790 | D16: ='INCOME STATEMENT'!D22 -> 910356474 | E16: ='INCOME STATEMENT'!E22 -> 2261432441 | F16: ='PROY LR'!D25 -> 2.4333392e+09 | G16: ='PROY LR'!E25 -> 3.2873135e+09 | H16: ='PROY LR'!F25 -> 4.2992808e+09
A17: Other Incomes/(Charges) | B17: 0 | C17: ='INCOME STATEMENT'!C28 -> 65115255 | D17: ='INCOME STATEMENT'!D28 -> 10442805 | E17: ='INCOME STATEMENT'!E28 -> 13015308 | F17: ='PROY LR'!D33 -> 13065185 | G17: ='PROY LR'!E33 -> 13115236 | H17: ='PROY LR'!F33 -> 13165460
A18: Non Operating Income | B18: 0 | C18: ='INCOME STATEMENT'!C30 -> 0 | D18: ='INCOME STATEMENT'!D30 -> 0 | E18: ='INCOME STATEMENT'!E30 -> -212875 | F18: ='PROY LR'!D34 -> -212874.09 | G18: ='PROY LR'!E34 -> -212873.19 | H18: ='PROY LR'!F34 -> -212872.28
A19: Profit Before Tax | B19: 0 | C19: ='INCOME STATEMENT'!C32 -> 746079045 | D19: ='INCOME STATEMENT'!D32 -> 920799279 | E19: ='INCOME STATEMENT'!E32 -> 2274234874 | F19: ='PROY LR'!D36 -> 2.4461915e+09 | G19: ='PROY LR'!E36 -> 3.3002158e+09 | H19: ='PROY LR'!F36 -> 4.3122334e+09
A20: Corporate Tax | B20: 0 | C20: ='INCOME STATEMENT'!C33 -> -305333971 | D20: ='INCOME STATEMENT'!D33 -> -165937126 | E20: ='INCOME STATEMENT'!E33 -> -436128347 | F20: ='PROY LR'!D37 -> -5.3816212e+08 | G20: ='PROY LR'!E37 -> -7.2604749e+08 | H20: ='PROY LR'!F37 -> -9.4869136e+08
A21: Net Profit After Tax | B21: 0 | C21: ='INCOME STATEMENT'!C35 -> 440745074 | D21: ='INCOME STATEMENT'!D35 -> 754862153 | E21: ='INCOME STATEMENT'!E35 -> 1838106527 | F21: ='PROY LR'!D39 -> 1.9080293e+09 | G21: ='PROY LR'!E39 -> 2.5741684e+09 | H21: ='PROY LR'!F39 -> 3.3635421e+09
A22: Land | C22: ='FIXED ASSET'!C63 -> 7817274315 | D22: ='FIXED ASSET'!D63 -> 7817274315 | E22: ='FIXED ASSET'!E63 -> 7817274315 | F22: ='PROY FIXED ASSETS'!D63 -> 7817274315 | G22: ='PROY FIXED ASSETS'!E63 -> 7817274315 | H22: ='PROY FIXED ASSETS'!F63 -> 7817274315
A23: Building | C23: ='FIXED ASSET'!C64 -> 408626524 | D23: ='FIXED ASSET'!D64 -> 376792768 | E23: ='FIXED ASSET'!E64 -> 340568087 | F23: ='PROY FIXED ASSETS'!D64 -> 3.0544849e+08 | G23: ='PROY FIXED ASSETS'!E64 -> 2.7140028e+08 | H23: ='PROY FIXED ASSETS'!F64 -> 2.3839075e+08
A24: Machinery, Vehicle, Fixture, FurnitUre, etc | C24: =SUM('FIXED ASSET'!C65:C68) -> 9738310924 | D24: =SUM('FIXED ASSET'!D65:D68) -> 8799020652 | E24: =SUM('FIXED ASSET'!E65:E68) -> 7853514992 | F24: =SUM('PROY FIXED ASSETS'!D65:D68) -> 7.0251538e+09 | G24: =SUM('PROY FIXED ASSETS'!E65:E68) -> 6.2994146e+09 | H24: =SUM('PROY FIXED ASSETS'!F65:F68) -> 5.6635765e+09

Sheet CFI
A1: =HOME!B4 -> Makmur Jaya Sejati Raya
A2: Cash Flow Available to Investors (CFI)
A3: ='BALANCE SHEET'!A3 -> (IDR)
E4: PROYEKSI
B5: =FCF!C5 -> 2019 | C5: =B5+1 -> 2020 | D5: =C5+1 -> 2021 | E5: =D5+1 -> 2022 | F5: =E5+1 -> 2023 | G5: =F5+1 -> 2024 | H5: =G5+1 -> 2025 | I5: =H5+1 -> 2026 | J5: =I5+1 -> 2027 | K5: =J5+1 -> 2028
A7: Free Cash Flow | B7: =FCF!C20 -> -7.792346e+09 | C7: =FCF!D20 -> 5.2564268e+08 | D7: =FCF!E20 -> 5.1106308e+09 | E7: =DCF!D20 -> 1.2140188e+09 | F7: =DCF!E20 -> 2.4266904e+09 | G7: =DCF!F20 -> 2.9789497e+09 | H7: =DCF!G20 -> 3.6568906e+09 | I7: =DCF!H20 -> 4.4891153e+09 | J7: =DCF!I20 -> 0 | K7: =DCF!J20 -> 0
A8: Add: Cash Flow from Non Operational | B8: ='INCOME STATEMENT'!C30 -> 0 | C8: ='INCOME STATEMENT'!D30 -> 0 | D8: ='INCOME STATEMENT'!E30 -> -212875 | E8: ='PROY LR'!D34 -> -212874.09 | F8: ='PROY LR'!E34 -> -212873.19 | G8: ='PROY LR'!F34 -> -212872.28 | H8: ='PROY LR'!G34 -> 0 | I8: ='PROY LR'!H34 -> 0 | J8: ='PROY LR'!I34 -> 0 | K8: ='PROY LR'!J34 -> 0
A9: Cash Flow Available to Investor | B9: =B7+B8 -> -7.792346e+09 | C9: =C7+C8 -> 5.2564268e+08 | D9: =D7+D8 -> 5.1104179e+09 | E9: =E7+E8 -> 1.2138059e+09 | F9: =F7+F8 -> 2.4264776e+09 | G9: =G7+G8 -> 2.9787368e+09 | H9: =H7+H8 -> 3.6568906e+09 | I9: =I7+I8 -> 4.4891153e+09 | ... K9: =K7+K8 -> 0

Sheet PROY FIXED ASSETS
A1: ='INCOME STATEMENT'!A1 -> Makmur Jaya Sejati Raya
A2: Fixed Asset Schedules
A3: ='[3]BALANCE SHEET'!A3 -> (IDR)
C5: ='FIXED ASSET'!E5 -> 2021 | D5: =C5+1 -> 2022 | E5: =D5+1 -> 2023 | F5: =E5+1 -> 2024
A6: A. Acquisition Costs
A7: Beginning
B8: Land (Tanah Lahan Sawit + Tanah Lahan Sawit (TA)) | C8: ='FIXED ASSET'!E8 -> 7817274315 | D8: =C26 -> 7817274315 | E8: =D26 -> 7817274315 | F8: =E26 -> 7817274315
B9: Building (Bangunan Mess/Barak + Bangunan Mess/Barak (TA) + Lapangan + Kantor) | C9: ='FIXED ASSET'!E9 -> 653687951 | D9: =C27 -> 653687951 | E9: =D27 -> 653687951 | F9: =E27 -> 653687951
B10: Equipment, Laboratory, & Machinery (Sarana & Prasarana) | C10: ='FIXED ASSET'!E10 -> 176449500 | D10: =C28 -> 176449500 | E10: =D28 -> 176449500 | F10: =E28 -> 176449500
B11: Vehicle & Heavy Equipment (Alat Berat + Kendaraan) | C11: ='FIXED ASSET'!E11 -> 2207972728 | D11: =C29 -> 2207972728 | E11: =D29 -> 2207972728 | F11: =E29 -> 2207972728
B12: Office Inventory (Inventaris Tanaman Sawit + Inventaris Tanaman Sawit (TA)) | C12: ='FIXED ASSET'!E12 -> 10145509610 | D12: =C30 -> 10145509610 | E12: =D30 -> 10145509610 | F12: =E30 -> 10145509610
B13: Electrical | C13: ='FIXED ASSET'!E13 -> 0 | D13: =C31 -> 0 | E13: =D31 -> 0 | F13: =E31 -> 0
A14: Total | C14: =SUM(C8:C13) -> 21000894104 | D14: =SUM(D8:D13) -> 21000894104 | E14: =SUM(E8:E13) -> 21000894104 | F14: =SUM(F8:F13) -> 21000894104
A16: Additions
B17: Land (Tanah Lahan Sawit + Tanah Lahan Sawit (TA)) | C17: ='FIXED ASSET'!E17 -> 0 | D17: =C17*(1+'FIXED ASSET'!$I17) -> 0 | E17: =D17*(1+'FIXED ASSET'!$I17) -> 0 | F17: =E17*(1+'FIXED ASSET'!$I17) -> 0
B18: Building (Bangunan Mess/Barak + Bangunan Mess/Barak (TA) + Lapangan + Kantor) | C18: ='FIXED ASSET'!E18 -> 0 | D18: =C18*(1+'FIXED ASSET'!$I18) -> 0 | E18: =D18*(1+'FIXED ASSET'!$I18) -> 0 | F18: =E18*(1+'FIXED ASSET'!$I18) -> 0
B19: Equipment, Laboratory, & Machinery (Sarana & Prasarana) | C19: ='FIXED ASSET'!E19 -> 0 | D19: =C19*(1+'FIXED ASSET'!$I19) -> 0 | E19: =D19*(1+'FIXED ASSET'!$I19) -> 0 | F19: =E19*(1+'FIXED ASSET'!$I19) -> 0
B20: Vehicle & Heavy Equipment (Alat Berat + Kendaraan) | C20: ='FIXED ASSET'!E20 -> 0 | D20: =C20*(1+'FIXED ASSET'!$I20) -> 0 | E20: =D20*(1+'FIXED ASSET'!$I20) -> 0 | F20: =E20*(1+'FIXED ASSET'!$I20) -> 0
B21: Office Inventory (Inventaris Tanaman Sawit + Inventaris Tanaman Sawit (TA)) | C21: ='FIXED ASSET'!E21 -> 0 | D21: =C21*(1+'FIXED ASSET'!$I21) -> 0 | E21: =D21*(1+'FIXED ASSET'!$I21) -> 0 | F21: =E21*(1+'FIXED ASSET'!$I21) -> 0
B22: Electrical | C22: ='FIXED ASSET'!E22 -> 0
A23: Total | C23: =SUM(C17:C22) -> 0 | D23: =SUM(D17:D22) -> 0 | E23: =SUM(E17:E22) -> 0 | F23: =SUM(F17:F22) -> 0
A25: Ending
B26: Land (Tanah Lahan Sawit + Tanah Lahan Sawit (TA)) | C26: =+C8+C17 -> 7817274315 | D26: =+D8+D17 -> 7817274315 | E26: =+E8+E17 -> 7817274315 | F26: =+F8+F17 -> 7817274315
B27: Building (Bangunan Mess/Barak + Bangunan Mess/Barak (TA) + Lapangan + Kantor) | C27: =+C9+C18 -> 653687951 | D27: =+D9+D18 -> 653687951 | E27: =+E9+E18 -> 653687951 | F27: =+F9+F18 -> 653687951
B28: Equipment, Laboratory, & Machinery (Sarana & Prasarana) | C28: =+C10+C19 -> 176449500 | D28: =+D10+D19 -> 176449500 | E28: =+E10+E19 -> 176449500 | F28: =+F10+F19 -> 176449500
B29: Vehicle & Heavy Equipment (Alat Berat + Kendaraan) | C29: =+C11+C20 -> 2207972728 | D29: =+D11+D20 -> 2207972728 | E29: =+E11+E20 -> 2207972728 | F29: =+F11+F20 -> 2207972728
B30: Office Inventory (Inventaris Tanaman Sawit + Inventaris Tanaman Sawit (TA)) | C30: =+C12+C21 -> 10145509610 | D30: =+D12+D21 -> 10145509610 | E30: =+E12+E21 -> 10145509610 | F30: =+F12+F21 -> 10145509610
B31: Electrical | C31: =+C13+C22 -> 0 | D31: =+D13+D22 -> 0 | E31: =+E13+E22 -> 0 | F31: =+F13+F22 -> 0
A32: Total | C32: =+C14+C23 -> 21000894104 | D32: =+D14+D23 -> 21000894104 | E32: =+E14+E23 -> 21000894104 | F32: =+F14+F23 -> 21000894104
A34: B. Depreciation
A35: Beginning
B36: Land (Tanah Lahan Sawit + Tanah Lahan Sawit (TA)) | C36: ='FIXED ASSET'!E36 -> 0 | D36: =C54 -> 0 | E36: =D54 -> 0 | F36: =E54 -> 0
B37: Building (Bangunan Mess/Barak + Bangunan Mess/Barak (TA) + Lapangan + Kantor) | C37: ='FIXED ASSET'!E37 -> 276895183 | D37: =C55 -> 313119864 | E37: =D55 -> 3.4823946e+08 | F37: =E55 -> 3.8228767e+08
B38: Equipment, Laboratory, & Machinery (Sarana & Prasarana) | C38: ='FIXED ASSET'!E38 -> 165897295 | D38: =C56 -> 176449498 | E38: =D56 -> 1.8592868e+08 | F38: =E56 -> 1.9444394e+08
B39: Vehicle & Heavy Equipment (Alat Berat + Kendaraan) | C39: ='FIXED ASSET'!E39 -> 1826348345 | D39: =C57 -> 1984688912 | E39: =D57 -> 2.1240347e+09 | F39: =E57 -> 2.2466644e+09
B40: Office Inventory (Inventaris Tanaman Sawit + Inventaris Tanaman Sawit (TA)) | C40: ='FIXED ASSET'!E40 -> 1738665546 | D40: =C58 -> 2515278436 | E40: =D58 -> 3.1948147e+09 | F40: =E58 -> 3.7894089e+09
B41: Electrical | C41: ='FIXED ASSET'!E41 -> 0 | D41: =C59 -> 0 | E41: =D59 -> 0 | F41: =E59 -> 0
A42: Total | C42: =SUM(C36:C41) -> 4007806369 | D42: =SUM(D36:D41) -> 4989536710 | E42: =SUM(E36:E41) -> 5.8530175e+09 | F42: =SUM(F36:F41) -> 6.6128049e+09
A44: Additions
B45: Land (Tanah Lahan Sawit + Tanah Lahan Sawit (TA)) | C45: ='FIXED ASSET'!E45 -> 0 | D45: =C45*(1+'FIXED ASSET'!$I45) -> 0 | E45: =D45*(1+'FIXED ASSET'!$I45) -> 0 | F45: =E45*(1+'FIXED ASSET'!$I45) -> 0
B46: Building (Bangunan Mess/Barak + Bangunan Mess/Barak (TA) + Lapangan + Kantor) | C46: ='FIXED ASSET'!E46 -> 36224681 | D46: =C46*(1+'FIXED ASSET'!$I46) -> 35119593 | E46: =D46*(1+'FIXED ASSET'!$I46) -> 34048217 | F46: =E46*(1+'FIXED ASSET'!$I46) -> 33009525
B47: Equipment, Laboratory, & Machinery (Sarana & Prasarana) | C47: ='FIXED ASSET'!E47 -> 10552203 | D47: =C47*(1+'FIXED ASSET'!$I47) -> 9479177.4 | E47: =D47*(1+'FIXED ASSET'!$I47) -> 8515264.9 | F47: =E47*(1+'FIXED ASSET'!$I47) -> 7649370.1
B48: Vehicle & Heavy Equipment (Alat Berat + Kendaraan) | C48: ='FIXED ASSET'!E48 -> 158340567 | D48: =C48*(1+'FIXED ASSET'!$I48) -> 1.3934579e+08 | E48: =D48*(1+'FIXED ASSET'!$I48) -> 1.2262966e+08 | F48: =E48*(1+'FIXED ASSET'!$I48) -> 1.0791881e+08
B49: Office Inventory (Inventaris Tanaman Sawit + Inventaris Tanaman Sawit (TA)) | C49: ='FIXED ASSET'!E49 -> 776612890 | D49: =C49*(1+'FIXED ASSET'!$H49) -> 6.7953627e+08 | E49: =D49*(1+'FIXED ASSET'!$H49) -> 5.9459423e+08 | F49: =E49*(1+'FIXED ASSET'!$H49) -> 5.2026995e+08
B50: Electrical | C50: ='FIXED ASSET'!E50 -> 0 | D50: =C50*(1+'FIXED ASSET'!$I50) -> 0 | E50: =D50*(1+'FIXED ASSET'!$I50) -> 0 | F50: =E50*(1+'FIXED ASSET'!$I50) -> 0
A51: Total | C51: =SUM(C45:C50) -> 981730341 | D51: =SUM(D45:D50) -> 8.6348083e+08 | E51: =SUM(E45:E50) -> 7.5978737e+08 | F51: =SUM(F45:F50) -> 6.6884766e+08
C52: ='FIXED ASSET'!E52 -> -0.12407995 | D52: =(D51-C51)/C51 -> -0.12045009 | E52: =(E51-D51)/D51 -> -0.12008774 | F52: =(F51-E51)/E51 -> -0.119691
A53: Ending
B54: Land (Tanah Lahan Sawit + Tanah Lahan Sawit (TA)) | C54: =+C36+C45 -> 0 | D54: =+D36+D45 -> 0 | E54: =+E36+E45 -> 0 | F54: =+F36+F45 -> 0
B55: Building (Bangunan Mess/Barak + Bangunan Mess/Barak (TA) + Lapangan + Kantor) | C55: =+C37+C46 -> 313119864 | D55: =+D37+D46 -> 3.4823946e+08 | E55: =+E37+E46 -> 3.8228767e+08 | F55: =+F37+F46 -> 4.152972e+08
B56: Equipment, Laboratory, & Machinery (Sarana & Prasarana) | C56: =+C38+C47 -> 176449498 | D56: =+D38+D47 -> 1.8592868e+08 | E56: =+E38+E47 -> 1.9444394e+08 | F56: =+F38+F47 -> 2.0209331e+08
B57: Vehicle & Heavy Equipment (Alat Berat + Kendaraan) | C57: =+C39+C48 -> 1984688912 | D57: =+D39+D48 -> 2.1240347e+09 | E57: =+E39+E48 -> 2.2466644e+09 | F57: =+F39+F48 -> 2.3545832e+09
B58: Office Inventory (Inventaris Tanaman Sawit + Inventaris Tanaman Sawit (TA)) | C58: =+C40+C49 -> 2515278436 | D58: =+D40+D49 -> 3.1948147e+09 | E58: =+E40+E49 -> 3.7894089e+09 | F58: =+F40+F49 -> 4.3096789e+09
B59: Electrical | C59: =+C41+C50 -> 0 | D59: =+D41+D50 -> 0 | E59: =+E41+E50 -> 0 | F59: =+F41+F50 -> 0
A60: Total | C60: =+C42+C51 -> 4989536710 | D60: =+D42+D51 -> 5.8530175e+09 | E60: =+E42+E51 -> 6.6128049e+09 | F60: =+F42+F51 -> 7.2816526e+09
A62: Net Value Fixed Assets
B63: Land (Tanah Lahan Sawit + Tanah Lahan Sawit (TA)) | C63: =+C26-C54 -> 7817274315 | D63: =+D26-D54 -> 7817274315 | E63: =+E26-E54 -> 7817274315 | F63: =+F26-F54 -> 7817274315
B64: Building (Bangunan Mess/Barak + Bangunan Mess/Barak (TA) + Lapangan + Kantor) | C64: =+C27-C55 -> 340568087 | D64: =+D27-D55 -> 3.0544849e+08 | E64: =+E27-E55 -> 2.7140028e+08 | F64: =+F27-F55 -> 2.3839075e+08
B65: Equipment, Laboratory, & Machinery (Sarana & Prasarana) | C65: =+C28-C56 -> 2 | D65: =+D28-D56 -> -9479175.4 | E65: =+E28-E56 -> -17994440 | F65: =+F28-F56 -> -25643810
B66: Vehicle & Heavy Equipment (Alat Berat + Kendaraan) | C66: =+C29-C57 -> 223283816 | D66: =+D29-D57 -> 83938026 | E66: =+E29-E57 -> -38691629 | F66: =+F29-F57 -> -1.4661044e+08
B67: Office Inventory (Inventaris Tanaman Sawit + Inventaris Tanaman Sawit (TA)) | C67: =+C30-C58 -> 7630231174 | D67: =+D30-D58 -> 6.9506949e+09 | E67: =+E30-E58 -> 6.3561007e+09 | F67: =+F30-F58 -> 5.8358307e+09
B68: Electrical | C68: =+C31-C59 -> 0 | D68: =+D31-D59 -> 0 | E68: =+E31-E59 -> 0 | F68: =+F31-F59 -> 0
A69: Total | C69: =SUM(C63:C68) -> 16011357394 | D69: =SUM(D63:D68) -> 1.5147877e+10 | E69: =SUM(E63:E68) -> 1.4388089e+10 | F69: =SUM(F63:F68) -> 1.3719242e+10

Sheet PROY LR
E1: Laporan Proyeksi Laba Rugi
A2: =HOME!B4 -> Makmur Jaya Sejati Raya
A3: Income Statement
A4: ='BALANCE SHEET'!A3 -> (IDR) | D4: 5 | E4: 6 | F4: 7
C6: ='PROY BALANCE SHEET'!C5 -> 2021 | D6: ='PROY BALANCE SHEET'!D5 -> 2022 | E6: ='PROY BALANCE SHEET'!E5 -> 2023 | F6: ='PROY BALANCE SHEET'!F5 -> 2024
M7: diisi sesuai proyeksi penilai
A8: Revenue | C8: ='INCOME STATEMENT'!E6 -> 16663916100 | D8: =C8*(1+$C$9) -> 2.0456242e+10 | E8: =D8*(1+$C$9) -> 2.5111616e+10 | F8: =E8*(1+$C$9) -> 3.0826445e+10 | K8: '-1e+07x + 9e+07
A9: Revenue Growth | C9: ='INCOME STATEMENT'!J6 -> 0.22757714 | D9: =(D8-C8)/C8 -> 0.22757714 | E9: =(E8-D8)/D8 -> 0.22757714 | F9: =(F8-E8)/E8 -> 0.22757714
A10: Cost of Good Sold | C10: ='INCOME STATEMENT'!E7 -> -10779658214 | D10: =ROUNDUP('KEY DRIVERS'!D20*D8,3) -> -1.3959203e+10 | E10: =ROUNDUP('KEY DRIVERS'!E20*E8,3) -> -1.7135999e+10 | F10: =ROUNDUP('KEY DRIVERS'!F20*F8,3) -> -2.1035761e+10
A11: Gross Profit | C11: ='INCOME STATEMENT'!E8 -> 5884257886 | D11: =+D8+D10 -> 6.4970392e+09 | E11: =+E8+E10 -> 7.9756168e+09 | F11: =+F8+F10 -> 9.7906849e+09
B12: Gross Profit Margin | C12: ='INCOME STATEMENT'!E9 -> 0.35311375 | D12: =+D11/D8 -> 0.31760668 | E12: =+E11/E8 -> 0.31760668 | F12: =+F11/F8 -> 0.31760668
A14: Operating Expenses:
B15: Others | C15: ='INCOME STATEMENT'!E12 -> 0 | D15: =D8*'KEY DRIVERS'!D23 -> 0 | E15: =E8*'KEY DRIVERS'!E23 -> 0 | F15: =F8*'KEY DRIVERS'!F23 -> 0
B16: General & Administrative Overheads | C16: ='INCOME STATEMENT'!E13 -> -2641095104 | D16: =D8*'KEY DRIVERS'!D24 -> -3.2002192e+09 | E16: =E8*'KEY DRIVERS'!E24 -> -3.928516e+09 | F16: =F8*'KEY DRIVERS'!F24 -> -4.8225564e+09
A17: Operating Expenses (Exclude Depreciation) | C17: =SUM(C15:C16) -> -2641095104 | D17: =SUM(D15:D16) -> -3.2002192e+09 | E17: =SUM(E15:E16) -> -3.928516e+09 | F17: =SUM(F15:F16) -> -4.8225564e+09
A19: EBITDA | C19: =C11+C17 -> 3243162782 | D19: =D11+D17 -> 3.29682e+09 | E19: =E11+E17 -> 4.0471009e+09 | F19: =F11+F17 -> 4.9681285e+09
C20: =C19/C8 -> 0.19462189 | D20: =D19/D8 -> 0.16116449 | E20: =E19/E8 -> 0.16116449 | F20: =F19/F8 -> 0.16116449
A22: Depreciation | C22: ='FIXED ASSET'!E51*-1 -> -981730341 | D22: ='PROY FIXED ASSETS'!D51*-1 -> -8.6348083e+08 | E22: ='PROY FIXED ASSETS'!E51*-1 -> -7.5978737e+08 | F22: ='PROY FIXED ASSETS'!F51*-1 -> -6.6884766e+08
A23: Depreciation Growth
A25: EBIT | C25: ='INCOME STATEMENT'!E22 -> 2261432441 | D25: =D19+D22 -> 2.4333392e+09 | E25: =E19+E22 -> 3.2873135e+09 | F25: =F19+F22 -> 4.2992808e+09
A26: EBIT Margin | C26: ='INCOME STATEMENT'!C23 -> 0.0729424 | D26: =D25/D8 -> 0.11895338 | E26: =E25/E8 -> 0.13090808 | F26: =F25/F8 -> 0.13946729
A28: Other Income/(Charge)
A29: Interest Income | C29: ='INCOME STATEMENT'!E26 -> 13957341 | D29: =C29*(1+'INCOME STATEMENT'!$J26) -> 14006615 | E29: =D29*(1+'INCOME STATEMENT'!$J26) -> 14056063 | F29: =E29*(1+'INCOME STATEMENT'!$J26) -> 14105686
A30: Interest Income Growth | C30: =('INCOME STATEMENT'!E26-'INCOME STATEMENT'!D26)/'INCOME STATEMENT'!D26 -> 0.1824314 | D30: =(D29-C29)/C29 -> 0.0035303454 | E30: =(E29-D29)/D29 -> 0.0035303454 | F30: =(F29-E29)/E29 -> 0.0035303454
A31: Interest Expense | C31: ='INCOME STATEMENT'!E27 -> -942033 | D31: =C31*(1+'INCOME STATEMENT'!$J27) -> -941430.23 | E31: =D31*(1+'INCOME STATEMENT'!$J27) -> -940827.84 | F31: =E31*(1+'INCOME STATEMENT'!$J27) -> -940225.84
A32: Interest Expense Growth | C32: =('INCOME STATEMENT'!E27-'INCOME STATEMENT'!D27)/'INCOME STATEMENT'!D27 -> -0.30790271 | D32: =(D31-C31)/C31 -> -0.00063986189 | E32: =(E31-D31)/D31 -> -0.00063986189 | F32: =(F31-E31)/E31 -> -0.00063986189
A33: Other Income/(Charge) | C33: =C29+C31 -> 13015308 | D33: =D29+D31 -> 13065185 | E33: =E29+E31 -> 13115236 | F33: =F29+F31 -> 13165460
A34: Non Operating Income | C34: ='INCOME STATEMENT'!E30 -> -212875 | D34: =C34*(1+'INCOME STATEMENT'!$J30) -> -212874.09 | E34: =D34*(1+'INCOME STATEMENT'!$J30) -> -212873.19 | F34: =E34*(1+'INCOME STATEMENT'!$J30) -> -212872.28
A36: Profit Before Tax | C36: =C25+C33+C34 -> 2274234874 | D36: =D25+D33+D34 -> 2.4461915e+09 | E36: =E25+E33+E34 -> 3.3002158e+09 | F36: =F25+F33+F34 -> 4.3122334e+09
A37: Corporate Tax | B37: =STAT_ASSUMPTIONS!B5 -> 0.22 | C37: ='INCOME STATEMENT'!E33 -> -436128347 | D37: =$B$37*D36*-1 -> -5.3816212e+08 | E37: =$B$37*E36*-1 -> -7.2604749e+08 | F37: =$B$37*F36*-1 -> -9.4869136e+08
A39: Net Profit After Tax | B39: NOPLAT | C39: =C36+C37 -> 1838106527 | D39: =D36+D37 -> 1.9080293e+09 | E39: =E36+E37 -> 2.5741684e+09 | F39: =F36+F37 -> 3.3635421e+09
A40: Net Profit After Tax Margin | C40: =C39/C8 -> 0.1103046 | D40: =D39/D8 -> 0.093273696 | E40: =E39/E8 -> 0.10250907 | F40: =F39/F8 -> 0.10911223

Sheet PROY BALANCE SHEET
A1: Laporan Proyeksi Neraca
A2: =HOME!B4 -> Makmur Jaya Sejati Raya
A3: Balance Sheet
A4: ='BALANCE SHEET'!A3 -> (IDR)
C5: ='BALANCE SHEET'!E4 -> 2021 | D5: =C5+1 -> 2022 | E5: =D5+1 -> 2023 | F5: =E5+1 -> 2024 | K5: Average Growth
A6: ASSETS
A8: Current Assets
B9: Cash on Hands | C9: ='BALANCE SHEET'!E8 -> 717848795 | D9: =C9*(1+C10) -> 2.1807393e+09 | E9: =D9*(1+D10) -> 6.6248268e+09 | F9: =E9*(1+E10) -> 2.0125436e+10
B10: Cash on Hands Growth | C10: ='BALANCE SHEET'!P8 -> 2.0378811 | D10: =(D9-C9)/C9 -> 2.0378811 | E10: =(E9-D9)/D9 -> 2.0378811 | F10: =(F9-E9)/E9 -> 2.0378811 | K10: =AVERAGE(D10:J10) -> 2.0378811
B11: Cash in Banks | C11: ='BALANCE SHEET'!E9 -> 337031731 | D11: =C11*(1+C12) -> 3.5037597e+08 | E11: =D11*(1+D12) -> 3.6424855e+08 | F11: =E11*(1+E12) -> 3.7867039e+08
B12: Cash in Banks Growth | C12: ='BALANCE SHEET'!P9 -> 0.039593415 | D12: =(D11-C11)/C11 -> 0.039593415 | E12: =(E11-D11)/D11 -> 0.039593415 | F12: =(F11-E11)/E11 -> 0.039593415 | K12: =AVERAGE(D12:J12) -> 0.039593415
B13: Account Receivable | C13: ='BALANCE SHEET'!E10 -> 191055111 | D13: =C13*(1+C14) -> 2.5472175e+08 | E13: =D13*(1+D14) -> 3.3960446e+08 | F13: =E13*(1+E14) -> 4.5277324e+08
B14: Account Receivable Growth | C14: ='BALANCE SHEET'!P10 -> 0.33323702 | D14: =C14 -> 0.33323702 | E14: =C14 -> 0.33323702 | F14: =C14 -> 0.33323702 | K14: =AVERAGE(D14:J14) -> 0.33323702
B15: Other Receivable | C15: ='BALANCE SHEET'!E11 -> 21000000 | D15: =C15*(1+C16) -> 18422481 | E15: =D15*(1+D16) -> 16161323 | F15: =E15*(1+E16) -> 14177698
B16: Other Receivable Growth | C16: ='BALANCE SHEET'!P11 -> -0.12273902 | D16: =(D15-C15)/C15 -> -0.12273902 | E16: =(E15-D15)/D15 -> -0.12273902 | F16: =(F15-E15)/E15 -> -0.12273902 | K16: =AVERAGE(D16:J16) -> -0.12273902
B17: Inventory | C17: ='BALANCE SHEET'!E12 -> 0 | D17: =C17*(1+C18) -> 0 | E17: 0 | F17: 0
B18: Inventory Growth | C18: ='BALANCE SHEET'!P12 -> 0 | D18: =IFERROR((D17-C17)/C17,0) -> 0 | E18: =IFERROR((E17-D17)/D17,0) -> 0 | F18: =IFERROR((F17-E17)/E17,0) -> 0 | K18: =AVERAGE(D18:J18) -> 0
B19: Others | C19: ='BALANCE SHEET'!E13 -> 0 | D19: =C19*(1+C20) -> 0 | E19: =D19*(1+D20) -> 0 | F19: =E19*(1+E20) -> 0
B20: Others Growth | C20: ='BALANCE SHEET'!P13 -> 0 | D20: =IFERROR((D19-C19)/C19,0) -> 0 | E20: =IFERROR((E19-D19)/D19,0) -> 0 | F20: =IFERROR((F19-E19)/E19,0) -> 0 | K20: =AVERAGE(D20:J20) -> 0
A21: Current Assets | C21: =C9+C11+C13+C15+C17+C19 -> 1266935637 | D21: =D9+D11+D13+D15+D17+D19 -> 2.8042595e+09 | E21: =E9+E11+E13+E15+E17+E19 -> 7.3448411e+09 | F21: =F9+F11+F13+F15+F17+F19 -> 2.0971058e+10
A23: Non Current Assets
A24: Fixed Asset
B25: Beginning | C25: ='BALANCE SHEET'!E19 -> 21000894104 | D25: ='PROY FIXED ASSETS'!D32 -> 21000894104 | E25: ='PROY FIXED ASSETS'!E32 -> 21000894104 | F25: ='PROY FIXED ASSETS'!F32 -> 21000894104
B26: Accumulated Depreciations | C26: ='BALANCE SHEET'!E20 -> -4989536710 | D26: ='PROY FIXED ASSETS'!D60*-1 -> -5.8530175e+09 | E26: ='PROY FIXED ASSETS'!E60*-1 -> -6.6128049e+09 | F26: ='PROY FIXED ASSETS'!F60*-1 -> -7.2816526e+09
B27: Accumulated Depreciations Growth | C27: =('BALANCE SHEET'!E20-'BALANCE SHEET'!D20)/'BALANCE SHEET'!D20 -> 0.24495453 | D27: =(D26-C26)/C26 -> 0.17305832 | E27: =(E26-D26)/D26 -> 0.12981122 | F27: =(F26-E26)/E26 -> 0.10114432 | K27: =AVERAGE(D27:J27) -> 0.13467129
B28: Fixed Assets, Net | C28: ='BALANCE SHEET'!E21 -> 16011357394 | D28: =+D25+D26 -> 1.5147877e+10 | E28: =+E25+E26 -> 1.4388089e+10 | F28: =+F25+F26 -> 1.3719242e+10
A29: Other Non Current Asset | C29: ='BALANCE SHEET'!E22 -> 0 | D29: =C29 -> 0 | E29: =D29 -> 0 | F29: =E29 -> 0
A30: Intangible Assets | C30: ='BALANCE SHEET'!E23 -> 0 | D30: =C30*(1+'BALANCE SHEET'!$P$23) -> 0 | E30: =D30*(1+'BALANCE SHEET'!$P$23) -> 0 | F30: =E30*(1+'BALANCE SHEET'!$P$23) -> 0
A31: Total Non Current Asset | C31: =C25+C26+C29 -> 16011357394 | D31: =D28+D29+D30 -> 1.5147877e+10 | E31: =E28+E29+E30 -> 1.4388089e+10 | F31: =F28+F29+F30 -> 1.3719242e+10
A33: ASSETS | C33: =+C21+C31 -> 17278293031 | D33: =+D21+D31 -> 1.7952136e+10 | E33: =+E21+E31 -> 2.173293e+10 | F33: =+F21+F31 -> 3.4690299e+10
A35: LIABILITIES & EQUITY
A36: Current Liabilities
B37: Bank Loan-Short Term | C37: ='BALANCE SHEET'!E30 -> 0 | D37: =C37*(1+C38) -> 0 | E37: =D37*(1+D38) -> 0 | F37: =E37*(1+E38) -> 0
C38: ='BALANCE SHEET'!P30 -> 0 | D38: =IFERROR((D37-C37)/C37,0) -> 0 | E38: =IFERROR((E37-D37)/D37,0) -> 0 | F38: =IFERROR((F37-E37)/E37,0) -> 0
B39: Account Payables | C39: ='BALANCE SHEET'!E31 -> 1823364600 | D39: =C39*(1+C40) -> 2.4670092e+09 | E39: =D39*(1+D40) -> 3.3378594e+09 | F39: =E39*(1+E40) -> 4.5161181e+09
C40: ='BALANCE SHEET'!P31 -> 0.35299832 | D40: =(D39-C39)/C39 -> 0.35299832 | E40: =(E39-D39)/D39 -> 0.35299832 | F40: =(F39-E39)/E39 -> 0.35299832
B41: Tax Payable | C41: ='BALANCE SHEET'!E32 -> 678518254 | D41: =C41*(1+C42) -> 1.4087829e+09 | E41: =D41*(1+D42) -> 2.9250048e+09 | F41: =E41*(1+E42) -> 6.0730814e+09
C42: ='BALANCE SHEET'!P32 -> 1.0762637 | D42: =(D41-C41)/C41 -> 1.0762637 | E42: =(E41-D41)/D41 -> 1.0762637 | F42: =(F41-E41)/E41 -> 1.0762637
B43: Others | C43: ='BALANCE SHEET'!E33 -> 1075354928 | D43: =C43*(1+C44) -> 1.9293002e+09 | E43: =D43*(1+D44) -> 3.461368e+09 | F43: =E43*(1+E44) -> 6.2100592e+09
C44: ='BALANCE SHEET'!P33 -> 0.79410547 | D44: =(D43-C43)/C43 -> 0.79410547 | E44: =(E43-D43)/D43 -> 0.79410547 | F44: =(F43-E43)/E43 -> 0.79410547
A45: Current Liabilities | C45: =SUM(C37:C43) -> 3.5772378e+09 | D45: =SUM(D37:D43) -> 5.8050923e+09 | E45: =SUM(E37:E43) -> 9.7242321e+09 | F45: =SUM(F37:F43) -> 1.6799259e+10
A47: Non Current Liabilities
B48: Bank Loan-Long Term | C48: ='BALANCE SHEET'!E37 -> 0 | D48: =IFERROR(C48*(1+C49),0) -> 0 | E48: =IFERROR(D48*(1+D49),0) -> 0 | F48: =IFERROR(E48*(1+E49),0) -> 0
C49: ='BALANCE SHEET'!P37 -> 0 | D49: =IFERROR((D48-C48)/C48,0) -> 0 | E49: =IFERROR((E48-D48)/D48,0) -> 0 | F49: =IFERROR((F48-E48)/E48,0) -> 0
B50: Other Non Current Liabilites | C50: ='BALANCE SHEET'!E38 -> 0 | D50: =C50*(1+C51) -> 0 | E50: =D50*(1+D51) -> 0 | F50: =E50*(1+E51) -> 0
C51: ='BALANCE SHEET'!P38 -> 0 | D51: =IFERROR((D50-C50)/C50,0) -> 0 | E51: =IFERROR((E50-D50)/D50,0) -> 0 | F51: =IFERROR((F50-E50)/E50,0) -> 0
A52: Non Current Liabilities | C52: =C48+C50 -> 0 | D52: =+D48+D50 -> 0 | E52: =+E48+E50 -> 0 | F52: =+F48+F50 -> 0
A54: Shareholders' Equity
A55: Paid Up Capital | C55: ='BALANCE SHEET'!E42 -> 5280000000 | D55: =C55 -> 5280000000 | E55: =D55 -> 5280000000 | F55: =E55 -> 5280000000
A56: Retained Earnings
B57: Surplus | C57: ='BALANCE SHEET'!E45 -> 6698715227 | D57: =C57 -> 6698715227 | E57: =D57 -> 6698715227 | F57: =E57 -> 6698715227
B58: Current Profit | C58: ='BALANCE SHEET'!E46 -> 1838106527 | D58: =C58+'PROY LR'!D39 -> 3.7461359e+09 | E58: =D58+'PROY LR'!E39 -> 6.3203042e+09 | F58: =E58+'PROY LR'!F39 -> 9.6838463e+09
A59: Retained Earnings, Ending Balance | C59: ='BALANCE SHEET'!E47 -> 8536821754 | D59: =D57+D58 -> 1.0444851e+10 | E59: =E57+E58 -> 1.3019019e+10 | F59: =F57+F58 -> 1.6382562e+10
A60: Shareholders' Equity | C60: =C55+C59 -> 13816821754 | D60: =D55+D59 -> 1.5724851e+10 | E60: =E55+E59 -> 1.8299019e+10 | F60: =F55+F59 -> 2.1662562e+10
A62: LIABILITES & EQUITY | C62: =C45+C52+C60 -> 1.739406e+10 | D62: =D45+D52+D60 -> 2.1529943e+10 | E62: =E45+E52+E60 -> 2.8023252e+10 | F62: =F45+F52+F60 -> 3.846182e+10
A63: Balance Control | D63: =D33-D62 -> -3.5778073e+09 | E63: =E33-E62 -> -6.2903213e+09 | F63: =F33-F62 -> -3.7715211e+09 | K63: =AVERAGE(D63:J63) -> -4.5465499e+09
A64: copas number only atu-atu
D65: 1 | E65: 2 | F65: 3

Sheet PROY CASH FLOW STATEMENT
A1: =HOME!B4 -> Makmur Jaya Sejati Raya
A2: Cash Flow Statement
A3: ='BALANCE SHEET'!A3 -> (IDR)
C4: ='CASH FLOW STATEMENT'!E4 -> 2021 | D4: =C4+1 -> 2022 | E4: =D4+1 -> 2023 | F4: =E4+1 -> 2024 | G4: =F4+1 -> 2025
A5: EBITDA | C5: ='INCOME STATEMENT'!E18 -> 3243162782 | D5: ='PROY LR'!D19 -> 3.29682e+09 | E5: ='PROY LR'!E19 -> 4.0471009e+09 | F5: ='PROY LR'!F19 -> 4.9681285e+09
A6: Corporate Tax | C6: ='INCOME STATEMENT'!E33 -> -436128347 | D6: ='PROY LR'!D37 -> -5.3816212e+08 | E6: ='PROY LR'!E37 -> -7.2604749e+08 | F6: ='PROY LR'!F37 -> -9.4869136e+08
A7: Changes in Working Capital
B8: Operating Current Assets (AR + Inventory) | C8: ='CASH FLOW STATEMENT'!E8 -> 484323209 | D8: =(('PROY BALANCE SHEET'!D13+'PROY BALANCE SHEET'!D17)-('PROY BALANCE SHEET'!C13+'PROY BALANCE SHEET'!C17))*-1 -> -63666636 | E8: =(('PROY BALANCE SHEET'!E13+'PROY BALANCE SHEET'!E17)-('PROY BALANCE SHEET'!D13+'PROY BALANCE SHEET'!D17))*-1 -> -84882716 | F8: =(('PROY BALANCE SHEET'!F13+'PROY BALANCE SHEET'!F17)-('PROY BALANCE SHEET'!E13+'PROY BALANCE SHEET'!E17))*-1 -> -1.1316878e+08
B9: Operating Current Liabilities (AP + Other Payable) | C9: ='CASH FLOW STATEMENT'!E9 -> 1880659928 | D9: =('PROY BALANCE SHEET'!D39+'PROY BALANCE SHEET'!D43)-('PROY BALANCE SHEET'!C39+'PROY BALANCE SHEET'!C43) -> 1.4975899e+09 | E9: =('PROY BALANCE SHEET'!E39+'PROY BALANCE SHEET'!E43)-('PROY BALANCE SHEET'!D39+'PROY BALANCE SHEET'!D43) -> 2.4029179e+09 | F9: =('PROY BALANCE SHEET'!F39+'PROY BALANCE SHEET'!F43)-('PROY BALANCE SHEET'!E39+'PROY BALANCE SHEET'!E43) -> 3.92695e+09
A10: Working Capital | C10: =+C8+C9 -> 2364983137 | D10: =+D8+D9 -> 1.4339232e+09 | E10: =+E8+E9 -> 2.3180352e+09 | F10: =+F8+F9 -> 3.8137812e+09 | M10: DCF, Changes Working Capital
A11: Cash Flow from Operations | C11: =SUM(C5:C9) -> 5172017572 | D11: =SUM(D5:D9) -> 4.1925811e+09 | E11: =SUM(E5:E9) -> 5.6390886e+09 | F11: =SUM(F5:F9) -> 7.8332184e+09
A13: Cash Flow from Non Operations | C13: ='INCOME STATEMENT'!E30 -> -212875 | D13: ='PROY LR'!D34 -> -212874.09 | E13: ='PROY LR'!E34 -> -212873.19 | F13: ='PROY LR'!F34 -> -212872.28
A17: Cash Flow from Investment (Capital Expenditure) | C17: ='FIXED ASSET'!E23*-1 -> 0 | D17: ='PROY FIXED ASSETS'!D23*-1 -> 0 | E17: ='PROY FIXED ASSETS'!E23*-1 -> 0 | F17: ='PROY FIXED ASSETS'!F23*-1 -> 0
A19: Cash Flow before Financing | C19: =C11+C13+C17 -> 5171804697 | D19: =D11+D13+D17 -> 4.1923682e+09 | E19: =E11+E13+E17 -> 5.6388757e+09 | F19: =F11+F13+F17 -> 7.8330055e+09
A21: Financing
B22: Equity Injection | C22: ='CASH FLOW STATEMENT'!E22 -> -3150000000 | D22: 0 | E22: 0 | F22: 0
B23: New Loan | C23: ='CASH FLOW STATEMENT'!E23 -> 0 | D23: 0 | E23: 0 | F23: 0
B24: Interest Expense | C24: ='INCOME STATEMENT'!E27 -> -942033 | D24: ='PROY LR'!D31 -> -941430.23 | E24: ='PROY LR'!E31 -> -940827.84 | F24: ='PROY LR'!F31 -> -940225.84
B25: Interest Income | C25: ='INCOME STATEMENT'!E26 -> 13957341 | D25: ='PROY LR'!D29 -> 14006615 | E25: ='PROY LR'!E29 -> 14056063 | F25: ='PROY LR'!F29 -> 14105686
B26: Principal Repayment | C26: ='ACC PAYABLES'!E20 -> 0 | D26: ='PROY ACC PAYABLES'!D21 -> 0 | E26: ='PROY ACC PAYABLES'!E21 -> 0 | F26: ='PROY ACC PAYABLES'!F21 -> 0
A28: Cash Flow from Financing | C28: =SUM(C22:C26) -> -3136984692 | D28: =SUM(D22:D26) -> 13065185 | E28: =SUM(E22:E26) -> 13115236 | F28: =SUM(F22:F26) -> 13165460
A30: Net Cash Flow | C30: =+C11+C13+C17+C28 -> 2034820005 | D30: =+D11+D13+D17+D28 -> 4.2054334e+09 | E30: =+E11+E13+E17+E28 -> 5.651991e+09 | F30: =+F11+F13+F17+F28 -> 7.846171e+09
A32: Cash-Beginning Balance | C32: ='CASH FLOW STATEMENT'!D33 -> 723908969 | D32: =C33 -> 1054880526 | E32: =D33 -> 2.5311153e+09 | F32: =E33 -> 6.9890753e+09
A33: Cash-Ending Balance | C33: ='BALANCE SHEET'!E8+'BALANCE SHEET'!E9 -> 1054880526 | D33: ='PROY BALANCE SHEET'!D9+'PROY BALANCE SHEET'!D11 -> 2.5311153e+09 | E33: ='PROY BALANCE SHEET'!E9+'PROY BALANCE SHEET'!E11 -> 6.9890753e+09 | F33: ='PROY BALANCE SHEET'!F9+'PROY BALANCE SHEET'!F11 -> 2.0504107e+10
A35: Cash Ending in Bank | C35: ='BALANCE SHEET'!E9 -> 337031731 | D35: ='PROY BALANCE SHEET'!D11 -> 3.5037597e+08 | E35: ='PROY BALANCE SHEET'!E11 -> 3.6424855e+08 | F35: ='PROY BALANCE SHEET'!F11 -> 3.7867039e+08
A36: Cash Ending in Cash on Hand | C36: ='BALANCE SHEET'!E8 -> 717848795 | D36: ='PROY BALANCE SHEET'!D9 -> 2.1807393e+09 | E36: ='PROY BALANCE SHEET'!E9 -> 6.6248268e+09 | F36: ='PROY BALANCE SHEET'!F9 -> 2.0125436e+10

Sheet PROY ACC PAYABLES
A1: Proyeksi Skedul Utang
A2: =HOME!B4 -> Makmur Jaya Sejati Raya
A3: Bank Loan Schedules
A4: ='BALANCE SHEET'!A3 -> (IDR)
C6: ='ACC PAYABLES'!E5 -> 2021 | D6: =C6+1 -> 2022 | E6: =D6+1 -> 2023 | F6: =E6+1 -> 2024 | G6: =F6+1 -> 2025 | H6: =G6+1 -> 2026 | I6: =H6+1 -> 2027 | J6: =I6+1 -> 2028
A8: Bank loan-SHORT TERM | C8: 8
A9: Principal | C9: ='ACC PAYABLES'!E8 -> 0.13 | D9: 0.13 | E9: 0.13 | F9: 0.13 | G9: 0.13 | H9: 0.13 | I9: 0 | J9: 0
A10: Beginning | C10: ='ACC PAYABLES'!E9 -> 0 | D10: =C13 -> 0 | E10: =D13 -> 0 | F10: =E13 -> 0 | G10: =F13 -> 0 | H10: =G13 -> 0 | I10: =H13 -> 0 | J10: =I13 -> 0
B11: Addition | C11: ='ACC PAYABLES'!E10 -> 0 | D11: 0 | E11: 0 | F11: 0 | G11: 0 | H11: 0 | I11: 0 | J11: 0
B12: Repayment | C12: ='ACC PAYABLES'!E11 -> 0 | D12: 0 | E12: 0 | F12: 0 | G12: 0 | H12: 0 | I12: 0 | J12: 0
A13: Ending | C13: =SUM(C10:C12) -> 0 | D13: =SUM(D10:D12) -> 0 | E13: =SUM(E10:E12) -> 0 | F13: =SUM(F10:F12) -> 0 | G13: =SUM(G10:G12) -> 0 | H13: =SUM(H10:H12) -> 0 | I13: =SUM(I10:I12) -> 0 | J13: =SUM(J10:J12) -> 0
A15: Interest Payable | B15: interest rate 14% | C15: ='ACC PAYABLES'!E14 -> 0 | D15: =D13*(RIGHT($B$15,3))*-1 -> 0 | E15: =E13*(RIGHT($B$15,3))*-1 -> 0 | F15: =F13*(RIGHT($B$15,3))*-1 -> 0 | G15: =G13*(RIGHT($B$15,3))*-1 -> 0 | H15: =H13*(RIGHT($B$15,3))*-1 -> 0 | I15: =I13*(RIGHT($B$15,3))*-1 -> 0 | J15: =J13*(RIGHT($B$15,3))*-1 -> 0
A17: Bank loan-LONG TERM | C17: 8
A18: Principal | C18: ='ACC PAYABLES'!E17 -> 0.13 | D18: 0.13 | E18: 0.13 | F18: 0.13 | G18: 0.13 | H18: 0.13 | I18: 0 | J18: 0
A19: Beginning | C19: ='ACC PAYABLES'!E18 -> 0 | D19: =C22 -> 0 | E19: =D22 -> 0 | F19: =E22 -> 0 | G19: =F22 -> 0 | H19: =G22 -> 0 | I19: =H22 -> 0 | J19: =I22 -> 0
B20: Addition | C20: ='ACC PAYABLES'!E19 -> 0 | D20: 0 | E20: 0 | F20: 0 | G20: 0 | H20: 0 | I20: 0 | J20: 0
B21: Repayment | C21: ='ACC PAYABLES'!E20 -> 0 | D21: 0 | E21: 0 | F21: 0 | G21: 0 | H21: 0 | I21: 0 | J21: 0
A22: Ending | C22: =SUM(C19:C21) -> 0 | D22: =SUM(D19:D21) -> 0 | E22: =SUM(E19:E21) -> 0 | F22: =SUM(F19:F21) -> 0 | G22: =SUM(G19:G21) -> 0 | H22: =SUM(H19:H21) -> 0 | I22: =SUM(I19:I21) -> 0 | J22: =SUM(J19:J21) -> 0
A24: Interest Payable | C24: ='ACC PAYABLES'!E23 -> 0 | D24: 0 | E24: 0 | F24: 0 | G24: 0 | H24: 0 | I24: 0 | J24: 0

Sheet PROY NOPLAT
A1: =HOME!B4 -> Makmur Jaya Sejati Raya
A2: NOPLAT
A3: ='BALANCE SHEET'!A3 -> (IDR)
C5: ='ACC PAYABLES'!E5 -> 2021 | D5: =C5 -> 2021 | E5: =D5+1 -> 2022 | F5: =E5+1 -> 2023
A7: Profit Before Tax | C7: ='INCOME STATEMENT'!E32 -> 2274234874 | D7: ='PROY LR'!D36 -> 2.4461915e+09 | E7: ='PROY LR'!E36 -> 3.3002158e+09 | F7: ='PROY LR'!F36 -> 4.3122334e+09
A8: Add: Interest Expenses | C8: ='INCOME STATEMENT'!E27*-1 -> 942033 | D8: ='PROY LR'!D31*-1 -> 941430.23 | E8: ='PROY LR'!E31*-1 -> 940827.84 | F8: ='PROY LR'!F31*-1 -> 940225.84
A9: Less: Interest Income | C9: ='INCOME STATEMENT'!E26*-1 -> -13957341 | D9: ='PROY LR'!D29*-1 -> -14006615 | E9: ='PROY LR'!E29*-1 -> -14056063 | F9: ='PROY LR'!F29*-1 -> -14105686
A10: Non Operating Income | C10: ='INCOME STATEMENT'!E30*-1 -> 212875 | D10: ='PROY LR'!D34*-1 -> 212874.09 | E10: ='PROY LR'!E34*-1 -> 212873.19 | F10: ='PROY LR'!F34*-1 -> 212872.28
A11: EBIT | C11: =SUM(C7:C10) -> 2261432441 | D11: =SUM(D7:D10) -> 2.4333392e+09 | E11: =SUM(E7:E10) -> 3.2873135e+09 | F11: =SUM(F7:F10) -> 4.2992808e+09
A13: Statutory Tax on EBIT | C13: =C11*STAT_ASSUMPTIONS!$B$5 -> 4.9751514e+08 | D13: =D11*STAT_ASSUMPTIONS!$B$5 -> 5.3533461e+08 | E13: =E11*STAT_ASSUMPTIONS!$B$5 -> 7.2320897e+08 | F13: =F11*STAT_ASSUMPTIONS!$B$5 -> 9.4584179e+08
A14: Tax Shield on Interest Expenses (excluded) | C14: =0 -> 0 | D14: =0 -> 0 | E14: =0 -> 0 | F14: =0 -> 0
A15: Tax on Interest Income (excluded) | C15: =0 -> 0 | D15: =0 -> 0 | E15: =0 -> 0 | F15: =0 -> 0
A16: Tax on Non Operating Income (excluded) | C16: =0 -> 0 | D16: =0 -> 0 | E16: =0 -> 0 | F16: =0 -> 0
A17: Total Taxes on EBIT | C17: =SUM(C13:C16) -> 4.9751514e+08 | D17: =SUM(D13:D16) -> 5.3533461e+08 | E17: =SUM(E13:E16) -> 7.2320897e+08 | F17: =SUM(F13:F16) -> 9.4584179e+08
A19: NOPLAT | C19: =C11-C17 -> 1.7639173e+09 | D19: =D11-D17 -> 1.8980045e+09 | E19: =E11-E17 -> 2.5641045e+09 | F19: =F11-F17 -> 3.3534391e+09 | M19: DCF, Noplat

Sheet WACC
A1: =HOME!B4 -> Makmur Jaya Sejati Raya
A2: Beta Levered
A4: Equity Risk Premium | B4: 0.0762
A5: Rating Based Default Spread | B5: 0.0226
A6: Risk Free (SUN) | B6: 0.027
A10: Perusahaan Pembanding | B10: BL | C10: Market Cap*) | D10: Debt | E10: BU | H10: *) Market Cap : | I10: Jumlah Lembar Saham x Harga Pasar Saham saat Cut Off Date (Lihat di Stockbit)
A11: PT Ancol Makanan, Tbk | B11: 1.2 | C11: 1000000000 | D11: 800000000 | E11: =B11/(1+((1-'INCOME STATEMENT'!$B$33)*(D11/C11))) -> 0.66666667
A12: PT Citra Dara Food, Tbk | B12: 0.7 | C12: 1000000000 | D12: 850000000 | E12: =B12/(1+((1-'INCOME STATEMENT'!$B$33)*(D12/C12))) -> 0.37837838
A13: PT Surya Sehat, Tbk | B13: 0.6 | C13: 1000000000 | D13: 2700000000 | E13: =B13/(1+((1-'INCOME STATEMENT'!$B$33)*(D13/C13))) -> 0.16216216
A14: Rata-rata | B14: =AVERAGE(B11:B13) -> 0.83333333 | C14: =SUM(C11:C13) -> 3000000000 | D14: =SUM(D11:D13) -> 4350000000 | E14: =AVERAGE(E11:E13) -> 0.4024024
A15: Relevered Beta | E15: =E14*(1+((1-'INCOME STATEMENT'!B33)*(D14/C14))) -> 0.98588589
A17: Struktur Kapital | B17: Nilai | C17: Bobot (%) Pasar | D17: Biaya Mdl (%) | E17: WACC
A19: Hutang | B19: ='BALANCE SHEET'!C34+'BALANCE SHEET'!C39 -> 1846235691 | C19: =D14/(D14+C14) -> 0.59183673 | D19: =B30*(1-'INCOME STATEMENT'!B33) -> 0.13 | E19: =C19*D19 -> 0.076938776
A20: Ekuitas | B20: ='BALANCE SHEET'!C48 -> 16645436325 | C20: =1-C19 -> 0.40816327 | D20: =B6+(E15*B4)-B5 -> 0.079524505 | E20: =C20*D20 -> 0.032458981
A22: Weighted Average Cost of Capital (WACC) | E22: 0.1031 | F22: **) Menurut Wajib Pajak
A26: Bunga Pinjaman Investasi
A27: 1. Bank Persero | B27: 0.12
A28: 2. Bank Swasta | B28: 0.13
A29: 3. Bank Umum | B29: 0.14
A30: rata-rata | B30: =+AVERAGE(B27:B29) -> 0.13

Sheet GROWTH REVENUE
A2: GROWTH
A4: =HOME!B4 -> Makmur Jaya Sejati Raya
A6: ="DATA PENJUALAN "&HOME!B4 -> DATA PENJUALAN Makmur Jaya Sejati Raya | G6: ="GROWTH SALES AND NET INCOME "&HOME!B4 -> GROWTH SALES AND NET INCOME Makmur Jaya Sejati Raya
A7: Uraian | B7: =0 -> 0 | C7: ='INCOME STATEMENT'!C5 -> 2019 | D7: ='INCOME STATEMENT'!D5 -> 2020 | E7: ='INCOME STATEMENT'!E5 -> 2021 | G7: Uraian | H7: =C7 -> 2019 | I7: =D7 -> 2020 | J7: =E7 -> 2021
A8: Penjualan | B8: =0 -> 0 | C8: ='INCOME STATEMENT'!C6 -> 9335637236 | D8: ='INCOME STATEMENT'!D6 -> 11406787320 | E8: ='INCOME STATEMENT'!E6 -> 16663916100 | G8: Penjualan | H8: =IF(B8=0,0,(C8-B8)/B8) -> 0 | I8: =IF(C8=0,0,(D8-C8)/C8) -> 0.22185417 | J8: =IF(D8=0,0,(E8-D8)/D8) -> 0.46087725
A9: Laba Bersih | B9: =0 -> 0 | C9: ='INCOME STATEMENT'!C35 -> 440745074 | D9: ='INCOME STATEMENT'!D35 -> 754862153 | E9: ='INCOME STATEMENT'!E35 -> 1838106527 | G9: Laba Bersih | H9: =IF(B9=0,0,(C9-B9)/B9) -> 0 | I9: =IF(C9=0,0,(D9-C9)/C9) -> 0.71269561 | J9: =IF(D9=0,0,(E9-D9)/D9) -> 1.4350228
L11: Y = -3E+06x + 7E+07
L12: Year | M12: x | N12: -3E+06 | O12: 7E+07 | P12: Proyeksi Sales
L13: =B8 -> 0 | M13: 1 | N13: -3000000 | O13: 70000000 | P13: =(N13*M13)+O13 -> 67000000
L14: =+L13+1 -> 1 | M14: 2 | N14: -3000000 | O14: 70000000 | P14: =(N14*M14)+O14 -> 64000000
L15: =+L14+1 -> 2 | M15: 3 | N15: -3000000 | O15: 70000000 | P15: =(N15*M15)+O15 -> 61000000
L16: =+L15+1 -> 3 | M16: 4 | N16: -3000000 | O16: 70000000 | P16: =(N16*M16)+O16 -> 58000000
L17: =+L16+1 -> 4 | M17: 5 | N17: -3000000 | O17: 70000000 | P17: =(N17*M17)+O17 -> 55000000
L18: =+L17+1 -> 5 | M18: 6 | N18: -3000000 | O18: 70000000 | P18: =(N18*M18)+O18 -> 52000000
L19: =+L18+1 -> 6 | M19: 7 | N19: -3000000 | O19: 70000000 | P19: =(N19*M19)+O19 -> 49000000
L20: =+L19+1 -> 7 | M20: 8 | N20: -3000000 | O20: 70000000 | P20: =(N20*M20)+O20 -> 46000000
L21: MEAN (AVERAGE GROWTH)
A36: INDUSTRI
A38: ="DATA PENJUALAN/PENDAPATAN INDUSTRI" -> DATA PENJUALAN/PENDAPATAN INDUSTRI | G38: ="GROWTH INDUSTRI " -> GROWTH INDUSTRI
A39: Uraian | B39: =B7 -> 0 | C39: =C7 -> 2019 | D39: =D7 -> 2020 | E39: =E7 -> 2021 | G39: Uraian | H39: =C39 -> 2019 | I39: =D39 -> 2020 | J39: =E39 -> 2021
A40: Penjualan | G40: Penjualan | H40: =IF(B40=0,0,(C40-B40)/B40) -> 0 | I40: =IF(C40=0,0,(D40-C40)/C40) -> 0 | J40: =IF(D40=0,0,(E40-D40)/D40) -> 0
A41: Pendapatan Bersih | G41: Pendapatan Bersih | H41: =IF(B41=0,0,(C41-B41)/B41) -> 0 | I41: =IF(C41=0,0,(D41-C41)/C41) -> 0 | J41: =IF(D41=0,0,(E41-D41)/D41) -> 0
A58: =A2 -> GROWTH
A60: ="PERBANDINGAN GROWTH INDUSTRI DENGAN "&A4 -> PERBANDINGAN GROWTH INDUSTRI DENGAN Makmur Jaya Sejati Raya
A62: DATA PENJUALAN/PENDAPATAN PT NSK INDONESIA | G62: GROWTH PT NSK INDONESIA
A63: Uraian | B63: =B39 -> 0 | C63: =C39 -> 2019 | D63: =D39 -> 2020 | E63: =E39 -> 2021 | G63: Uraian | H63: =C63 -> 2019 | I63: =D63 -> 2020 | J63: =E63 -> 2021
A64: Penjualan | B64: =B8 -> 0 | C64: =C8 -> 9335637236 | D64: =D8 -> 11406787320 | E64: =E8 -> 16663916100 | G64: Penjualan | H64: =IF(B64=0,0,(C64-B64)/B64) -> 0 | I64: =IF(C64=0,0,(D64-C64)/C64) -> 0.22185417 | J64: =IF(D64=0,0,(E64-D64)/D64) -> 0.46087725
A65: Pendapatan Bersih | B65: =B9 -> 0 | C65: =C9 -> 440745074 | D65: =D9 -> 754862153 | E65: =E9 -> 1838106527 | G65: Pendapatan Bersih | H65: =IF(B65=0,0,(C65-B65)/B65) -> 0 | I65: =IF(C65=0,0,(D65-C65)/C65) -> 0.71269561 | J65: =IF(D65=0,0,(E65-D65)/D65) -> 1.4350228
A66: ="DATA PENJUALAN/PENDAPATAN INDUSTRI" -> DATA PENJUALAN/PENDAPATAN INDUSTRI | G66: ="GROWTH INDUSTRI " -> GROWTH INDUSTRI
A67: Uraian | B67: =B63 -> 0 | C67: =C63 -> 2019 | D67: =D63 -> 2020 | E67: =E63 -> 2021 | G67: Uraian | H67: =C67 -> 2019 | I67: =D67 -> 2020 | J67: =E67 -> 2021
A68: Penjualan | B68: =B40 -> 0 | C68: =C40 -> 0 | D68: =D40 -> 0 | E68: =E40 -> 0 | G68: Penjualan | H68: =IF(B68=0,0,(C68-B68)/B68) -> 0 | I68: =IF(C68=0,0,(D68-C68)/C68) -> 0 | J68: =IF(D68=0,0,(E68-D68)/D68) -> 0
A69: Pendapatan Bersih | B69: =B41 -> 0 | C69: =C41 -> 0 | D69: =D41 -> 0 | E69: =E41 -> 0 | G69: Pendapatan Bersih | H69: =IF(B69=0,0,(C69-B69)/B69) -> 0 | I69: =IF(C69=0,0,(D69-C69)/C69) -> 0 | J69: =IF(D69=0,0,(E69-D69)/D69) -> 0

Sheet PANGSA PASAR
C1: PEMBANDING 1
A2: PANGSA PASAR | B2: PENJUALAN PERUSAHAAN
B3: PENJUALAN TOTAL INDUSTRI

Sheet PASAR PEMBANDING_
B1: PERHITUNGAN KESEBANDINGAN
B2: URAIAN | C2: (dalam USD) | G2: RASIO | K2: SKOR KESEBANDINGAN
C3: ='PASAR KESEBANDINGAN'!L39 -> CHEM | D3: ='PASAR KESEBANDINGAN'!M39 -> CLPI | E3: ='PASAR KESEBANDINGAN'!N39 -> CTBN | F3: OBYEK PENILAIAN | G3: =C3 -> CHEM | H3: =D3 -> CLPI | I3: =E3 -> CTBN | J3: OBYEK PENILAIAN | K3: =G3 -> CHEM | L3: =H3 -> CLPI | M3: =I3 -> CTBN
B4: Pendapatan | C4: 430754674 | D4: 25247152 | E4: 53564289 | F4: ='INCOME STATEMENT'!E6 -> 16663916100
B5: Laba Kotor | C5: 64890712 | D5: 2946925 | E5: 16382726 | F5: ='INCOME STATEMENT'!E8 -> 5884257886 | G5: =C5/C$4 -> 0.15064424 | H5: =D5/D$4 -> 0.11672307 | I5: =E5/E$4 -> 0.30585164 | J5: =F5/F$4 -> 0.35311375
B6: Laba Usaha | C6: 17145071 | D6: -8691889 | E6: 9922149.2 | F6: ='INCOME STATEMENT'!E18 -> 3243162782 | G6: =C6/C$4 -> 0.039802403 | H6: =D6/D$4 -> -0.34427206 | I6: =E6/E$4 -> 0.18523814 | J6: =F6/F$4 -> 0.19462189 | K6: 1 | L6: 0 | M6: 0
B7: Laba Bersih | C7: 11537048 | D7: -10798748 | E7: 3274641.6 | F7: ='INCOME STATEMENT'!E35 -> 1838106527 | G7: =C7/C$4 -> 0.026783338 | H7: =D7/D$4 -> -0.42772143 | I7: =E7/E$4 -> 0.061134791 | J7: =F7/F$4 -> 0.1103046 | K7: 0 | L7: 0 | M7: 1
E8: 0
B9: Aset Lancar | C9: 213098529 | D9: 10349688 | E9: 10893780 | F9: ='BALANCE SHEET'!E15 -> 1266935637 | G9: =C9/C$11 -> 0.36192765 | H9: =D9/D$11 -> 0.1308411 | I9: =E9/E$11 -> 0.10391162 | J9: =F9/F$11 -> 12.084817 | K9: 0 | L9: 1 | M9: 0
B10: Aset Tidak Lancar | C10: 375689124 | D10: 68751512 | E10: 93943196 | F10: ='BALANCE SHEET'!E24 -> 16011357394 | G10: =C10/C$11 -> 0.63807235 | H10: =D10/D$11 -> 0.8691589 | I10: =E10/E$11 -> 0.89608838 | J10: =F10/F$11 -> 152.72624 | K10: 1 | L10: 0 | M10: 0
B11: Total Aset | C11: =+C9+C10 -> 588787653 | D11: =+D9+D10 -> 79101200 | E11: 1.0483698e+08 | F11: 1.0483698e+08
B12: Liabilitas Jk Pendek | C12: 188729175 | D12: 14443414 | E12: 25434442 | F12: ='BALANCE SHEET'!E34 -> 3577237782 | G12: =C12/C$14 -> 0.66734838 | H12: =D12/D$14 -> 0.29152606 | I12: =E12/E$14 -> 0.3456281 | J12: =F12/F$14 -> 48.611008 | K12: 0 | L12: 1 | M12: 0
B13: Liabilitas Jk Panjang | C13: 94075398 | D13: 35100747 | E13: 48154605 | F13: ='BALANCE SHEET'!E39 -> 0 | G13: =C13/C$14 -> 0.33265162 | H13: =D13/D$14 -> 0.70847394 | I13: =E13/E$14 -> 0.6543719 | J13: =F13/F$14 -> 0 | K13: 1 | L13: 0 | M13: 0
B14: Total Liabilitas | C14: =+C12+C13 -> 282804573 | D14: =+D12+D13 -> 49544161 | E14: 73589047 | F14: 73589047
B15: Ekuitas | C15: 305983080 | D15: 29557039 | E15: 31247929 | F15: ='BALANCE SHEET'!E48 -> 13816821754 | G15: =C15/C$11 -> 0.51968325 | H15: =D15/D$11 -> 0.37366107 | I15: =E15/E$11 -> 0.2980621 | J15: =F15/F$11 -> 131.7934 | K15: 0 | L15: 0 | M15: 1
B16: Harga Pasar Saham (IDR)*) | C16: 78 | D16: 196 | E16: 357
B17: Jumlah Lembar | C17: 3275120000 | D17: 23483317538 | E17: 3397500000
B18: Market Cap (IDR) | C18: =+C16*C17 -> 255459360000 | D18: =+D16*D17 -> 4602730237448 | E18: =+E16*E17 -> 1212907500000
B19: Kurs | C19: =DCF!C41 -> 5280000000 | D19: =C19 -> 5280000000 | E19: =D19 -> 5280000000
B20: Market Cap (USD) | C20: =C18/C19 -> 48.382455 | D20: =D18/D19 -> 871.72921 | E20: =E18/E19 -> 229.71733
B21: *) Historis harga pasar saham pada tanggal Penilaian, sumber Stockbit.com | K21: =SUM(K6:K15) -> 3 | L21: =SUM(L6:L15) -> 2 | M21: =SUM(M6:M15) -> 2
K22: =K21/SUM($K$21:$M$21) -> 0.42857143 | L22: =L21/SUM($K$21:$M$21) -> 0.28571429 | M22: =M21/SUM($K$21:$M$21) -> 0.28571429
B23: PERHITUNGAN NILAI
B24: MULTIPLE | C24: MULTIPLE VALUE | F24: FUNDAMENTAL | H24: WEIGHTED | I24: VALUE
B25: Skor Kesebandingan | C25: =K22 -> 0.42857143 | D25: =L22 -> 0.28571429 | E25: =M22 -> 0.28571429
B26: P/S | C26: ='PASAR KESEBANDINGAN'!L40 -> 1.7049226 | D26: ='PASAR KESEBANDINGAN'!M40 -> 0.37422902 | E26: ='PASAR KESEBANDINGAN'!N40 -> 0.35850278 | F26: =F4 -> 16663916100 | G26: =($C$25*C26*F26)+($D$25*D26*F26)+($E$25*E26*F26) -> 1.5664632e+10 | H26: 0 | I26: =G26*H26 -> 0
B27: P/B | C27: ='PASAR KESEBANDINGAN'!L41 -> 1.8347108 | D27: ='PASAR KESEBANDINGAN'!M41 -> 0.54297062 | E27: ='PASAR KESEBANDINGAN'!N41 -> 0.72881455 | F27: =F15 -> 13816821754 | G27: =($C$25*C27*F27)+($D$25*D27*F27)+($E$25*E27*F27) -> 1.5884811e+10 | H27: =1-H26 -> 1 | I27: =G27*H27 -> 1.5884811e+10
F28: INDICATED VALUE OF EQUITY | I28: =+I26+I27 -> 1.5884811e+10
F29: PFC | H29: ='DLOC(PFC)'!E25 -> 0.34 | I29: =I28*H29 -> 5.4008356e+09
F30: CONTROLING INDICATED VALUE OF EQUITY | I30: =+I28+I29 -> 2.1285646e+10
F31: DLOM | H31: =DCF!B34 -> 0 | I31: =I30*H31 -> 0
F32: MARKET VALUE OF EQUITY | I32: =+I30+I31 -> 2.1285646e+10
F33: SHARES | H33: 0.95
F34: ="MARKET VALUE OF "&TEXT(H33,"0,0%")&" EQUITY" -> MARKET VALUE OF 95% EQUITY | I34: =I32*H33 -> 2.0221364e+10
F35: Kurs | I35: =DCF!C41 -> 5280000000
F36: Nilai Pasar Saham | I36: =I34*I35 -> 1.067688e+20
F37: Menurut WP | I37: =DCF!C44 -> 0
F38: Selisih | I38: =I36-I37 -> 1.067688e+20 | J38: =(I38-I37)/I37 -> #DIV/0!
F39: Tarif | H39: =DCF!B47 -> 0 | I39: =I38*H39 -> 0

Sheet PASAR KESEBANDINGAN1
A1: ANALISIS KESEBANDINGAN
A2: ="PENILAIAN SAHAM "&HOME!B4 -> PENILAIAN SAHAM Makmur Jaya Sejati Raya
A3: CUT OFF DATE: | B3: =HOME!B20 -> 44561
A6: NO | B6: PERUSAHAAN PEMBANDING | F6: OBYEK PENILAIAN | G6: SKOR KESEBANDINGAN
B7: KODE EMITEN | C7: TAHUN | D7: PARAMETER | E7: RASIO
A8: 1 | B8: SMDR | C8: =YEAR($B$3)-2 -> 2019 | D8: DER
D9: ROA
D10: ROE
D11: NPM
C15: =YEAR($B$3)-1 -> 2020 | D15: DER
D16: ROA
D17: ROE
D18: NPM
C22: =YEAR($B$3) -> 2021 | D22: DER
D23: ROA
D24: ROE
D25: NPM
C27: RATA-RATA | D27: DER | E27: =IFERROR(AVERAGE(E8,E15,E22),0) -> 0 | F27: =IFERROR(AVERAGE(F8,F15,F22),0) -> 0
D28: ROA | E28: =IFERROR(AVERAGE(E9,E16,E23),0) -> 0 | F28: =IFERROR(AVERAGE(F9,F16,F23),0) -> 0
D29: ROE | E29: =IFERROR(AVERAGE(E10,E17,E24),0) -> 0 | F29: =IFERROR(AVERAGE(F10,F17,F24),0) -> 0
D30: NPM | E30: =IFERROR(AVERAGE(E11,E18,E25),0) -> 0 | F30: =IFERROR(AVERAGE(F11,F18,F25),0) -> 0
C31: JUMLAH | G31: =SUM(G27:G30) -> 0
C32: MEDIAN | D32: DER | E32: =IFERROR(AVERAGE(E12,E19,E26),0) -> 0 | F32: =IFERROR(AVERAGE(F12,F19,F26),0) -> 0
D33: ROA | E33: =IFERROR(AVERAGE(E13,E20,E27),0) -> 0 | F33: =IFERROR(AVERAGE(F13,F20,F27),0) -> 0
D34: ROE | E34: =IFERROR(AVERAGE(E14,E21,E28),0) -> 0 | F34: =IFERROR(AVERAGE(F14,F21,F28),0) -> 0
D35: NPM | E35: =IFERROR(AVERAGE(E15,E22,E29),0) -> 0 | F35: =IFERROR(AVERAGE(F15,F22,F29),0) -> 0
C36: JUMLAH | G36: =SUM(G32:G35) -> 0
A37: 2 | B37: BLTA | C37: =YEAR($B$3)-2 -> 2019 | D37: DER
D38: ROA
D39: ROE
D40: NPM
C44: =YEAR($B$3)-1 -> 2020 | D44: DER
D45: ROA
D46: ROE
D47: NPM
C51: =YEAR($B$3) -> 2021 | D51: DER
D52: ROA
D53: ROE
D54: NPM
C56: RATA-RATA | D56: DER | E56: =IFERROR(AVERAGE(E37,E44,E51),0) -> 0 | F56: =IFERROR(AVERAGE(F37,F44,F51),0) -> 0
D57: ROA | E57: =IFERROR(AVERAGE(E38,E45,E52),0) -> 0 | F57: =IFERROR(AVERAGE(F38,F45,F52),0) -> 0
D58: ROE | E58: =IFERROR(AVERAGE(E39,E46,E53),0) -> 0 | F58: =IFERROR(AVERAGE(F39,F46,F53),0) -> 0
D59: NPM | E59: =IFERROR(AVERAGE(E40,E47,E54),0) -> 0 | F59: =IFERROR(AVERAGE(F40,F47,F54),0) -> 0
C60: JUMLAH | G60: =SUM(G56:G59) -> 0
C61: MEDIAN | D61: DER | E61: =IFERROR(AVERAGE(E41,E48,E55),0) -> 0 | F61: =IFERROR(AVERAGE(F41,F48,F55),0) -> 0
D62: ROA | E62: =IFERROR(AVERAGE(E42,E49,E56),0) -> 0 | F62: =IFERROR(AVERAGE(F42,F49,F56),0) -> 0
D63: ROE | E63: =IFERROR(AVERAGE(E43,E50,E57),0) -> 0 | F63: =IFERROR(AVERAGE(F43,F50,F57),0) -> 0
D64: NPM | E64: =IFERROR(AVERAGE(E44,E51,E58),0) -> 0 | F64: =IFERROR(AVERAGE(F44,F51,F58),0) -> 0
C65: JUMLAH | G65: =SUM(G61:G64) -> 0
A66: 3 | B66: PORT | C66: =YEAR($B$3)-2 -> 2019 | D66: DER
D67: ROA
D68: ROE
D69: NPM
C73: =YEAR($B$3)-1 -> 2020 | D73: DER
D74: ROA
D75: ROE
D76: NPM
C80: =YEAR($B$3) -> 2021 | D80: DER
D81: ROA
D82: ROE
D83: NPM
C85: RATA-RATA | D85: DER | E85: =IFERROR(AVERAGE(E66,E73,E80),0) -> 0 | F85: =IFERROR(AVERAGE(F66,F73,F80),0) -> 0
D86: ROA | E86: =IFERROR(AVERAGE(E67,E74,E81),0) -> 0 | F86: =IFERROR(AVERAGE(F67,F74,F81),0) -> 0
D87: ROE | E87: =IFERROR(AVERAGE(E68,E75,E82),0) -> 0 | F87: =IFERROR(AVERAGE(F68,F75,F82),0) -> 0
D88: NPM | E88: =IFERROR(AVERAGE(E69,E76,E83),0) -> 0 | F88: =IFERROR(AVERAGE(F69,F76,F83),0) -> 0
C89: JUMLAH | G89: =SUM(G85:G88) -> 0
C90: MEDIAN | D90: DER | E90: =IFERROR(AVERAGE(E70,E77,E84),0) -> 0 | F90: =IFERROR(AVERAGE(F70,F77,F84),0) -> 0
D91: ROA | E91: =IFERROR(AVERAGE(E71,E78,E85),0) -> 0 | F91: =IFERROR(AVERAGE(F71,F78,F85),0) -> 0
D92: ROE | E92: =IFERROR(AVERAGE(E72,E79,E86),0) -> 0 | F92: =IFERROR(AVERAGE(F72,F79,F86),0) -> 0
D93: NPM | E93: =IFERROR(AVERAGE(E73,E80,E87),0) -> 0 | F93: =IFERROR(AVERAGE(F73,F80,F87),0) -> 0
C94: JUMLAH | G94: =SUM(G90:G93) -> 0
A96: BOBOT KESEBANDINGAN
A98: NO | B98: KODE EMITEN | C98: SKOR RATA-RATA | D98: SKOR MEDIAN | E98: BOBOT RATA-RATA | F98: BOBOT MEDIAN
B99: =B8 -> SMDR | C99: =G31 -> 0 | D99: =G36 -> 0 | E99: =IFERROR(C99/SUM($C$99:$C$101),0) -> 0 | F99: =IFERROR(D99/SUM($D$99:$D$101),0) -> 0
B100: =B37 -> BLTA | C100: =G60 -> 0 | D100: =G65 -> 0 | E100: =IFERROR(C100/SUM($C$99:$C$101),0) -> 0 | F100: =IFERROR(D100/SUM($D$99:$D$101),0) -> 0
B101: =B66 -> PORT | C101: =G89 -> 0 | D101: =G94 -> 0 | E101: =IFERROR(C101/SUM($C$99:$C$101),0) -> 0 | F101: =IFERROR(D101/SUM($D$99:$D$101),0) -> 0

Sheet AAM
A1: ='BALANCE SHEET'!A1 -> Makmur Jaya Sejati Raya
A2: Metode Penyesuaian Aset Bersih
A3: ='BALANCE SHEET'!A3 -> (IDR)
C5: ='BALANCE SHEET'!E4 -> 2021 | D5: Penyesuaian | E5: =C5&"*)" -> 2021*)
A6: ASSETS
A8: Current Assets
B9: Cash on Hands | C9: ='BALANCE SHEET'!E8 -> 717848795 | D9: 0 | E9: =C9+D9 -> 717848795
B10: Cash on Bank (Deposit) | C10: ='BALANCE SHEET'!E9 -> 337031731 | D10: 0 | E10: =C10+D10 -> 337031731
B11: Account Receivable | C11: ='BALANCE SHEET'!E10 -> 191055111 | D11: 0 | E11: =C11+D11 -> 191055111
B12: Other Receivable | C12: ='BALANCE SHEET'!E11 -> 21000000 | D12: 0 | E12: =C12+D12 -> 21000000
B13: Inventory | C13: ='BALANCE SHEET'!E12 -> 0 | D13: 0 | E13: =C13+D13 -> 0
B14: Others | C14: ='BALANCE SHEET'!E13 -> 0 | D14: 0 | E14: =C14+D14 -> 0
A16: Current Assets | C16: =SUM(C9:C14) -> 1266935637 | E16: =SUM(E9:E14) -> 1266935637
A18: Non Current Assets
A19: Fixed Asset | B19: Beginning | C19: ='BALANCE SHEET'!E19 -> 21000894104 | D19: 0 | E19: =C19+D19 -> 21000894104
B20: Fixed Assets, Net | C20: ='BALANCE SHEET'!E21 -> 16011357394 | D20: 0 | E20: =C20+D20 -> 16011357394
A21: Non Current Assets | C21: ='BALANCE SHEET'!E22 -> 0 | D21: 0 | E21: =C21+D21 -> 0
A22: Total Non Current Asset | C22: ='BALANCE SHEET'!E24 -> 16011357394 | D22: 0 | E22: =SUM(E20:E21) -> 16011357394
A23: Intangible Asset | C23: ='BALANCE SHEET'!E23 -> 0 | D23: 0 | E23: =C23 -> 0
A24: ASSETS | C24: =+C16+C22 -> 17278293031 | E24: =+E16+E22+E23 -> 17278293031
A26: LIABILITIES & EQUITY
A27: Current Liabilities
B28: Bank Loan-Short Term | C28: ='BALANCE SHEET'!E30 -> 0 | D28: 0 | E28: =+C28+D28 -> 0
B29: Account Payables | C29: ='BALANCE SHEET'!E31 -> 1823364600 | D29: 0 | E29: =+C29+D29 -> 1823364600
B30: Tax Payable | C30: ='BALANCE SHEET'!E32 -> 678518254 | D30: 0 | E30: =+C30+D30 -> 678518254
B31: Others | C31: ='BALANCE SHEET'!E33 -> 1075354928 | D31: 0 | E31: =+C31+D31 -> 1075354928
A32: Current Liabilities | C32: =SUM(C28:C31) -> 3577237782 | E32: =SUM(E28:E31) -> 3577237782
A34: Non Current Liabilities
B35: Bank Loan-Long Term | C35: ='BALANCE SHEET'!E37 -> 0 | D35: 0 | E35: =+C35+D35 -> 0
B36: Related Party acc. Payable & Employee Benefits | C36: ='BALANCE SHEET'!E38 -> 0 | D36: 0 | E36: =+C36+D36 -> 0
A37: Non Current Liabilities | C37: =+C35+C36 -> 0 | E37: =+E35+E36 -> 0
A39: Shareholders' Equity
A40: Paid Up Capital | C40: ='BALANCE SHEET'!E42 -> 5280000000 | E40: =+C40+D40 -> 5280000000
A41: Addition | C41: ='BALANCE SHEET'!E43 -> 0 | E41: =+C41+D41 -> 0
A42: Retained Earnings
B43: Deficit | C43: ='BALANCE SHEET'!E45 -> 6698715227 | D43: 0 | E43: =+C43+D43 -> 6698715227
B44: Current profit | C44: ='BALANCE SHEET'!E46 -> 1838106527 | E44: =+C44+D44 -> 1838106527
A45: Retained Earnings, Ending Balance | C45: =C43+C44 -> 8536821754 | E45: =+C45+D45 -> 8536821754
A46: Changes on Asset Revaluation | C46: 0 | D46: =D20+D21 -> 0 | E46: =+C46+D46 -> 0
A47: Shareholders' Equity | C47: =C40+C45+C41 -> 13816821754 | E47: =E40+E45+E41+E46 -> 13816821754
A49: LIABILITES & EQUITY | C49: =C32+C37+C47 -> 17394059536 | E49: =E32+E37+E47 -> 17394059536
A51: Nett Asset Value | E51: =+E24-(E29+E30+E31)-E36 -> 13701055249
A52: Interest Bearing Debt | E52: =+C28+C35 -> 0
A53: Equity Value | E53: =E51-E52 -> 13701055249
A54: DLOM | D54: =0 -> 0 | E54: =E53*D54 -> 0 | F54: *)
A55: Equity Value (100%) Less DLOM | E55: =E53+E54 -> 13701055249
A56: =HOME!A26 -> DISCOUNT LACK OF CONTROL/PREMIUM FOR CONTROL | D56: =0 -> 0 | E56: =E55*D56 -> 0
A57: Market Value of Equity (100%) | E57: =E55+E56 -> 13701055249
A58: Percentage of Shares | D58: =1 -> 1
A59: Market Value of 100% Equity | E59: =E57*D58 -> 13701055249
A60: Value per share | E60: =E59/HOME!B15 -> 2.5948968
C67: DLOM | D67: Paling Tinggi (Resiko Rendah) | E67: =40%*-1 -> -0.4
D68: Moderat | E68: =30%*-1 -> -0.3
D69: Paling Rendah (Resiko Tinggi) | E69: =20%*-1 -> -0.2
C70: DLOC (PFC) | D70: Paling Tinggi (Resiko Rendah) | E70: =70%*-1 -> -0.7
D71: Moderat | E71: =50%*-1 -> -0.5
D72: Paling Rendah (Resiko Tinggi) | E72: =30%*-1 -> -0.3
A75: *)DLOM perusahaan terbuka pemegang saham mayoritas maksimal 20% (pasal 41 huruf b ayat 1 POJK 35)

Sheet BORROWING CAP
B1: RATE OF RETURN ON NETT TANGIBLE ASSET
B3: BORROWING CAPACITY
B4: No | C4: Jenis Aktiva | D4: Jumlah | E4: Borrowing Capacity (%) | F4: Borrowing Capacity
B5: 1 | C5: Piutang | D5: ='BALANCE SHEET'!E10 -> 191055111 | E5: =F5/D5 -> 1.1099159 | F5: ='BALANCE SHEET'!E10+'BALANCE SHEET'!E11 -> 212055111 | G5: CALK 5
B6: 2 | C6: Persediaan | D6: ='BALANCE SHEET'!C12 -> 0 | E6: =IFERROR(F6/D6,0) -> 0 | F6: ='BALANCE SHEET'!E12 -> 0 | G6: CALK 7
B7: 3 | C7: Aktiva Tetap | D7: ='BALANCE SHEET'!E21 -> 16011357394 | E7: 0.7 | F7: =D7*E7 -> 1.120795e+10
C8: Jumlah | D8: =SUM(D5:D7) -> 16202412505 | F8: =SUM(F5:F7) -> 1.1420005e+10
B10: TINGKAT BALIKAN RATA-RATA TERTIMBANG
B11: No | C11: Jenis Modal | D11: Biaya Modal | E11: Bobot | F11: Biaya Modal Tertimbang
B12: 1 | C12: Hutang | D12: ='DISCOUNT RATE'!G7 -> 0.06864 | E12: =F8/D8 -> 0.70483363 | F12: =E12*D12 -> 0.048379781
B13: 2 | C13: Ekuitas | D13: ='DISCOUNT RATE'!G8 -> 0.124537 | E13: =1-E12 -> 0.29516637 | F13: =E13*D13 -> 0.036759134
F14: =+F12+F13 -> 0.085138914
F16: =EEM!D43 -> 6026194000

Sheet DISCOUNT RATE
A1: Discount Rate Analysis (CAPM) | E1: BU = B/(1+ ( (1-t)x DER)) | G1: = | H1: =C4/(1+((1-C2)*C8)) -> 0.93320959
A2: Tax Rate | C2: 0.22 | E2: BL = BU x ( 1+ ((1-t)x DER )) | G2: = | H2: =H1*(1+((1-C2)*C8)) -> 1.09
A3: Risk Free | C3: 0.064795 | E3: Ke = Rf + (β.Rp) - RBDS | G3: = | H3: =C3+(H2*C5)-C6 -> 0.124537
A4: Beta | C4: 1.09 | E4: Kd = i x (1 - t) | G4: = | H4: =C7*(1-C2) -> 0.06864
A5: Equity Risk Premium (Rating) | C5: 0.0738 | E5: Struktur Kapital | F5: Bobot (%) Pasar | G5: Biaya Mdl (%) | H5: WACC (%) | K5: pinjaman inves
A6: Country Default Spread (Based on Rating) | C6: 0.0207 | K6: BANK PERSERO | L6: 9.41
A7: Debt Rate | C7: =ROUND(L11/100,3) -> 0.088 | E7: Hutang | F7: =C8/(1+C8) -> 0.1772256 | G7: =H4 -> 0.06864 | H7: =F7*G7 -> 0.012164766 | K7: BANK PEMDAS | L7: 9.06
A8: DER industry | C8: 0.2154 | E8: Ekuitas | F8: =1-F7 -> 0.8227744 | G8: =H3 -> 0.124537 | H8: =F8*G8 -> 0.10246585 | K8: BANK SWASNAS | L8: 8.23
A9: CoE | C9: =H3 -> 0.124537 | K9: BANK ASENG | L9: 8.51
A10: CoD | C10: =H4 -> 0.06864 | E10: Weighted Average Cost of Capital (WACC) | H10: =+H7+H8 -> 0.11463062 | K10: BANK OM OM | L10: 8.81
A11: WACC | C11: =H10 -> 0.11463062 | K11: AVERAGE | L11: =AVERAGE(L6:L10) -> 8.804
A12: Growth | C12: ='GROWTH RATE'!B15 -> -0.039131153

Sheet EEM
B2: =HOME!B4 -> Makmur Jaya Sejati Raya
B3: Metode Kapitalisasi Kelebihan Pendapatan
B4: ='BALANCE SHEET'!A3 -> (IDR) | C4: *)Kecuali Dinyatakan Lain
B5: FCFF Model
B7: Nett Tangible Asset Value | D7: =STAT_EEM!B7 -> 13303692977 | F7: aktiva berwujudnya (tidak termasuk non operating asset)
B8: Return on Tangibel Asset | C8: =STAT_EEM!B15 -> 0.085138914
B9: Earning Return on Nett Tangible Asset | D9: =D7*C8 -> 1.132662e+09 | F9: pendapatan yang digenerate oleh aktiva berwujud operasional
B12: NOPLAT | D12: =STAT_EEM!B14 -> 1.7639173e+09
B13: Add: Depreciation | D13: =0 -> 0
B14: Gross Cash Flow | D14: =D12+D13 -> 1.7639173e+09
B16: Changes in Working Capital
B17: (Increase) Decrease in Current Asset | D17: =0 -> 0
B18: Increase (Decrease) in Current Liabilities | D18: =0 -> 0
B19: Total Net Changes in Working Capital | D19: =0 -> 0
B21: Less: Capital Expenditures | D21: =0 -> 0
B23: Gross Investment | D23: =0 -> 0
B25: Free Cash Flow | D25: =D14+D23 -> 1.7639173e+09 | F25: arus kas bebas
B27: Excess Earning | D27: =D25-D9 -> 6.3125533e+08 | F27: pendapatan yang digenerate dari aktiva tidak berwujud
B28: Capitalization Rate | C28: =STAT_EEM!B18 -> 0.11463062
B29: Capitalized Excess Earning | D29: =D27/C28 -> 5.5068648e+09 | F29: atb ---> goodwill
B31: Enterprise Value | D31: =D7+D29 -> 1.8810558e+10
B32: Interest Bearing Debt | D32: =-STAT_EEM!B21 -> 0
B33: Non Operating Asset | D33: =STAT_EEM!B11 -> 1075880526
B34: Equity Value (100%) | D34: =D31+D32+D33 -> 1.9886438e+10
B35: DLOM | C35: =0 -> 0 | D35: =D34*C35 -> 0
B36: Equity Value (100%) Less DLOM | D36: =D34+D35 -> 1.9886438e+10
B37: =HOME!A26 -> DISCOUNT LACK OF CONTROL/PREMIUM FOR CONTROL | C37: =0 -> 0 | D37: =D36*C37 -> 0
B38: Market Value of Equity (100%) | D38: =D36+D37 -> 1.9886438e+10
B39: Percentage of Shares | C39: =HOME!B17 -> 0.3030303
B40: ="Market Value of "&TEXT(C39,"0.00%")&" Equity" -> Market Value of 30.30% Equity | D40: =D38*C39 -> 6.0261934e+09
B41: =AAM!B62 -> 0 | D41: 1 | E41: US$
B42: In IDR | D42: =D40*D41 -> 6.0261934e+09 | E42: Rp
B43: Rounded | D43: =ROUNDUP(D42,-3) -> 6026194000 | E43: Rp
B44: Jumlah Lembar | D44: =HOME!B15 -> 5280000000
D45: =D42/D44 -> 1.1413245
D46: =D43-D44 -> 746194000

Sheet PASAR KESEBANDINGAN
B1: RASIO KEUANGAN OBYEK PENILAIAN DAN PERUSAHAAN PEMBANDING
B2: NO. | C2: EMITEN | D2: NAMA PERUSAHAAN | E2: DER | F2: ROA | G2: ROE | H2: NPM | I2: TOTAL | J2: SKOR DER | K2: SKOR ROA | L2: SKOR ROE | M2: SKOR NPM | N2: SKOR PANGSA PASAR | O2: TOTAL SKOR | P2: DATA PEMBANDING YANG DIGUNAKAN
I3: SALES
C4: PAS | D4: OBYEK PEMBANDING | E4: ='FINANCIAL RATIO'!F20 -> 0.25890453 | F4: ='FINANCIAL RATIO'!F10 -> 0.10638241 | G4: ='FINANCIAL RATIO'!F11 -> 0.13303396 | H4: ='FINANCIAL RATIO'!F9 -> 0.1103046
B5: 1 | C5: ALDO | D5: =IFERROR(VLOOKUP(C5,EMITEN,2,FALSE),"") -> Alkindo Naratama Tbk | E5: 1.15 | F5: 0.0086 | G5: 0.0184 | H5: 0.0125 | J5: =IF(AND(E5>=E$33*-1,E5<=E$34),1,0) -> 0 | K5: =IF(AND(F5>=F$33*-1,F5<=F$34),1,0) -> 1 | L5: =IF(AND(G5>=G$33*-1,G5<=G$34),1,0) -> 1 | M5: =IF(AND(H5>=H$33*-1,H5<=H$34),1,0) -> 1 | O5: =SUM(J5:M5) -> 3 | P5: =IF(O5=$E$35,C5,"")
B6: =+B5+1 -> 2 | C6: ALKA | D6: =IFERROR(VLOOKUP(C6,EMITEN,2,FALSE),"") -> Alakasa Industrindo Tbk | E6: 1.89 | F6: 0.0854 | G6: 0.25 | H6: 0.0279 | J6: =IF(AND(E6>=E$33*-1,E6<=E$34),1,0) -> 0 | K6: =IF(AND(F6>=F$33*-1,F6<=F$34),1,0) -> 1 | L6: =IF(AND(G6>=G$33*-1,G6<=G$34),1,0) -> 0 | M6: =IF(AND(H6>=H$33*-1,H6<=H$34),1,0) -> 1 | O6: =SUM(J6:M6) -> 2 | P6: =IF(O6=$E$35,C6,"")
B7: =+B6+1 -> 3 | C7: AMMN | D7: =IFERROR(VLOOKUP(C7,EMITEN,2,FALSE),"") -> PT Amman Mineral Internasional Tbk. | E7: 0.44 | F7: 0.0526 | G7: 0.0985 | H7: 0.38 | J7: =IF(AND(E7>=E$33*-1,E7<=E$34),1,0) -> 1 | K7: =IF(AND(F7>=F$33*-1,F7<=F$34),1,0) -> 1 | L7: =IF(AND(G7>=G$33*-1,G7<=G$34),1,0) -> 1 | M7: =IF(AND(H7>=H$33*-1,H7<=H$34),1,0) -> 0 | O7: =SUM(J7:M7) -> 3 | P7: =IF(O7=$E$35,C7,"")
B8: =+B7+1 -> 4 | C8: ANTM | D8: =IFERROR(VLOOKUP(C8,EMITEN,2,FALSE),"") -> Aneka Tambang Tbk. | E8: 0.44 | F8: 0.11 | G8: 0.16 | H8: 0.13 | J8: =IF(AND(E8>=E$33*-1,E8<=E$34),1,0) -> 1 | K8: =IF(AND(F8>=F$33*-1,F8<=F$34),1,0) -> 0 | L8: =IF(AND(G8>=G$33*-1,G8<=G$34),1,0) -> 0 | M8: =IF(AND(H8>=H$33*-1,H8<=H$34),1,0) -> 1 | O8: =SUM(J8:M8) -> 2 | P8: =IF(O8=$E$35,C8,"")
B9: =+B8+1 -> 5 | C9: APLI | D9: =IFERROR(VLOOKUP(C9,EMITEN,2,FALSE),"") -> Asiaplast Industries Tbk | E9: 0.51 | F9: 0.12 | G9: 0.18 | H9: 0.16 | J9: =IF(AND(E9>=E$33*-1,E9<=E$34),1,0) -> 1 | K9: =IF(AND(F9>=F$33*-1,F9<=F$34),1,0) -> 0 | L9: =IF(AND(G9>=G$33*-1,G9<=G$34),1,0) -> 0 | M9: =IF(AND(H9>=H$33*-1,H9<=H$34),1,0) -> 0 | O9: =SUM(J9:M9) -> 1 | P9: =IF(O9=$E$35,C9,"")
B10: =+B9+1 -> 6 | C10: ARCI | D10: =IFERROR(VLOOKUP(C10,EMITEN,2,FALSE),"") -> PT Archi Indonesia Tbk | E10: 2.06 | F10: 0.0134 | G10: 0.0409 | H10: 0.061 | J10: =IF(AND(E10>=E$33*-1,E10<=E$34),1,0) -> 0 | K10: =IF(AND(F10>=F$33*-1,F10<=F$34),1,0) -> 1 | L10: =IF(AND(G10>=G$33*-1,G10<=G$34),1,0) -> 1 | M10: =IF(AND(H10>=H$33*-1,H10<=H$34),1,0) -> 1 | O10: =SUM(J10:M10) -> 3 | P10: =IF(O10=$E$35,C10,"")
B11: =+B10+1 -> 7 | C11: YPAS | D11: =IFERROR(VLOOKUP(C11,EMITEN,2,FALSE),"") -> Yanaprima Hastapersada Tbk | E11: 1.04 | F11: 0.0435 | G11: 0.0887 | H11: 0.0428 | J11: =IF(AND(E11>=E$33*-1,E11<=E$34),1,0) -> 0 | K11: =IF(AND(F11>=F$33*-1,F11<=F$34),1,0) -> 1 | L11: =IF(AND(G11>=G$33*-1,G11<=G$34),1,0) -> 1 | M11: =IF(AND(H11>=H$33*-1,H11<=H$34),1,0) -> 1 | O11: =SUM(J11:M11) -> 3 | P11: =IF(O11=$E$35,C11,"")
B12: =+B11+1 -> 8 | C12: CHEM | D12: =IFERROR(VLOOKUP(C12,EMITEN,2,FALSE),"") -> PT Chemstar Indonesia Tbk | E12: 0.28 | F12: 0.0205 | G12: 0.0261 | H12: 0.0343 | J12: =IF(AND(E12>=E$33*-1,E12<=E$34),1,0) -> 1 | K12: =IF(AND(F12>=F$33*-1,F12<=F$34),1,0) -> 1 | L12: =IF(AND(G12>=G$33*-1,G12<=G$34),1,0) -> 1 | M12: =IF(AND(H12>=H$33*-1,H12<=H$34),1,0) -> 1 | O12: =SUM(J12:M12) -> 4 | P12: =IF(O12=$E$35,C12,"") -> CHEM
B13: =+B12+1 -> 9 | C13: CITA | D13: =IFERROR(VLOOKUP(C13,EMITEN,2,FALSE),"") -> Cita Mineral Investindo Tbk | E13: 0.19 | F13: 0.082 | G13: 0.098 | H13: 0.17 | J13: =IF(AND(E13>=E$33*-1,E13<=E$34),1,0) -> 1 | K13: =IF(AND(F13>=F$33*-1,F13<=F$34),1,0) -> 1 | L13: =IF(AND(G13>=G$33*-1,G13<=G$34),1,0) -> 1 | M13: =IF(AND(H13>=H$33*-1,H13<=H$34),1,0) -> 0 | O13: =SUM(J13:M13) -> 3 | P13: =IF(O13=$E$35,C13,"")
B14: =+B13+1 -> 10 | C14: CLPI | D14: =IFERROR(VLOOKUP(C14,EMITEN,2,FALSE),"") -> Colorpak Indonesia Tbk | E14: 0.38 | F14: 0.0563 | G14: 0.0777 | H14: 0.0706 | J14: =IF(AND(E14>=E$33*-1,E14<=E$34),1,0) -> 1 | K14: =IF(AND(F14>=F$33*-1,F14<=F$34),1,0) -> 1 | L14: =IF(AND(G14>=G$33*-1,G14<=G$34),1,0) -> 1 | M14: =IF(AND(H14>=H$33*-1,H14<=H$34),1,0) -> 1 | O14: =SUM(J14:M14) -> 4 | P14: =IF(O14=$E$35,C14,"") -> CLPI
B15: =+B14+1 -> 11 | C15: CMNT | D15: =IFERROR(VLOOKUP(C15,EMITEN,2,FALSE),"") -> PT Cemindo Gemilang Tbk | E15: 3.45 | F15: 0.0064 | G15: 0.0284 | H15: 0.0167 | J15: =IF(AND(E15>=E$33*-1,E15<=E$34),1,0) -> 0 | K15: =IF(AND(F15>=F$33*-1,F15<=F$34),1,0) -> 1 | L15: =IF(AND(G15>=G$33*-1,G15<=G$34),1,0) -> 1 | M15: =IF(AND(H15>=H$33*-1,H15<=H$34),1,0) -> 1 | O15: =SUM(J15:M15) -> 3 | P15: =IF(O15=$E$35,C15,"")
B16: =+B15+1 -> 12 | C16: CTBN | D16: =IFERROR(VLOOKUP(C16,EMITEN,2,FALSE),"") -> Citra Tubindo Tbk | E16: 0.7 | F16: 0.048 | G16: 0.0819 | H16: 0.0519 | J16: =IF(AND(E16>=E$33*-1,E16<=E$34),1,0) -> 1 | K16: =IF(AND(F16>=F$33*-1,F16<=F$34),1,0) -> 1 | L16: =IF(AND(G16>=G$33*-1,G16<=G$34),1,0) -> 1 | M16: =IF(AND(H16>=H$33*-1,H16<=H$34),1,0) -> 1 | O16: =SUM(J16:M16) -> 4 | P16: =IF(O16=$E$35,C16,"") -> CTBN
B17: =+B16+1 -> 13 | C17: DPNS | D17: =IFERROR(VLOOKUP(C17,EMITEN,2,FALSE),"") -> Duta Pertiwi Nusantara Tbk | E17: 0.18 | F17: 0.0414 | G17: 0.0487 | H17: 0.19 | J17: =IF(AND(E17>=E$33*-1,E17<=E$34),1,0) -> 1 | K17: =IF(AND(F17>=F$33*-1,F17<=F$34),1,0) -> 1 | L17: =IF(AND(G17>=G$33*-1,G17<=G$34),1,0) -> 1 | M17: =IF(AND(H17>=H$33*-1,H17<=H$34),1,0) -> 0 | O17: =SUM(J17:M17) -> 3 | P17: =IF(O17=$E$35,C17,"")
... B24: =+B23+1 -> 20 | C24: PDPP | D24: =IFERROR(VLOOKUP(C24,EMITEN,2,FALSE),"") -> PT Primadaya Plastisindo Tbk | E24: 0.34 | F24: 0.05 | G24: 0.0688 | H24: 0.12 | J24: =IF(AND(E24>=E$33*-1,E24<=E$34),1,0) -> 1 | K24: =IF(AND(F24>=F$33*-1,F24<=F$34),1,0) -> 1 | L24: =IF(AND(G24>=G$33*-1,G24<=G$34),1,0) -> 1 | M24: =IF(AND(H24>=H$33*-1,H24<=H$34),1,0) -> 1 | O24: =SUM(J24:M24) -> 4 | P24: =IF(O24=$E$35,C24,"") -> PDPP
J25: =IF(AND(E25>=E$33*-1,E25<=E$34),1,0) -> 0 | K25: =IF(AND(F25>=F$33*-1,F25<=F$34),1,0) -> 1 | L25: =IF(AND(G25>=G$33*-1,G25<=G$34),1,0) -> 1 | M25: =IF(AND(H25>=H$33*-1,H25<=H$34),1,0) -> 1 | O25: =SUM(J25:M25) -> 3 | P25: =IF(O25=$E$35,C25,"")
J26: =IF(AND(E26>=E$33*-1,E26<=E$34),1,0) -> 0 | K26: =IF(AND(F26>=F$33*-1,F26<=F$34),1,0) -> 1 | L26: =IF(AND(G26>=G$33*-1,G26<=G$34),1,0) -> 1 | M26: =IF(AND(H26>=H$33*-1,H26<=H$34),1,0) -> 1 | O26: =SUM(J26:M26) -> 3 | P26: =IF(O26=$E$35,C26,"")
J27: =IF(AND(E27>=E$33*-1,E27<=E$34),1,0) -> 0 | K27: =IF(AND(F27>=F$33*-1,F27<=F$34),1,0) -> 1 | L27: =IF(AND(G27>=G$33*-1,G27<=G$34),1,0) -> 1 | M27: =IF(AND(H27>=H$33*-1,H27<=H$34),1,0) -> 1 | O27: =SUM(J27:M27) -> 3 | P27: =IF(O27=$E$35,C27,"")
J28: =IF(AND(E28>=E$33*-1,E28<=E$34),1,0) -> 0 | K28: =IF(AND(F28>=F$33*-1,F28<=F$34),1,0) -> 1 | L28: =IF(AND(G28>=G$33*-1,G28<=G$34),1,0) -> 1 | M28: =IF(AND(H28>=H$33*-1,H28<=H$34),1,0) -> 1 | O28: =SUM(J28:M28) -> 3 | P28: =IF(O28=$E$35,C28,"")
J29: =IF(AND(E29>=E$33*-1,E29<=E$34),1,0) -> 0 | K29: =IF(AND(F29>=F$33*-1,F29<=F$34),1,0) -> 1 | L29: =IF(AND(G29>=G$33*-1,G29<=G$34),1,0) -> 1 | M29: =IF(AND(H29>=H$33*-1,H29<=H$34),1,0) -> 1 | O29: =SUM(J29:M29) -> 3 | P29: =IF(O29=$E$35,C29,"")
D31: MEAN | E31: =AVERAGE(E5:E29) -> 0.7615 | F31: =AVERAGE(F5:F29) -> 0.064795 | G31: =AVERAGE(G5:G29) -> 0.10116 | H31: =AVERAGE(H5:H29) -> 0.11632
D32: STANDARD DEVIASI | E32: =_xlfn.STDEV.S(E4:E29) -> 0.81684235 | F32: =_xlfn.STDEV.S(F4:F29) -> 0.043396731 | G32: =_xlfn.STDEV.S(G4:G29) -> 0.065140271 | H32: =_xlfn.STDEV.S(H4:H29) -> 0.091967471
D33: BATAS BAWAH | E33: =E31-E32 -> -0.055342351 | F33: =F31-F32 -> 0.021398269 | G33: =G31-G32 -> 0.036019729 | H33: =H31-H32 -> 0.024352529
D34: BATAS ATAS | E34: =E31+E33 -> 0.70615765 | F34: =F31+F33 -> 0.086193269 | G34: =G31+G33 -> 0.13717973 | H34: =H31+H33 -> 0.14067253
D35: MAX SCORE | E35: =MAX(O5:O29) -> 4
D36: TOTAL REVENUE of INDUSTRY
B37: MULTIPLE
B38: NO. | C38: MULTIPLE | D38: PENGGUNAAN | I38: NILAI YANG DIHASILKAN | K38: FUNDAMENTAL | L38: MULTIPLE VALUE | O38: KETERANGAN
L39: CHEM | M39: CLPI | N39: CTBN
B40: 1 | C40: P/S | D40: Perusahaan yang mempunyai laba negatif, sangat umum untuk menilai perusahaan start up, dengan beban penjualan dan beban operasional cukup tinggi yang tidak dapat ditutup oleh penjualan | I40: Nilai Ekuitas | K40: ='INCOME STATEMENT'!E6 -> 16663916100 | L40: ='PASAR PEMBANDING'!D22/'PASAR PEMBANDING'!D5 -> 1.7049226 | M40: ='PASAR PEMBANDING'!E22/'PASAR PEMBANDING'!E5 -> 0.37422902 | N40: ='PASAR PEMBANDING'!F22/'PASAR PEMBANDING'!F5 -> 0.35850278
B41: 2 | C41: P/B | D41: Perusahaan yang mempunyai aset base stabil dan aset menjadi komponen yang sangat dominan dalam perusahaan tersebut, contohnya perusahaan yang bergerak dalam industri keuangan seperti bank, multifinance, asuransi, dan perusahaan properti/real estate | I41: Nilai Ekuitas | K41: ='BALANCE SHEET'!E48 -> 13816821754 | L41: ='PASAR PEMBANDING'!D22/'PASAR PEMBANDING'!D16 -> 1.8347108 | M41: ='PASAR PEMBANDING'!E22/'PASAR PEMBANDING'!E16 -> 0.54297062 | N41: ='PASAR PEMBANDING'!F22/'PASAR PEMBANDING'!F16 -> 0.72881455
B42: =+B41+1 -> 3 | C42: EV/EBIT | D42: Perusahaan yang masih dalam tahap pertumbuhan tetapi secara kinerja laba belum mencapai tahap stabil | I42: Nilai Enterprise (Debt + Equity) | K42: ='INCOME STATEMENT'!E22 -> 2261432441 | L42: =('PASAR PEMBANDING'!D15+'PASAR PEMBANDING'!D16)/'PASAR PEMBANDING'!D8 -> 131.17688 | M42: =('PASAR PEMBANDING'!E15+'PASAR PEMBANDING'!E16)/'PASAR PEMBANDING'!E8 -> 11.894599 | N42: =('PASAR PEMBANDING'!F15+'PASAR PEMBANDING'!F16)/'PASAR PEMBANDING'!F8 -> 8.0342958 | O42: Untuk menghasilkan Nilai Ekuitas, Nilai Enterprise harus dikurangkan dengan Hutang berbunga (pinjaman dari bank atau bukan, jangka panjang atau pendek, yang mengandung bunga)
B43: =+B42+1 -> 4 | C43: EV/EBITDA | D43: Perusahaan yang sedang berkebang namun kemungkinan masih mengalami kerugian secara keuangan karena laba operasional dari investasi perusahaan dengan pengeluaran barang modal yang tinggi belum dapat menutupi bunga pinjaman dan depresiasi, sehingga meski membukukan EBITDA positif, perusahan mungkin masih mencatat nilai rugi bersih | I43: Nilai Enterprise (Debt + Equity) | K43: ='INCOME STATEMENT'!E18 -> 3243162782 | L43: =('PASAR PEMBANDING'!D15+'PASAR PEMBANDING'!D16)/'PASAR PEMBANDING'!D7 -> 131.17688 | M43: =('PASAR PEMBANDING'!E15+'PASAR PEMBANDING'!E16)/'PASAR PEMBANDING'!E7 -> 13.207747 | N43: =('PASAR PEMBANDING'!F15+'PASAR PEMBANDING'!F16)/'PASAR PEMBANDING'!F7 -> 7.8217264
B44: =+B43+1 -> 5 | C44: EV/S | D44: Perusahaan yang baru berdiri (start up) yang mempunyai karakteristik biaya operasional masih lebih tinggi dari tingkat pendapatan, misalnya e commerce atau bisnis berbasis internet, dan sangat cocok untuk perusahaan yang menjadikan pangsa pasar sebagai hal yang kritikal, contohnya perusahaan retail barang konsumsi yang sangat mementingkan pangsa pasar untuk mempertahankan perusahaannya | I44: Nilai Enterprise (Debt + Equity) | K44: =K40 -> 16663916100 | L44: =('PASAR PEMBANDING'!D15+'PASAR PEMBANDING'!D16)/'PASAR PEMBANDING'!D5 -> 1.2399656 | M44: =('PASAR PEMBANDING'!E15+'PASAR PEMBANDING'!E16)/'PASAR PEMBANDING'!E5 -> 0.96303567 | N44: =('PASAR PEMBANDING'!F15+'PASAR PEMBANDING'!F16)/'PASAR PEMBANDING'!F5 -> 0.82187134

Sheet PASAR PEMBANDING
B2: PERHITUNGAN KESEBANDINGAN
B3: FS | C3: URAIAN | D3: (dalam IDR) | H3: RASIO | L3: SKOR KESEBANDINGAN
D4: ='PASAR KESEBANDINGAN'!L39 -> CHEM | E4: ='PASAR KESEBANDINGAN'!M39 -> CLPI | F4: ='PASAR KESEBANDINGAN'!N39 -> CTBN | G4: OBYEK PENILAIAN | H4: =D4 -> CHEM | I4: =E4 -> CLPI | J4: =F4 -> CTBN | K4: OBYEK PENILAIAN | L4: =H4 -> CHEM | M4: =I4 -> CLPI | N4: =J4 -> CTBN
B5: Income Statement | C5: Revenue | D5: 119655832334 | E5: 806306849977 | F5: 3.2036937e+12 | G5: ='INCOME STATEMENT'!E6 -> 16663916100
C6: COGS | D6: -82688848989 | E6: -698190914143 | F6: -2.5449892e+12 | G6: ='INCOME STATEMENT'!E7 -> -10779658214 | H6: =D6/D$5 -> -0.69105573 | I6: =E6/E$5 -> -0.86591217 | J6: =F6/F$5 -> -0.79439217 | K6: =G6/G$5 -> -0.64688625 | N6: 1
C7: EBITDA | D7: 1131061452 | E7: 58791423530 | F7: 3.3662952e+11 | G7: ='INCOME STATEMENT'!E18 -> 3243162782 | H7: =D7/D$5 -> 0.0094526228 | I7: =E7/E$5 -> 0.072914454 | J7: =F7/F$5 -> 0.10507544 | K7: =G7/G$5 -> 0.19462189 | N7: 1
C8: EBIT | D8: 1131061452 | E8: 65281918531 | F8: 3.2772306e+11 | G8: ='INCOME STATEMENT'!E22 -> 2261432441 | H8: =D8/D$5 -> 0.0094526228 | I8: =E8/E$5 -> 0.080964113 | J8: =F8/F$5 -> 0.10229538 | K8: =G8/G$5 -> 0.13570834 | N8: 1
B10: Balance Sheet | C10: Aset Lancar | D10: 116692606752 | E10: 657741165545 | F10: 1.9702056e+12 | G10: ='BALANCE SHEET'!E15 -> 1266935637 | H10: =D10/D$12 -> 0.78650203 | I10: =E10/E$12 -> 0.84705634 | J10: =F10/F$12 -> 0.74826722 | K10: =G10/G$12 -> 0.073325278 | N10: 1
C11: Aset Tidak Lancar | D11: 31676504147 | E11: 118761095703 | F11: 6.6281845e+11 | G11: ='BALANCE SHEET'!E24 -> 16011357394 | H11: =D11/D$12 -> 0.21349797 | I11: =E11/E$12 -> 0.15294366 | J11: =F11/F$12 -> 0.25173278 | K11: =G11/G$12 -> 0.92667472 | N11: 1
C12: Total Aset | D12: =+D10+D11 -> 148369110899 | E12: =+E10+E11 -> 776502261248 | F12: =+F10+F11 -> 2.633024e+12 | G12: =+G10+G11 -> 17278293031
C13: Liabilitas Jangka Pendek | D13: 31350314230 | E13: 207256474579 | F13: 9.4143229e+11 | G13: ='BALANCE SHEET'!E34 -> 3577237782 | H13: =D13/D$15 -> 0.84325407 | I13: =E13/E$15 -> 0.93876666 | J13: =F13/F$15 -> 0.89055328 | K13: =G13/G$15 -> 1
C14: Liabilitas Jangka Panjang | D14: 5827465784 | E14: 13518806847 | F14: 1.1569962e+11 | G14: ='BALANCE SHEET'!E39 -> 0 | H14: =D14/D$15 -> 0.15674593 | I14: =E14/E$15 -> 0.061233335 | J14: =F14/F$15 -> 0.10944672 | K14: =G14/G$15 -> 0 | M14: 1
C15: Total Liabilitas | D15: =+D13+D14 -> 37177780014 | E15: =+E13+E14 -> 220775281426 | F15: =+F13+F14 -> 1.0571319e+12 | G15: =+G13+G14 -> 3577237782
C16: Ekuitas | D16: 111191330885 | E16: 555726979822 | F16: 1.5758921e+12 | G16: ='BALANCE SHEET'!E48 -> 13816821754 | H16: =D16/D$12 -> 0.74942372 | I16: =E16/E$12 -> 0.7156798 | J16: =F16/F$12 -> 0.59851035 | K16: =G16/G$12 -> 0.79966359 | L16: 1
C17: Harga Pasar Saham (IDR) | D17: 120 | E17: 985 | F17: 1435 | H17: Total Skor | L17: =SUM(L6:L16) -> 1 | M17: =SUM(M6:M16) -> 1 | N17: =SUM(N6:N16) -> 5
C18: Laba per Lembar Saham | D18: 0.36 | E18: 172 | F18: 0.023 | G18: 353277
C19: Jumlah Lembar | D19: 1700032794 | E19: 306338500 | F19: 800371500 | H19: Bobot Pembanding | L19: =L17/SUM($L$17:$N$17) -> 0.14285714 | M19: =M17/SUM($L$17:$N$17) -> 0.14285714 | N19: =N17/SUM($L$17:$N$17) -> 0.71428571
C20: Market Cap (IDR) | D20: =+D17*D19 -> 204003935280 | E20: =+E17*E19 -> 301743422500 | F20: =+F17*F19 -> 1148533102500
C21: Kurs | D21: 1 | E21: =D21 -> 1 | F21: 1
C22: Market Cap (idr) | D22: =D20/D21 -> 204003935280 | E22: =E20/E21 -> 301743422500 | F22: =F20/F21 -> 1148533102500
B25: PERHITUNGAN NILAI
B26: NO | C26: MULTIPLE | D26: MULTIPLE VALUE | G26: FUNDAMENTAL | I26: WEIGHTED | J26: VALUE
C27: Skor Kesebandingan | D27: =L19 -> 0.14285714 | E27: =M19 -> 0.14285714 | F27: =N19 -> 0.71428571
B28: 1 | C28: P/S | D28: =IFERROR(VLOOKUP(C28,MULTIPLES,10,FALSE),"") -> 1.7049226 | E28: =IFERROR(VLOOKUP(C28,MULTIPLES,11,FALSE),"") -> 0.37422902 | F28: =IFERROR(VLOOKUP(C28,MULTIPLES,12,FALSE),"") -> 0.35850278 | G28: =IFERROR(VLOOKUP(C28,MULTIPLES,9,FALSE),0) -> 16663916100 | H28: =($D$27*D28*G28)+($E$27*E28*G28)+($F$27*F28*G28) -> 9.21673e+09 | I28: 1 | J28: =H28*I28 -> 9.21673e+09
B29: =IF(C29="","",2) | D29: =IFERROR(VLOOKUP(C29,MULTIPLES,10,FALSE),"") | E29: =IFERROR(VLOOKUP(C29,MULTIPLES,11,FALSE),"") | F29: =IFERROR(VLOOKUP(C29,MULTIPLES,12,FALSE),"") | G29: =IFERROR(VLOOKUP(C29,MULTIPLES,9,FALSE),"") | H29: =IFERROR(($D$27*D29*G29)+($E$27*E29*G29)+($F$27*F29*G29),"") | I29: =1-I28 -> 0 | J29: =IFERROR(H29*I29,0) -> 0
G30: =IF(LEFT(C28,1)="p","INDICATED VALUE OF EQUITY","ENTERPRISE VALUE") -> INDICATED VALUE OF EQUITY | J30: =+J28+J29 -> 9.21673e+09
G31: =IF(G30="ENTERPRISE VALUE","DEBT",0) -> 0 | J31: =IF(G31="DEBT",('BALANCE SHEET'!E30+'BALANCE SHEET'!E37)*-1,0) -> 0
G32: =IF(G31="DEBT","INDICATED VALUE OF EQUITY",0) -> 0 | J32: =IF(G31="DEBT",J30+J31,0) -> 0
G33: PFC | I33: 0.7 | J33: =IF(G31="DEBT",J32*I33,J30*I33) -> 6.451711e+09
G34: CONTROLING INDICATED VALUE OF EQUITY | J34: =+J30+J33 -> 1.5668441e+10
G35: DLOM | I35: =EEM!C35 -> 0 | J35: =J34*I35 -> 0
G36: MARKET VALUE OF EQUITY | J36: =+J34+J35 -> 1.5668441e+10
G37: SHARES | I37: =EEM!C39 -> 0.3030303 | J37: 135000
G38: ="MARKET VALUE OF "&TEXT(I37,"0,0%")&" EQUITY" -> MARKET VALUE OF 30% EQUITY | J38: =J36*I37 -> 4.7480124e+09
G39: Rounded | J39: =ROUNDUP(J38,-3) -> 4748013000
G41: Jumlah Lembar | J41: =DCF!C41 -> 5280000000
J42: =J38/J41 -> 0.89924478

Sheet GROWTH RATE
A1: =HOME!B4 -> Makmur Jaya Sejati Raya
A2: Growth Rate
B4: =ROIC!C5 -> 2020 | C4: =ROIC!D5 -> 2021
A6: Net Fixed Assets at the End of Year | B6: ='FIXED ASSET'!D69 -> 16993087735 | C6: ='FIXED ASSET'!E69 -> 16011357394
A7: Add: Net Current Asset at the End of Year | B7: ='BALANCE SHEET'!D15 -> 1417287289 | C7: ='BALANCE SHEET'!E15 -> 1266935637
A8: Less: Net Fixed Assets at the Beginning of Year | B8: ='BALANCE SHEET'!C21*-1 -> -17964211763 | C8: ='BALANCE SHEET'!D21*-1 -> -16993087735
A9: Less: Net Current Assets at the Beginning of Year | B9: ='BALANCE SHEET'!C15*-1 -> -706318865 | C9: ='BALANCE SHEET'!D15*-1 -> -1417287289
A10: Total Net Investment | B10: =SUM(B6:B9) -> -260155604 | C10: =SUM(C6:C9) -> -1132081993
A12: Total Invested Capital Beginning of Year | B12: =ROIC!B12 -> 18251502791 | C12: =ROIC!C12 -> 17686466055
A14: Growth Rate = Net Investment/Invested Capital | B14: =B10/B12 -> -0.014253928 | C14: =C10/C12 -> -0.064008377
A15: Average | B15: =AVERAGE(B14:C14) -> -0.039131153

Sheet DCF
A1: =HOME!B4 -> Makmur Jaya Sejati Raya
A2: Discounted Cash Flow
A3: ='BALANCE SHEET'!A3 -> (IDR)
A4: FCFF Model
C5: ='BALANCE SHEET'!E4 -> 2021 | D5: =C5+1 -> 2022 | E5: =D5+1 -> 2023 | F5: =E5+1 -> 2024 | G5: =F5+1 -> 2025 | H5: =G5+1 -> 2026
C6: =HOME!B20 -> 44561 | D6: =HOME!B21 -> 44926
A7: NOPLAT | C7: =STAT_DCF!B15 -> 1.249783e+09 | D7: =STAT_DCF!C15 -> 1.534205e+09 | E7: =STAT_DCF!D15 -> 1.883355e+09 | F7: =STAT_DCF!E15 -> 2.3119635e+09 | G7: =STAT_DCF!F15 -> 2.8381136e+09 | H7: =STAT_DCF!G15 -> 3.4840034e+09
A8: Add: Depreciation | C8: =STAT_DCF!B26 -> 1.0833458e+09 | D8: =STAT_DCF!C26 -> 1.3298905e+09 | E8: =STAT_DCF!D26 -> 1.6325432e+09 | F8: =STAT_DCF!E26 -> 2.0040727e+09 | G8: =STAT_DCF!F26 -> 2.4601538e+09 | H8: =STAT_DCF!G26 -> 3.0200286e+09
A9: Gross Cash Flow | C9: =C7+C8 -> 2.3331287e+09 | D9: =D7+D8 -> 2.8640955e+09 | E9: =E7+E8 -> 3.5158982e+09 | F9: =F7+F8 -> 4.3160362e+09 | G9: =G7+G8 -> 5.2982674e+09 | H9: =H7+H8 -> 6.504032e+09
A11: Changes in Working Capital
A12: Less: Change in Operating NWC | C12: =0 -> 0 | D12: =-STAT_DCF!C25 -> -3.2018623e+08 | E12: =-STAT_DCF!D25 -> 5.4333546e+08 | F12: =-STAT_DCF!E25 -> 6.6698619e+08 | G12: =-STAT_DCF!F25 -> 8.18777e+08 | H12: =-STAT_DCF!G25 -> 1.0051119e+09
A13: Operating WC detail included in row 12 | C13: =0 -> 0 | D13: =0 -> 0 | E13: =0 -> 0 | F13: =0 -> 0 | G13: =0 -> 0 | H13: =0 -> 0
A14: Total Net Changes in Working Capital | C14: =SUM(C12:C13) -> 0 | D14: =SUM(D12:D13) -> -3.2018623e+08 | E14: =SUM(E12:E13) -> 5.4333546e+08 | F14: =SUM(F12:F13) -> 6.6698619e+08 | G14: =SUM(G12:G13) -> 8.18777e+08 | H14: =SUM(H12:H13) -> 1.0051119e+09
A16: Less: Capital Expenditures | C16: =-STAT_DCF!B27 -> -1.0833458e+09 | D16: =-STAT_DCF!C27 -> -1.3298905e+09 | E16: =-STAT_DCF!D27 -> -1.6325432e+09 | F16: =-STAT_DCF!E27 -> -2.0040727e+09 | G16: =-STAT_DCF!F27 -> -2.4601538e+09 | H16: =-STAT_DCF!G27 -> -3.0200286e+09
A18: Gross Investment | C18: =C14+C16 -> -1.0833458e+09 | D18: =D14+D16 -> -1.6500767e+09 | E18: =E14+E16 -> -1.0892077e+09 | F18: =F14+F16 -> -1.3370865e+09 | G18: =G14+G16 -> -1.6413768e+09 | H18: =H14+H16 -> -2.0149167e+09
A20: Free Cash Flow | C20: =C9+C18 -> 1.249783e+09 | D20: =D9+D18 -> 1.2140188e+09 | E20: =E9+E18 -> 2.4266904e+09 | F20: =F9+F18 -> 2.9789497e+09 | G20: =G9+G18 -> 3.6568906e+09 | H20: =H9+H18 -> 4.4891153e+09
A22: Period (n year) | D22: 1 | E22: 2 | F22: 3 | G22: 4 | H22: 5
A23: Discount Factor | B23: =STAT_ASSUMPTIONS!B6 -> 0.11463062 | D23: =1/((1+$B$23)^D22) -> 0.8971582 | E23: =1/((1+$B$23)^E22) -> 0.80489283 | F23: =1/((1+$B$23)^F22) -> 0.72211621 | G23: =1/((1+$B$23)^G22) -> 0.64785247 | H23: =1/((1+$B$23)^H22) -> 0.58122616
A24: PV of Free Cash Flow | D24: =D20*D23 -> 1.0891669e+09 | E24: =E20*E23 -> 1.9532257e+09 | F24: =F20*F23 -> 2.1511479e+09 | G24: =G20*G23 -> 2.3691256e+09 | H24: =H20*H23 -> 2.6091912e+09
A25: Total PV FCF Explicit Period | C25: =SUM(D24:H24) -> 1.0171857e+10
A26: Growth Rate (SPI 3305.31. c) | B26: =STAT_ASSUMPTIONS!B8 -> 0
A27: Terminal Value | C27: =H20*((1+B26)/(B23-B26)) -> 3.9161572e+10
A28: PV of Terminal Value | C28: =C27*H23 -> 2.276173e+10
A29: Enterprise Value | C29: =C25+C28 -> 3.2933587e+10
A30: Interest Bearing Debt | C30: =-STAT_DCF!B38 -> 0 | D30: Bank Loan Short Term + Bank Loan Long Term
A31: Surplus Asset Cash | C31: =STAT_DCF!B37 -> 1075880526
A32: Iddle Non Operating Asset (Building) | C32: =0 -> 0
A33: Equity Value (100%) | C33: =SUM(C29:C32) -> 3.4009468e+10
A34: DLOM | B34: =0 -> 0 | C34: =C33*B34 -> 0
A35: Equity Value (100%) Less DLOM | C35: =C33+C34 -> 3.4009468e+10
A36: =HOME!A26 -> DISCOUNT LACK OF CONTROL/PREMIUM FOR CONTROL | B36: =0 -> 0 | C36: =C35*B36 -> 0
A37: Market Value of Equity (100%) | C37: =C35+C36 -> 3.4009468e+10
A38: Percentage of Shares | B38: =1 -> 1
A39: Market Value of 100% Equity | C39: =C37*B38 -> 3.4009468e+10
A40: Rounded | C40: =ROUNDUP(C39,-3) -> 34009468000
A41: Jumlah Lembar | C41: =HOME!B15 -> 5280000000
C42: =C39/C41 -> 6.4411871

Sheet PERBANDINGAN
B2: Hasil Perhitungan Nilai Pasar Masing-Masing Pendekatan
B3: NO. | C3: PENDEKATAN | D3: NILAI (IDR)
B4: 1 | C4: Pendekatan Pendapatan (Discounted Cash Flow Method) | D4: =DCF!C39 -> 3.4009468e+10
B5: 2 | C5: Pendekatan Pasar (Guideline Publicly Traded Company Method) | D5: ='PASAR PEMBANDING'!J38 -> 4.7480124e+09
B6: 3 | C6: Pendekatan Aset (Excess Earning Method) | D6: =EEM!D42 -> 6.0261934e+09
B8: Perbandingan Nilai Pasar
B9: No | C9: Perbandingan Pendekatan | D9: %
B10: 1 | C10: Pendekatan Pendapatan (Discounted Cash Flow Method) : Pendekatan Pasar (Guideline Publicly Traded Company Method) | D10: =D4/D5 -> 7.1628852
B11: 2 | C11: Pendekatan Pendapatan (Discounted Cash Flow Method) : Pendekatan Aset (Excess Earning Method) | D11: =D4/D6 -> 5.6436071
B12: 3 | C12: Pendekatan Aset (Excess Earning Method) : Pendekatan Pasar (Guideline Publicly Traded Company Method) | D12: =D6/D5 -> 1.2692034

Sheet DIVIDEND DISCOUNT MODEL
A1: STOCK VALUATION DIVIDEND DISCOUNT MODEL
A2: nice to know aja
A3: Single Growth
A4: Dividend Per Share | B4: 333333 | C4: IDR | D4: *Financial Statement CALK 19
A5: Exchange Rate | B5: =EEM!D41 -> 1 | C5: IDR/USD
A6: Cost of Equity | B6: ='DISCOUNT RATE'!H4 -> 0.06864
A7: Growth | B7: 0
A8: Market Value of Share | B8: =(1+B6)/(B6-B7)*B4*B5 -> 5189583 | C8: IDR
A9: Jumlah Lembar | B9: =EEM!D44 -> 5280000000
A10: Indikasi Nilai Saham | B10: =B8*B9 -> 2.7400998e+16
A11: DLOM | B11: =EEM!C35 -> 0
A12: Nilai Pasar Saham | B12: =B10*(1+B11) -> 2.7400998e+16
A13: Per Lembar | B13: =B12/B9 -> 5189583

Sheet HARGA PASAR SAHAM
A1: PT CITRA TUBINDO TBK
A3: 6.5e-05 | B3: =1/A3 -> 15384.615
A5: Penjualan | B5: 208240090 | C5: =B5*$B$3 -> 3.2036937e+12
A6: COGS | B6: -165424296 | C6: =B6*$B$3 -> -2.5449892e+12
A7: EBITDA | B7: 21880919 | C7: =B7*$B$3 -> 3.3662952e+11
A8: EBIT | B8: 21301999 | C8: =B8*$B$3 -> 3.2772306e+11
A10: Aset Lancar | B10: 128063363 | C10: =+B10*$B$3 -> 1.9702056e+12
A11: Aset Tidak Lancar | B11: 43083199 | C11: =+B11*$B$3 -> 6.6281845e+11
A12: Total Aset | B12: =+B10+B11 -> 171146562 | C12: =+B12*$B$3 -> 2.633024e+12
A13: Liabilitas Jk Pendek | B13: 61193099 | C13: =+B13*$B$3 -> 9.4143229e+11
A14: Liabilitas Jk Panjang | B14: 7520475 | C14: =+B14*$B$3 -> 1.1569962e+11
A15: Total Liabilitas | B15: =+B13+B14 -> 68713574 | C15: =+B15*$B$3 -> 1.0571319e+12
A16: Ekuitas | B16: 102432988 | C16: =+B16*$B$3 -> 1.5758921e+12
A17: Harga Pasar Saham (IDR)*)
A18: Jumlah Lembar | B18: 800371500

Sheet SIMULASI POTENSI PAJAK
A1: Equity Value | C1: AAM | E1: =IF(C1="AAM", AAM!E53, IF(C1="EEM", EEM!D34, IF(C1="DCF", DCF!C33, ""))) -> 13701055249
A3: DLOM | C3: =DLOM!D36&" "&DLOM!F36 -> Potensi Resistensi Wajib Pajak Tinggi | D3: =DLOM!F34*-1 -> -0.25 | E3: =+E1*D3 -> -3.4252638e+09
A4: Equity Value (100%) Less DLOM | E4: =+E1+E3 -> 1.0275791e+10
A6: ='DLOC(PFC)'!C26 -> DLOC Objek Penilaian | C6: ='DLOC(PFC)'!C28&" "&'DLOC(PFC)'!E28 -> Potensi Resistensi Wajib Pajak Tinggi | D6: ='DLOC(PFC)'!E26*-1 -> -0.34 | E6: =+E4*D6 -> -3.4937691e+09
A7: =IF(A6="DLOC Objek Penilaian","Equity Value (100%) Less DLOC","Equity Value (100%) Add PFC") -> Equity Value (100%) Less DLOC | E7: =+E4+E6 -> 6.7820223e+09
A9: Resistensi Wajib Pajak Keseluruhan | C9: =IF(AND(C3="Potensi Resistensi Wajib Pajak Tinggi", C6="Potensi Resistensi Wajib Pajak Tinggi"), "Potensi Resistensi Wajib Pajak Tinggi", IF(AND(C3="Potensi Resistensi Wajib Pajak Tinggi", C6="Potensi Resistensi Wajib Pajak Moderat"), "Potensi Resistensi Wajib Pajak Tinggi", IF(AND(C3="Potensi Resistensi Wajib Pajak Tinggi", C6="Potensi Resistensi Wajib Pajak Rendah"), "Potensi Resistensi Wajib Pajak Moderat", IF(AND(C3="Potensi Resistensi Wajib Pajak Moderat", C6="Potensi Resistensi Wajib Pajak Tinggi"), "Potensi Resistensi Wajib Pajak Tinggi", IF(AND(C3="Potensi Resistensi Wajib Pajak Moderat", C6="Potensi Resistensi Wajib Pajak Moderat"), "Potensi Resistensi Wajib Pajak Moderat", IF(AND(C3="Potensi Resistensi Wajib Pajak Moderat", C6="Potensi Resistensi Wajib Pajak Rendah"), "Potensi Resistensi Wajib Pajak Moderat", IF(AND(C3="Potensi Resistensi Wajib Pajak Rendah", C6="Potensi Resistensi Wajib Pajak Tinggi"), "Potensi Resistensi Wajib Pajak Moderat", IF(AND(C3="Potensi Resistensi Wajib Pajak Rendah", C6="Potensi Resistensi Wajib Pajak Moderat"), "Potensi Resistensi Wajib Pajak Moderat", IF(AND(C3="Potensi Resistensi Wajib Pajak Rendah", C6="Potensi Resistensi Wajib Pajak Rendah"), "Potensi Resistensi Wajib Pajak Rendah", ""))))))))) -> Potensi Resistensi Wajib Pajak Tinggi
A11: Market Value of Equity (100%) | E11: =E7 -> 6.7820223e+09
A12: Percentage of Shares | E12: =HOME!B17 -> 0.3030303
A13: =AAM!A59 -> Market Value of 100% Equity | E13: =+E11*E12 -> 2.0551583e+09
A14: Nilai Pengalihan Saham yang Dilaporkan | E14: =HOME!B16 -> 1600000000
A15: Potensi Pengalihan Saham yang Belum Dikenakan Pajak | E15: =E13-E14 -> 4.5515829e+08
A17: Jenis Subjek Pajak | E17: =HOME!B11 -> Orang Pribadi
A18: Tahun Pengalihan | E18: =YEAR(HOME!B20) -> 2021
A19: ="Simulasi Potensi Pajak Penghasilan Kurang Bayar"&" "&E17 -> Simulasi Potensi Pajak Penghasilan Kurang Bayar Orang Pribadi

Sheet STAT_SUMMARY
A1: Commercial Statutory 22% Valuation Summary
A3: Basis | B3: Commercial earnings, statutory 22% normalized NOPLAT, no fiscal correction, no DLOM/DLOC
A4: Valuation Date | B4: =STAT_ASSUMPTIONS!B3 -> 44561
A6: Method | B6: Overwritten Source Model | C6: Rebuilt Indication | D6: Change | E6: Use Status | F6: Notes
A7: AAM | B7: =AAM!E53 -> 13701055249 | C7: =STAT_AAM!D18 -> 13701055249 | D7: =C7-B7 -> 0 | E7: Preliminary indication | F7: Book NAV proxy pending independent FMV asset appraisal
A8: EEM | B8: =EEM!D34 -> 1.9886438e+10 | C8: =STAT_EEM!B22 -> 1.9886438e+10 | D8: =C8-B8 -> 0 | E8: Normalized indication | F8: Uses commercial EBIT x 78%, maintenance capex = depreciation, no 2021 WC release
A9: DCF | B9: =DCF!C33 -> 3.4009468e+10 | C9: =STAT_DCF!B39 -> 3.4009468e+10 | D9: =C9-B9 -> 0 | E9: Base indication | F9: 5-year FCFF, source WACC, base terminal growth 0%, operating WC days
A12: Key model corrections
A13: Fiscal NPAT and fiscal corrections excluded from earning power.
A14: Tax payable excluded from operating WC in EEM/DCF; retained as liability in AAM.
A15: Capex normalized to depreciation; 2021 one-off WC release not capitalized in EEM.
A16: DLOM/DLOC/minority discounts not applied.
A18: Selected sensitivities
A19: DCF source WACC, g = PDF/workbook reinvestment growth | B19: =STAT_SENS!B5 -> 2.4918779e+10
A20: DCF source WACC, g = 0% | B20: =STAT_SENS!B6 -> 3.4009468e+10
A21: DCF source WACC, g = 3% | B21: =STAT_SENS!B7 -> 4.3002993e+10
A22: DCF corrected WACC, g = 0% | B22: =STAT_SENS!C6 -> 2.5377744e+10
A23: DCF no incremental WC release, source WACC, g = 0% | B23: =STAT_SENS!B13 -> 2.7166767e+10

Sheet STAT_ASSUMPTIONS
A1: Commercial Statutory 22% Valuation Assumptions
A2: Assumption | B2: Value | C2: Status | D2: Source / Notes
A3: Valuation date | B3: =HOME!B20 -> 44561 | C3: Locked | D3: Tanggal penilaian 31 Desember 2021.
A4: Earning power basis | B4: Commercial profit | C4: Locked | D4: Fiscal correction is reconciliation only.
A5: Statutory corporate tax rate | B5: 0.22 | C5: Confirmed by user | D5: Used for normalized forward-looking NOPLAT.
A6: Source WACC | B6: ='DISCOUNT RATE'!H10 -> 0.11463062 | C6: Workbook-derived | D6: Used as base discount rate; see sensitivity.
A7: Corrected WACC sensitivity | B7: ='DISCOUNT RATE'!F7*'DISCOUNT RATE'!H4+'DISCOUNT RATE'!F8*('DISCOUNT RATE'!C3+'DISCOUNT RATE'!H2*'DISCOUNT RATE'!C5+'DISCOUNT RATE'!C6) -> 0.14869348 | C7: Sensitivity | D7: Adds country/default spread rather than subtracting it in CAPM sensitivity.
A8: Base terminal growth | B8: 0 | C8: Confirmed by user | D8: Base case locked at 0%; sensitivities at workbook -6.20% and 3.00% retained.
A9: Revenue growth | B9: ='INCOME STATEMENT'!J6 -> 0.22757714 | C9: Workbook-derived | D9: Workbook historical average; lower than actual 2020-2021 average.
A10: Return on net tangible assets | B10: ='BORROWING CAP'!F14 -> 0.085138914 | C10: Workbook-derived | D10: Used as required return for EEM.
A11: Explicit DCF forecast years | B11: 5 | C11: Model input | D11: 2022E-2026E.
A12: Maintenance capex | B12: Equals depreciation | C12: Model convention | D12: Avoids zero-capex overstatement.
A13: Operating WC policy | B13: Historical AR/AP/other-payable days | C13: Formula-derived | D13: Tax payable and debt are excluded from operating WC.
A14: Non-operating assets | B14: =SUM('BALANCE SHEET'!E8:E9)+'BALANCE SHEET'!E11 -> 1075880526 | C14: Review | D14: Cash, bank/deposit, and employee receivable treated as non-operating absent minimum cash data.
A15: DLOM/DLOC/minority discount | B15: 0 | C15: Locked | D15: No DLOM, DLOC, or minority discount applied.
A16: Fiscal correction | B16: Do not use | C16: Locked | D16: Fiscal correction and fiscal NPAT are not earning-power inputs.

Sheet STAT_HIST
A1: Historical Commercial Drivers
A2: Driver | B2: 2019A | C2: 2020A | D2: 2021A | E2: Normalized / Avg | F2: Treatment
A3: Revenue | B3: ='INCOME STATEMENT'!C6 -> 9335637236 | C3: ='INCOME STATEMENT'!D6 -> 11406787320 | D3: ='INCOME STATEMENT'!E6 -> 16663916100 | E3: =D3 -> 16663916100 | F3: Commercial source
A4: Revenue growth | C4: =C3/B3-1 -> 0.22185417 | D4: =D3/C3-1 -> 0.46087725 | E4: =AVERAGE(C4:D4) -> 0.34136571 | F4: Actual 2020-2021 average shown
A5: Workbook revenue growth | E5: ='INCOME STATEMENT'!J6 -> 0.22757714 | F5: Used for DCF base
A6: COGS % revenue | B6: =-'INCOME STATEMENT'!C7/'INCOME STATEMENT'!C6 -> 0.73702608 | C6: =-'INCOME STATEMENT'!D7/'INCOME STATEMENT'!D6 -> 0.66326764 | D6: =-'INCOME STATEMENT'!E7/'INCOME STATEMENT'!E6 -> 0.64688625 | E6: =AVERAGE(B6:D6) -> 0.68239332 | F6: Used
A7: G&A % revenue | B7: =-'INCOME STATEMENT'!C13/'INCOME STATEMENT'!C6 -> 0.15216784 | C7: =-'INCOME STATEMENT'!D13/'INCOME STATEMENT'!D6 -> 0.15866684 | D7: =-'INCOME STATEMENT'!E13/'INCOME STATEMENT'!E6 -> 0.15849186 | E7: =AVERAGE(B7:D7) -> 0.15644218 | F7: Used
A8: Depreciation % revenue | B8: =-'INCOME STATEMENT'!C21/'INCOME STATEMENT'!C6 -> 0.037863679 | C8: =-'INCOME STATEMENT'!D21/'INCOME STATEMENT'!D6 -> 0.098257204 | D8: =-'INCOME STATEMENT'!E21/'INCOME STATEMENT'!E6 -> 0.058913543 | E8: =AVERAGE(B8:D8) -> 0.065011476 | F8: Used
A9: EBIT margin | B9: ='INCOME STATEMENT'!C22/'INCOME STATEMENT'!C6 -> 0.0729424 | C9: ='INCOME STATEMENT'!D22/'INCOME STATEMENT'!D6 -> 0.079808315 | D9: ='INCOME STATEMENT'!E22/'INCOME STATEMENT'!E6 -> 0.13570834 | E9: =AVERAGE(B9:D9) -> 0.096153019 | F9: Used
A10: Commercial NPAT | B10: ='INCOME STATEMENT'!C35 -> 440745074 | C10: ='INCOME STATEMENT'!D35 -> 754862153 | D10: ='INCOME STATEMENT'!E35 -> 1838106527 | F10: Commercial source
A11: Statutory NOPLAT | B11: ='INCOME STATEMENT'!C22*(1-STAT_ASSUMPTIONS!$B$5) -> 5.3115176e+08 | C11: ='INCOME STATEMENT'!D22*(1-STAT_ASSUMPTIONS!$B$5) -> 7.1007805e+08 | D11: ='INCOME STATEMENT'!E22*(1-STAT_ASSUMPTIONS!$B$5) -> 1.7639173e+09 | F11: Commercial EBIT x (1-tax)
A12: AR days | B12: ='BALANCE SHEET'!C10/'INCOME STATEMENT'!C6*365 -> 9.7192857 | C12: ='BALANCE SHEET'!D10/'INCOME STATEMENT'!D6*365 -> 21.611088 | D12: ='BALANCE SHEET'!E10/'INCOME STATEMENT'!E6*365 -> 4.1847976 | E12: =AVERAGE(B12:D12) -> 11.83839 | F12: Used
A13: Inventory days | B13: =IFERROR('BALANCE SHEET'!C12/-'INCOME STATEMENT'!C7*365,0) -> 0 | C13: =IFERROR('BALANCE SHEET'!D12/-'INCOME STATEMENT'!D7*365,0) -> 0 | D13: =IFERROR('BALANCE SHEET'!E12/-'INCOME STATEMENT'!E7*365,0) -> 0 | E13: =AVERAGE(B13:D13) -> 0 | F13: Used
A14: AP days | B14: ='BALANCE SHEET'!C31/-'INCOME STATEMENT'!C7*365 -> 71.566137 | C14: ='BALANCE SHEET'!D31/-'INCOME STATEMENT'!D7*365 -> 34.860263 | D14: ='BALANCE SHEET'!E31/-'INCOME STATEMENT'!E7*365 -> 61.739256 | E14: =AVERAGE(B14:D14) -> 56.055219 | F14: Used
A15: Other payable days | B15: ='BALANCE SHEET'!C33/-'INCOME STATEMENT'!C13*365 -> 102.19392 | C15: ='BALANCE SHEET'!D33/-'INCOME STATEMENT'!D13*365 -> 59.588305 | D15: ='BALANCE SHEET'!E33/-'INCOME STATEMENT'!E13*365 -> 148.61432 | E15: =AVERAGE(B15:D15) -> 103.46552 | F15: Used
A16: Tax payable | B16: ='BALANCE SHEET'!C32 -> 99403988 | C16: ='BALANCE SHEET'!D32 -> 250347400 | D16: ='BALANCE SHEET'!E32 -> 678518254 | F16: Excluded from operating WC
A17: Operating NWC excl cash/tax/debt | B17: ='BALANCE SHEET'!C10+'BALANCE SHEET'!C12-'BALANCE SHEET'!C31-'BALANCE SHEET'!C33 -> -1498240675 | C17: ='BALANCE SHEET'!D10+'BALANCE SHEET'!D12-'BALANCE SHEET'!D31-'BALANCE SHEET'!D33 -> -342681280 | D17: ='BALANCE SHEET'!E10+'BALANCE SHEET'!E12-'BALANCE SHEET'!E31-'BALANCE SHEET'!E33 -> -2707664417 | F17: Used

Sheet STAT_AAM
A1: AAM - Commercial Source Book NAV Proxy
A2: Item | B2: Book / Source | C2: FMV Adjustment | D2: FMV / Adjusted | E2: Treatment
A3: Cash on hand | B3: ='BALANCE SHEET'!E8 -> 717848795 | C3: 0 | D3: =B3+C3 -> 717848795 | E3: Included in AAM assets
A4: Cash on bank / deposit | B4: ='BALANCE SHEET'!E9 -> 337031731 | C4: 0 | D4: =B4+C4 -> 337031731 | E4: Included in AAM assets
A5: Account receivable | B5: ='BALANCE SHEET'!E10 -> 191055111 | C5: 0 | D5: =B5+C5 -> 191055111 | E5: Included in AAM assets
A6: Other receivable | B6: ='BALANCE SHEET'!E11 -> 21000000 | C6: 0 | D6: =B6+C6 -> 21000000 | E6: Included in AAM assets
A7: Inventory | B7: ='BALANCE SHEET'!E12 -> 0 | C7: 0 | D7: =B7+C7 -> 0 | E7: Included in AAM assets
A8: Other current assets | B8: ='BALANCE SHEET'!E13 -> 0 | C8: 0 | D8: =B8+C8 -> 0 | E8: Included in AAM assets
A9: Fixed assets net | B9: ='BALANCE SHEET'!E21 -> 16011357394 | C9: 0 | D9: =B9+C9 -> 16011357394 | E9: No independent FMV appraisal supplied
A10: Other non-current / intangible assets | B10: ='BALANCE SHEET'!E22+'BALANCE SHEET'!E23 -> 0 | C10: 0 | D10: =B10+C10 -> 0 | E10: Included if any
A11: Adjusted total assets | B11: =SUM(B3:B10) -> 17278293031 | C11: =SUM(C3:C10) -> 0 | D11: =SUM(D3:D10) -> 17278293031 | E11: Asset side only; not fiscal PDF replacement
A12: Bank loan short-term | B12: ='BALANCE SHEET'!E30 -> 0 | C12: 0 | D12: =B12+C12 -> 0 | E12: Liability
A13: Account payable | B13: ='BALANCE SHEET'!E31 -> 1823364600 | C13: 0 | D13: =B13+C13 -> 1823364600 | E13: Liability
A14: Tax payable | B14: ='BALANCE SHEET'!E32 -> 678518254 | C14: 0 | D14: =B14+C14 -> 678518254 | E14: AAM liability; not earning-power input
A15: Other payable | B15: ='BALANCE SHEET'!E33 -> 1075354928 | C15: 0 | D15: =B15+C15 -> 1075354928 | E15: Liability
A16: Bank loan long-term | B16: ='BALANCE SHEET'!E37 -> 0 | C16: 0 | D16: =B16+C16 -> 0 | E16: Liability
A17: Related party / employee benefit liabilities | B17: ='BALANCE SHEET'!E38 -> 0 | C17: 0 | D17: =B17+C17 -> 0 | E17: Liability
A18: Equity Value 100% - AAM | B18: =B11-SUM(B12:B17) -> 13701055249 | C18: =C11-SUM(C12:C17) -> 0 | D18: =D11-SUM(D12:D17) -> 13701055249 | E18: No DLOM/DLOC

Sheet STAT_EEM
A1: EEM - Commercial Normalized Excess Earnings
A2: Line Item | B2: Amount / Rate | C2: Formula / Treatment | D2: Notes
A3: Fixed assets net | B3: ='BALANCE SHEET'!E21 -> 16011357394 | C3: Source | D3: Operating tangible assets
A4: Operating current assets | B4: ='BALANCE SHEET'!E10+'BALANCE SHEET'!E12 -> 191055111 | C4: AR + inventory | D4: Cash, deposit, employee receivable excluded
A5: Operating current liabilities | B5: ='BALANCE SHEET'!E31+'BALANCE SHEET'!E33 -> 2898719528 | C5: AP + other payable | D5: Tax payable and debt excluded from operating WC
A6: Net operating working capital | B6: =B4-B5 -> -2707664417 | C6: Operating CA - operating CL | D6: May be negative due supplier/other payable financing
A7: Net operating tangible assets | B7: =B3+B6 -> 13303692977 | C7: Fixed assets net + operating NWC | D7: EEM tangible asset base
A8: Cash on hand | B8: ='BALANCE SHEET'!E8 -> 717848795 | C8: Non-operating asset | D8: Review if minimum operating cash should be retained
A9: Cash on bank / deposit | B9: ='BALANCE SHEET'!E9 -> 337031731 | C9: Non-operating asset | D9: Review if minimum operating cash should be retained
A10: Employee receivable | B10: ='BALANCE SHEET'!E11 -> 21000000 | C10: Non-operating asset | D10: Non-trade receivable
A11: Total non-operating assets | B11: =SUM(B8:B10) -> 1075880526 | C11: Added after EV | D11: No debt in source balance sheet
A12: Commercial EBIT 2021 | B12: ='INCOME STATEMENT'!E22 -> 2261432441 | C12: Commercial source | D12: No fiscal correction
A13: Statutory tax rate | B13: =STAT_ASSUMPTIONS!B5 -> 0.22 | C13: Confirmed input | D13: 22%
A14: Normalized NOPLAT | B14: =B12*(1-B13) -> 1.7639173e+09 | C14: EBIT x (1-tax) | D14: Forward-looking normalized basis
A15: Return on NTA rate | B15: =STAT_ASSUMPTIONS!B10 -> 0.085138914 | C15: Workbook-derived | D15: Borrowing capacity sheet
A16: Required return on NTA | B16: =B7*B15 -> 1.132662e+09 | C16: NTA x return rate | D16: Charge for tangible assets
A17: Excess earnings | B17: =B14-B16 -> 6.3125533e+08 | C17: NOPLAT - required return | D17: Capitalized below
A18: Capitalization rate | B18: =STAT_ASSUMPTIONS!B6-STAT_ASSUMPTIONS!B8 -> 0.11463062 | C18: WACC - terminal growth | D18: Base g = 0%
A19: Capitalized excess earnings | B19: =B17/B18 -> 5.5068648e+09 | C19: Excess / cap rate | D19: Positive cap rate check in STAT_CHECKS
A20: Enterprise value | B20: =B7+B19 -> 1.8810558e+10 | C20: NTA + capitalized excess | D20: Before non-operating assets/debt
A21: Interest-bearing debt | B21: ='BALANCE SHEET'!E30+'BALANCE SHEET'!E37 -> 0 | C21: Debt bridge | D21: Zero per source
A22: Equity Value 100% - EEM | B22: =B20+B11-B21 -> 1.9886438e+10 | C22: EV + non-operating assets - debt | D22: No DLOM/DLOC

Sheet STAT_DCF
A1: DCF - Commercial Statutory 22% FCFF
A3: Line Item | B3: 2021A | C3: 2022E | D3: 2023E | E3: 2024E | F3: 2025E | G3: 2026E
A4: Period | B4: 0 | C4: 1 | D4: 2 | E4: 3 | F4: 4 | G4: 5
A5: Revenue | B5: ='INCOME STATEMENT'!E6 -> 16663916100 | C5: =B5*(1+STAT_ASSUMPTIONS!$B$9) -> 2.0456242e+10 | D5: =C5*(1+STAT_ASSUMPTIONS!$B$9) -> 2.5111616e+10 | E5: =D5*(1+STAT_ASSUMPTIONS!$B$9) -> 3.0826445e+10 | F5: =E5*(1+STAT_ASSUMPTIONS!$B$9) -> 3.784184e+10 | G5: =F5*(1+STAT_ASSUMPTIONS!$B$9) -> 4.6453777e+10
A6: Revenue growth | C6: =C5/B5-1 -> 0.22757714 | D6: =D5/C5-1 -> 0.22757714 | E6: =E5/D5-1 -> 0.22757714 | F6: =F5/E5-1 -> 0.22757714 | G6: =G5/F5-1 -> 0.22757714
A7: COGS % revenue | B7: =-'INCOME STATEMENT'!J7 -> 0.68239332 | C7: =$B$7 -> 0.68239332 | D7: =$B$7 -> 0.68239332 | E7: =$B$7 -> 0.68239332 | F7: =$B$7 -> 0.68239332 | G7: =$B$7 -> 0.68239332
A8: COGS | B8: =B5*B7 -> 1.1371345e+10 | C8: =C5*C7 -> 1.3959203e+10 | D8: =D5*D7 -> 1.7135999e+10 | E8: =E5*E7 -> 2.1035761e+10 | F8: =F5*F7 -> 2.5823019e+10 | G8: =G5*G7 -> 3.1699748e+10
A9: G&A % revenue | B9: =-'INCOME STATEMENT'!J13 -> 0.15644218 | C9: =$B$9 -> 0.15644218 | D9: =$B$9 -> 0.15644218 | E9: =$B$9 -> 0.15644218 | F9: =$B$9 -> 0.15644218 | G9: =$B$9 -> 0.15644218
A10: G&A expense | B10: =B5*B9 -> 2.6069394e+09 | C10: =C5*C9 -> 3.2002192e+09 | D10: =D5*D9 -> 3.928516e+09 | E10: =E5*E9 -> 4.8225564e+09 | F10: =F5*F9 -> 5.92006e+09 | G10: =G5*G9 -> 7.2673303e+09
A11: D&A % revenue | B11: =AVERAGE(-'INCOME STATEMENT'!C21/'INCOME STATEMENT'!C6,-'INCOME STATEMENT'!D21/'INCOME STATEMENT'!D6,-'INCOME STATEMENT'!E21/'INCOME STATEMENT'!E6) -> 0.065011476 | C11: =$B$11 -> 0.065011476 | D11: =$B$11 -> 0.065011476 | E11: =$B$11 -> 0.065011476 | F11: =$B$11 -> 0.065011476 | G11: =$B$11 -> 0.065011476
A12: Depreciation | B12: =B5*B11 -> 1.0833458e+09 | C12: =C5*C11 -> 1.3298905e+09 | D12: =D5*D11 -> 1.6325432e+09 | E12: =E5*E11 -> 2.0040727e+09 | F12: =F5*F11 -> 2.4601538e+09 | G12: =G5*G11 -> 3.0200286e+09
A13: EBIT | B13: =B5-B8-B10-B12 -> 1.6022858e+09 | C13: =C5-C8-C10-C12 -> 1.9669295e+09 | D13: =D5-D8-D10-D12 -> 2.4145577e+09 | E13: =E5-E8-E10-E12 -> 2.9640558e+09 | F13: =F5-F8-F10-F12 -> 3.6386072e+09 | G13: =G5-G8-G10-G12 -> 4.466671e+09
A14: Statutory tax rate | B14: =STAT_ASSUMPTIONS!$B$5 -> 0.22 | C14: =$B$14 -> 0.22 | D14: =$B$14 -> 0.22 | E14: =$B$14 -> 0.22 | F14: =$B$14 -> 0.22 | G14: =$B$14 -> 0.22
A15: NOPLAT | B15: =B13*(1-B14) -> 1.249783e+09 | C15: =C13*(1-C14) -> 1.534205e+09 | D15: =D13*(1-D14) -> 1.883355e+09 | E15: =E13*(1-E14) -> 2.3119635e+09 | F15: =F13*(1-F14) -> 2.8381136e+09 | G15: =G13*(1-G14) -> 3.4840034e+09
A16: AR days | B16: =AVERAGE('BALANCE SHEET'!C10/'INCOME STATEMENT'!C6*365,'BALANCE SHEET'!D10/'INCOME STATEMENT'!D6*365,'BALANCE SHEET'!E10/'INCOME STATEMENT'!E6*365) -> 11.83839 | C16: =$B$16 -> 11.83839 | D16: =$B$16 -> 11.83839 | E16: =$B$16 -> 11.83839 | F16: =$B$16 -> 11.83839 | G16: =$B$16 -> 11.83839
A17: Inventory days | B17: =AVERAGE(IFERROR('BALANCE SHEET'!C12/-'INCOME STATEMENT'!C7*365,0),IFERROR('BALANCE SHEET'!D12/-'INCOME STATEMENT'!D7*365,0),IFERROR('BALANCE SHEET'!E12/-'INCOME STATEMENT'!E7*365,0)) -> 0 | C17: =$B$17 -> 0 | D17: =$B$17 -> 0 | E17: =$B$17 -> 0 | F17: =$B$17 -> 0 | G17: =$B$17 -> 0
A18: AP days | B18: =AVERAGE('BALANCE SHEET'!C31/-'INCOME STATEMENT'!C7*365,'BALANCE SHEET'!D31/-'INCOME STATEMENT'!D7*365,'BALANCE SHEET'!E31/-'INCOME STATEMENT'!E7*365) -> 56.055219 | C18: =$B$18 -> 56.055219 | D18: =$B$18 -> 56.055219 | E18: =$B$18 -> 56.055219 | F18: =$B$18 -> 56.055219 | G18: =$B$18 -> 56.055219
A19: Other payable days | B19: =AVERAGE('BALANCE SHEET'!C33/-'INCOME STATEMENT'!C13*365,'BALANCE SHEET'!D33/-'INCOME STATEMENT'!D13*365,'BALANCE SHEET'!E33/-'INCOME STATEMENT'!E13*365) -> 103.46552 | C19: =$B$19 -> 103.46552 | D19: =$B$19 -> 103.46552 | E19: =$B$19 -> 103.46552 | F19: =$B$19 -> 103.46552 | G19: =$B$19 -> 103.46552
A20: Account receivable | B20: ='BALANCE SHEET'!E10 -> 191055111 | C20: =C5*C16/365 -> 6.6347667e+08 | D20: =D5*D16/365 -> 8.144688e+08 | E20: =E5*E16/365 -> 9.9982328e+08 | F20: =F5*F16/365 -> 1.2273602e+09 | G20: =G5*G16/365 -> 1.5066793e+09
A21: Inventory | B21: ='BALANCE SHEET'!E12 -> 0 | C21: =C8*C17/365 -> 0 | D21: =D8*D17/365 -> 0 | E21: =E8*E17/365 -> 0 | F21: =F8*F17/365 -> 0 | G21: =G8*G17/365 -> 0
A22: Account payable | B22: ='BALANCE SHEET'!E31 -> 1823364600 | C22: =C8*C18/365 -> 2.1437978e+09 | D22: =D8*D18/365 -> 2.6316772e+09 | E22: =E8*E18/365 -> 3.2305867e+09 | F22: =F8*F18/365 -> 3.9657944e+09 | G22: =G8*G18/365 -> 4.8683186e+09
A23: Other payable | B23: ='BALANCE SHEET'!E33 -> 1075354928 | C23: =C10*C19/365 -> 9.0715707e+08 | D23: =D10*D19/365 -> 1.1136053e+09 | E23: =E10*E19/365 -> 1.3670364e+09 | F23: =F10*F19/365 -> 1.6781426e+09 | G23: =G10*G19/365 -> 2.0600495e+09
A24: Operating NWC | B24: =B20+B21-B22-B23 -> -2707664417 | C24: =C20+C21-C22-C23 -> -2.3874782e+09 | D24: =D20+D21-D22-D23 -> -2.9308137e+09 | E24: =E20+E21-E22-E23 -> -3.5977998e+09 | F24: =F20+F21-F22-F23 -> -4.4165768e+09 | G24: =G20+G21-G22-G23 -> -5.4216888e+09
A25: Change in NWC | C25: =C24-B24 -> 3.2018623e+08 | D25: =D24-C24 -> -5.4333546e+08 | E25: =E24-D24 -> -6.6698619e+08 | F25: =F24-E24 -> -8.18777e+08 | G25: =G24-F24 -> -1.0051119e+09
A26: D&A add-back | B26: =B12 -> 1.0833458e+09 | C26: =C12 -> 1.3298905e+09 | D26: =D12 -> 1.6325432e+09 | E26: =E12 -> 2.0040727e+09 | F26: =F12 -> 2.4601538e+09 | G26: =G12 -> 3.0200286e+09
A27: Maintenance capex | B27: =B12 -> 1.0833458e+09 | C27: =C12 -> 1.3298905e+09 | D27: =D12 -> 1.6325432e+09 | E27: =E12 -> 2.0040727e+09 | F27: =F12 -> 2.4601538e+09 | G27: =G12 -> 3.0200286e+09
A28: Free Cash Flow | B28: =B15+B26-B27 -> 1.249783e+09 | C28: =C15+C26-C27-C25 -> 1.2140188e+09 | D28: =D15+D26-D27-D25 -> 2.4266904e+09 | E28: =E15+E26-E27-E25 -> 2.9789497e+09 | F28: =F15+F26-F27-F25 -> 3.6568906e+09 | G28: =G15+G26-G27-G25 -> 4.4891153e+09
A29: Discount factor | C29: =1/(1+$B$31)^C4 -> 0.8971582 | D29: =1/(1+$B$31)^D4 -> 0.80489283 | E29: =1/(1+$B$31)^E4 -> 0.72211621 | F29: =1/(1+$B$31)^F4 -> 0.64785247 | G29: =1/(1+$B$31)^G4 -> 0.58122616
A30: PV FCF | C30: =C28*C29 -> 1.0891669e+09 | D30: =D28*D29 -> 1.9532257e+09 | E30: =E28*E29 -> 2.1511479e+09 | F30: =F28*F29 -> 2.3691256e+09 | G30: =G28*G29 -> 2.6091912e+09
A31: WACC | B31: =STAT_ASSUMPTIONS!B6 -> 0.11463062
A32: Terminal growth | B32: =STAT_ASSUMPTIONS!B8 -> 0
A33: PV explicit FCF | B33: =SUM(C30:G30) -> 1.0171857e+10
A34: Terminal value | B34: =G28*(1+B32)/(B31-B32) -> 3.9161572e+10
A35: PV terminal value | B35: =B34/(1+B31)^G4 -> 2.276173e+10
A36: Enterprise value | B36: =B33+B35 -> 3.2933587e+10
A37: Non-operating assets | B37: =STAT_EEM!B11 -> 1075880526
A38: Interest-bearing debt | B38: =STAT_EEM!B21 -> 0
A39: Equity Value 100% - DCF | B39: =B36+B37-B38 -> 3.4009468e+10

Sheet STAT_SENS
A1: Sensitivity and Cross-Checks
A3: DCF sensitivity - with operating WC days
A4: Terminal Growth | B4: Source WACC | C4: Corrected WACC Sensitivity
